Workbook
Name ____________HOB1: #REF!
Name ___________HOB1: #REF!
Name __________HOB1: #REF!
Name _________HOB1: #REF!
Name ________HOB1: #REF!
Name _______HOB1: #REF!
Name ______HOB1: #REF!
Name _____HOB1: #REF!
Name ____HOB1: #REF!
Name ___HOB1: #REF!
Name __C100000: #REF!
Name __C608550: #REF!
Name __C90000: #REF!
Name __Cpe111: #REF!
Name __Cpe112: #REF!
Name __Cpe113: #REF!
Name __Cpe114: #REF!
Name __Cpe115: #REF!
Name __Cpe116: #REF!
Name __Cpe118: #REF!
Name __Cpe119: #REF!
Name __Cpe131: #REF!
Name __Cpe135: #REF!
Name __Cpe141: #REF!
Name __Cpe148: #REF!
Name __Cpe151: #REF!
Name __Cpe155: #REF!
Name __Cpe160: #REF!
Name __Cpe171: #REF!
Name __Cpe172: #REF!
Name __Cpe211: #REF!
Name __Cpe212: #REF!
Name __Cpe213: #REF!
Name __Cpe221: #REF!
Name __Cpe222: #REF!
Name __Cpe223: #REF!
Name __Cpe228: #REF!
Name __Cpe231: #REF!
Name __Cpe232: #REF!
Name __Cpe233: #REF!
Name __Cpe234: #REF!
Name __Cpe235: #REF!
Name __Cpe238: #REF!
Name __Cpe239: #REF!
Name __Cpe241: #REF!
Name __Cpe248: #REF!
Name __Cpe251: #REF!
Name __Cpe258: #REF!
Name __Cpe271: #REF!
Name __Cpe272: #REF!
Name __Cpe281: #REF!
Name __Cpe282: #REF!
Name __Cpe283: #REF!
Name __Cpe292: #REF!
Name __Cpe293: #REF!
Name __Cpe294: #REF!
Name __Cpe295: #REF!
Name __Cpe311: #REF!
Name __Cpe312: #REF!
Name __Cpe313: #REF!

Sheet Hyp 2027
A1: HYPOTHESES 2027 - seule zone de saisie du modele | B1: =B9+(B9/$J$9)*$M$5 -> 4.5149631e+09 | C1: =C9+(C9/$J$9)*$M$5 -> 3.4850173e+09 | D1: =D9+(D9/$J$9)*$M$5 -> 53048948 | E1: =E9+(E9/$J$9)*$M$5 -> 5.9627164e+09 | F1: =F9+(F9/$J$9)*$M$5 -> 6.0608194e+08 | G1: =G9+(G9/$J$9)*$M$5 -> 8.987445e+08 | H1: =H9+(H9/$J$9)*$M$5 -> 8.685728e+08 | I1: =I9+(I9/$J$9)*$M$5 -> 1.6740804e+09
A2: Bleu = saisie (fichiers M01-M06 et SAZ Marge Tech FORECAST.xlsx) | Noir = formule | B2: =(B12/$J$12)*$L$11+B12 -> 5.4545011e+09 | C2: =(C11/$J$11)*$L$11+C11 -> 3.4783853e+09 | D2: =(D11/$J$11)*$L$11+D11 -> 64062804 | E2: =(E11/$J$11)*$L$11+E11 -> 6.3107771e+09 | F2: =(F11/$J$11)*$L$11+F11 -> 5.9281545e+08 | G2: =(G11/$J$11)*$L$11+G11 -> 9.0604974e+08 | H2: =(H11/$J$11)*$L$11+H11 -> 8.6150106e+08 | I2: =(I11/$J$11)*$L$11+I11 -> 1.7141771e+09 | J2: =SUM(B2:I2) -> 1.938227e+10
A3: DIRECT 2026 YTD (fichiers M01-M06) | B3: Motor | C3: Health | D3: Worker injury | E3: Fire | F3: Engineering | G3: Liability | H3: Miscellaneous | I3: Transport | J3: Total | O3: Motor | P3: Health | Q3: Worker injury | R3: Fire | S3: Engineering | T3: Liability | U3: Miscellaneous | V3: Transport
A5: Primes emises M01 | B5: 1.9545379e+09 | C5: 1.88643e+09 | D5: 8614310.8 | E5: 7.4610775e+08 | F5: 1.0837485e+08 | G5: 39441442 | H5: 3.5224116e+08 | I5: 16638269 | J5: =SUM(B5:I5) -> 5.1123857e+09 | K5: =5542385658 -> 5542385658 | L5: =K5-J5 -> 4.3e+08 | M5: 1500000000
A6: Primes emises M02 | B6: 2.4105843e+09 | C6: 2.2056225e+09 | D6: 25094566 | E6: 2.3201667e+09 | F6: 2.7718729e+08 | G6: 2.0909543e+08 | H6: 4.8835035e+08 | I6: 1.0230056e+09 | J6: =SUM(B6:I6) -> 8959106785 | K6: 8759106785 | L6: =K6-J6 -> -200000000 | O6: =B6>B5 -> TRUE | P6: =C6>C5 -> TRUE | Q6: =D6>D5 -> TRUE | R6: =E6>E5 -> TRUE | S6: =F6>F5 -> TRUE | T6: =G6>G5 -> TRUE | U6: =H6>H5 -> TRUE | V6: =I6>I5 -> TRUE
A7: Primes emises M03 | B7: 2.8687888e+09 | C7: 2.5569658e+09 | D7: 25814243 | E7: =2392440950.21417+1500000000 -> 3.892441e+09 | F7: 3.6386719e+08 | G7: 2.3796607e+08 | H7: =697612996.267642-100000000 -> 5.97613e+08 | I7: 1.1210727e+09 | J7: =SUM(B7:I7) -> 1.1664529e+10 | K7: 10264528782 | L7: =K7-J7 -> -1.4e+09 | O7: =B7>B6 -> TRUE | P7: =C7>C6 -> TRUE | Q7: =D7>D6 -> TRUE | R7: =E7>E6 -> TRUE | S7: =F7>F6 -> TRUE | T7: =G7>G6 -> TRUE | U7: =H7>H6 -> TRUE | V7: =I7>I6 -> TRUE
A8: Primes emises M04 | B8: 3.0831911e+09 | C8: =2567548952.1017+200000000 -> 2.767549e+09 | D8: =25748616.4745879+10000000 -> 35748616 | E8: 5.1439292e+09 | F8: 4.4951478e+08 | G8: 6.9718804e+08 | H8: 6.874981e+08 | I8: 1.1348398e+09 | J8: =SUM(B8:I8) -> 1.3999459e+10 | K8: 15289458632 | L8: =K8-J8 -> 1.29e+09 | O8: =B8>B7 -> TRUE | P8: =C8>C7 -> TRUE | Q8: =D8>D7 -> TRUE | R8: =E8>E7 -> TRUE | S8: =F8>F7 -> TRUE | T8: =G8>G7 -> TRUE | U8: =H8>H7 -> TRUE | V8: =I8>I7 -> TRUE
A9: Primes emises M05 | B9: 4.1400331e+09 | C9: 3.1956157e+09 | D9: 48643676 | E9: =6167562601.13338-700000000 -> 5.4675626e+09 | F9: 5.5575189e+08 | G9: =874111273.352422-50000000 -> 8.2411127e+08 | H9: =896445087.426672-100000000 -> 7.9644509e+08 | I9: 1.535062e+09 | J9: =SUM(B9:I9) -> 1.6563225e+10 | K9: 16113854026 | L9: =K9-J9 -> -4.4937128e+08 | O9: =B9>B8 -> TRUE | P9: =C9>C8 -> TRUE | Q9: =D9>D8 -> TRUE | R9: =E9>E8 -> TRUE | S9: =F9>F8 -> TRUE | T9: =G9>G8 -> TRUE | U9: =H9>H8 -> TRUE | V9: =I9>I8 -> TRUE
A10: Primes emises M06 | B10: =4068649041.64682+200000000+200000000 -> 4.468649e+09 | C10: =2927804903.89432+400000000 -> 3.3278049e+09 | D10: 60891855 | E10: 6.2965674e+09 | F10: 5.6600044e+08 | G10: 8.7411127e+08 | H10: =896445087.426672-60000000 -> 8.3644509e+08 | I10: 1.633055e+09 | J10: =SUM(B10:I10) -> 1.8063525e+10 | K10: 17187985458 | L10: =K10-J10 -> -8.7553955e+08 | O10: =B10>B9 -> TRUE | P10: =C10>C9 -> TRUE | Q10: =D10>D9 -> TRUE | R10: =E10>E9 -> TRUE | S10: =F10>F9 -> TRUE | T10: =G10>G9 -> TRUE | U10: =H10>H9 -> TRUE | V10: =I10>I9 -> TRUE
A11: Primes emises M07 | B11: =4569040691.11808+200000000 -> 4.7690407e+09 | C11: =3223456698.09457+300000000 -> 3.5234567e+09 | D11: 64892902 | E11: 6.3925494e+09 | F11: 6.0049689e+08 | G11: 9.1778994e+08 | H11: 8.7266401e+08 | I11: 1736388630 | J11: =SUM(B11:I11) -> 1.8877279e+10 | K11: 18635804603 | L11: =K11-J11 -> -2.4147459e+08 | O11: =B11>B10 -> TRUE | P11: =C11>C10 -> TRUE | Q11: =D11>D10 -> TRUE | R11: =E11>E10 -> TRUE | S11: =F11>F10 -> TRUE | T11: =G11>G10 -> TRUE | U11: =H11>H10 -> TRUE | V11: =I11>I10 -> TRUE
A12: Primes emises M08 (2025) | B12: 5516071353 | C12: 3704847289 | D12: 65279929 | E12: 6498115245 | F12: 688956997 | G12: 2433459825 | H12: 904690916 | I12: 1.8222483e+09 | J12: =SUM(B12:I12) -> 2.163367e+10 | L12: =K12-J12 -> -2.163367e+10 | O12: =B12>B11 -> TRUE | P12: =C12>C11 -> TRUE | Q12: =D12>D11 -> TRUE | R12: =E12>E11 -> TRUE | S12: =F12>F11 -> TRUE | T12: =G12>G11 -> TRUE | U12: =H12>H11 -> TRUE | V12: =I12>I11 -> TRUE
A13: Primes emises M09 | B13: 5851081097 | C13: 3876660359 | D13: 66922967 | E13: 6891818224 | F13: 692645455 | G13: 2898741452 | H13: 9.3132971e+08 | I13: 1957192660 | J13: =SUM(B13:I13) -> 2.3166392e+10 | L13: =K13-J13 -> -2.3166392e+10 | O13: =B13>B12 -> TRUE | P13: =C13>C12 -> TRUE | Q13: =D13>D12 -> TRUE | R13: =E13>E12 -> TRUE | S13: =F13>F12 -> TRUE | T13: =G13>G12 -> TRUE | U13: =H13>H12 -> TRUE | V13: =I13>I12 -> TRUE
A14: Primes emises M10 | B14: 6.2599616e+09 | C14: 4148277719 | D14: 70127240 | E14: 7.1844536e+09 | F14: 7.0207769e+08 | G14: 2949978253 | H14: 1000090510 | I14: 2095028158 | J14: =SUM(B14:I14) -> 2.4409995e+10 | L14: =K14-J14 -> -2.4409995e+10 | O14: =B14>B13 -> TRUE | P14: =C14>C13 -> TRUE | Q14: =D14>D13 -> TRUE | R14: =E14>E13 -> TRUE | S14: =F14>F13 -> TRUE | T14: =G14>G13 -> TRUE | U14: =H14>H13 -> TRUE | V14: =I14>I13 -> TRUE
A15: Primes emises M11 | B15: 6657885305 | C15: 4342479221 | D15: 72768637 | E15: 7302571869 | F15: 740428992 | G15: 3060788157 | H15: 1173135828 | I15: 2286613640 | J15: =SUM(B15:I15) -> 25636671649 | L15: =K15-J15 -> -25636671649 | O15: =B15>B14 -> TRUE | P15: =C15>C14 -> TRUE | Q15: =D15>D14 -> TRUE | R15: =E15>E14 -> TRUE | S15: =F15>F14 -> TRUE | T15: =G15>G14 -> TRUE | U15: =H15>H14 -> TRUE | V15: =I15>I14 -> TRUE
A16: Primes emises M12 | B16: 6963552336 | C16: 4396984788 | D16: 77934224 | E16: 7485337118 | F16: 793216278 | G16: 3121991319 | H16: 1211281670 | I16: 2364392134 | J16: =SUM(B16:I16) -> 26414689867 | L16: =K16-J16 -> -26414689867 | O16: =B16>B15 -> TRUE | P16: =C16>C15 -> TRUE | Q16: =D16>D15 -> TRUE | R16: =E16>E15 -> TRUE | S16: =F16>F15 -> TRUE | T16: =G16>G15 -> TRUE | U16: =H16>H15 -> TRUE | V16: =I16>I15 -> TRUE
L17: =K17-J17 -> 0
A19: Sinistres payes Per. M01 | B19: 949634 | C19: 463425 | D19: 0 | E19: 0 | F19: 0 | G19: 0 | H19: 0 | I19: -3089000
A20: Sinistres payes Per. M02 | B20: 2192777 | C20: 14632418 | D20: 0 | E20: 0 | F20: 0 | G20: 0 | H20: 0 | I20: 330000
A21: Sinistres payes Per. M03 | B21: 10974365 | C21: 141758782 | D21: 0 | E21: 0 | F21: 0 | G21: 0 | H21: 0 | I21: 3762494
A22: Sinistres payes Per. M04 | B22: 55301048 | C22: 317091145 | D22: 0 | E22: 0 | F22: 0 | G22: 444050 | H22: 0 | I22: 12463598 | K22: 9.3132971e+08
A23: Sinistres payes Per. M05 | B23: 95344622 | C23: 604911137 | D23: 0 | E23: 0 | F23: 0 | G23: 829050 | H23: 0 | I23: 14164104 | K23: 1000090510
A24: Sinistres payes Per. M06 | B24: 146149062 | C24: 839203521 | D24: 0 | E24: 550999 | F24: 0 | G24: 954050 | H24: 0 | I24: 94382038 | K24: 1173135828
A25: Sinistres payes Per. M07 | B25: 211016709 | C25: 1072120441 | D25: 0 | E25: 600999 | F25: 0 | G25: 1369882 | H25: 0 | I25: 94926410
A26: Sinistres payes Per. M08 (2025) | B26: 3.1000322e+08 | C26: 1292606030 | D26: 0 | E26: 32359188 | F26: 656218 | G26: 0 | H26: 0 | I26: 107013568
A27: Sinistres payes Per. M09 | B27: 3.9851989e+08 | C27: 1535820319 | D27: 0 | E27: 33170472 | F27: 656218 | G27: 0 | H27: 0 | I27: 116236704
A28: Sinistres payes Per. M10 | B28: 5.5058135e+08 | C28: 1805140581 | D28: 0 | E28: 43782290 | F28: 656218 | G28: 0 | H28: 0 | I28: 130998797
A29: Sinistres payes Per. M11 | B29: 6.784687e+08 | C29: 2080986023 | D29: 0 | E29: 50117618 | F29: 4218680 | G29: 1389287 | H29: 0 | I29: 173479878
A30: Sinistres payes Per. M12 | B30: 7.5118785e+08 | C30: 2082958327 | D30: 0 | E30: 661074779 | F30: 7511861 | G30: 1389287 | H30: 0 | I30: 707705435
A32: Sinistres payes Ant. M01 | B32: 239790513 | C32: 543859743 | D32: 0 | E32: 32114472 | F32: 1517222 | G32: 57060000 | H32: 0 | I32: 7300000
A33: Sinistres payes Ant. M02 | B33: 548926130 | C33: 777327039 | D33: 0 | E33: 93435634 | F33: 1517222 | G33: 80540705 | H33: 0 | I33: 25559022
A34: Sinistres payes Ant. M03 | B34: 711990944 | C34: 922709764 | D34: 0 | E34: 133368400 | F34: 1517222 | G34: 82655330 | H34: 0 | I34: 17115528
A35: Sinistres payes Ant. M04 | B35: 1032616588 | C35: 1022151662 | D35: 0 | E35: 417365766 | F35: 2396324 | G35: 73550013 | H35: 248734 | I35: 58410334
A36: Sinistres payes Ant. M05 | B36: 1143280554 | C36: 1034722223 | D36: 0 | E36: 499444317 | F36: 4850950 | G36: 81527291 | H36: 2605526 | I36: 132805300
A37: Sinistres payes Ant. M06 | B37: 1338652150 | C37: 1037476740 | D37: 0 | E37: 505479166 | F37: 12354273 | G37: 81961786 | H37: 2615526 | I37: 202559309
... A76: Variation REC M12 | B76: -27758870 | C76: -61681095 | D76: 2206525 | E76: -3.1399389e+08 | F76: -2.0583621e+08 | G76: -1.3588032e+08 | H76: -2.1866166e+08 | I76: -71053474
A78: REASS 2026 YTD (fichiers M01-M06) | B78: Motor | C78: Health | D78: Worker injury | E78: Fire | F78: Engineering | G78: Liability | H78: Miscellaneous | I78: Transport
A79: Primes cedees M01 | B79: 83266640 | C79: 19654609 | D79: 226891.52 | E79: 4.8145194e+08 | F79: 2.209327e+08 | G79: 29555088 | H79: 1.2694383e+08 | I79: 5921901.6
A80: Primes cedees M02 | B80: 65366210 | C80: 49823447 | D80: 638518.95 | E80: 1.2526641e+09 | F80: 82436581 | G80: 65504427 | H80: 3.0696606e+08 | I80: 2.3814546e+08
A81: Primes cedees M03 | B81: 93115430 | C81: 65604928 | D81: 687950.82 | E81: 1.3664674e+09 | F81: 2.8694842e+08 | G81: 68328031 | H81: 4.0521064e+08 | I81: 2.8232789e+08
A82: Primes cedees M04 | B82: 1.1506391e+08 | C82: 81138031 | D82: 724945.38 | E82: 4.3421475e+09 | F82: 3.2476051e+08 | G82: 4.3999423e+08 | H82: 4.4129593e+08 | I82: 2.9927304e+08
A83: Primes cedees M05 | B83: 1.2358216e+08 | C83: 96638728 | D83: 1609675.9 | E83: 3.8859075e+09 | F83: 3.2953303e+08 | G83: 4.4993549e+08 | H83: 4.6691284e+08 | I83: 3.2845738e+08
A84: Primes cedees M06 | B84: 1.4328928e+08 | C84: 1.1483535e+08 | D84: 1667525.4 | E84: 4.5462543e+09 | F84: 3.6280023e+08 | G84: 5.2740277e+08 | H84: 4.7865237e+08 | I84: 4.5747943e+08
A85: Primes cedees M07 | B85: 1.5919099e+08 | C85: 1.3165053e+08 | D85: 1732051.5 | E85: 4.5603853e+09 | F85: 3.721365e+08 | G85: 5.276048e+08 | H85: 5.0432851e+08 | I85: 5.1120481e+08
A86: Primes cedees M08 (2025) | B86: 1.6668502e+08 | C86: 1.3694725e+08 | D86: 2035547.5 | E86: 4.0523661e+09 | F86: 2.9386379e+08 | G86: 2.1908707e+09 | H86: 4.1217403e+08 | I86: 5.5173307e+08
A87: Primes cedees M09 | B87: 227501746 | C87: 1.4596402e+08 | D87: 4207281 | E87: 5485752056 | F87: 315810690 | G87: 2516289896 | H87: 410541051 | I87: 694422496
A88: Primes cedees M10 | B88: #VALUE! | C88: 65604928 | D88: 687950.82 | E88: 1.3664674e+09 | F88: 2.8694842e+08 | G88: 68328031 | H88: 4.0521064e+08 | I88: 2.8232789e+08
A89: Primes cedees M11 | B89: 1.5919099e+08 | C89: 81138031 | D89: 724945.38 | E89: 4.3421475e+09 | F89: 3.2476051e+08 | G89: 4.3999423e+08 | H89: 4.4129593e+08 | I89: 2.9927304e+08
A90: Primes cedees M12 | B90: 1.5919099e+08 | C90: 96638728 | D90: 1609675.9 | E90: 3.8859075e+09 | F90: 3.2953303e+08 | G90: 4.4993549e+08 | H90: 4.6691284e+08 | I90: 3.2845738e+08
A92: Sinistres payes Per. M01 | B92: 130000000 | C92: 0 | D92: 0 | E92: -66475.833 | F92: 0 | G92: 0 | H92: 0 | I92: -78017870
A93: Sinistres payes Per. M02 | B93: 136128 | C93: 0 | D93: 0 | E93: 0 | F93: 0 | G93: 0 | H93: 0 | I93: 7425
A94: Sinistres payes Per. M03 | B94: 136128 | C94: 0 | D94: 0 | E94: 0 | F94: 0 | G94: 0 | H94: 84656.115 | I94: 0
A95: Sinistres payes Per. M04 | B95: 1011929 | C95: 0 | D95: 0 | E95: 0 | F95: 0 | G95: 9991.125 | H95: 0 | I95: 270317.34
A96: Sinistres payes Per. M05 | B96: 1011929 | C96: 0 | D96: 0 | E96: 0 | F96: 0 | G96: 18654 | H96: 0 | I96: 318692
A97: Sinistres payes Per. M06 | B97: 0 | C97: 0 | D97: 0 | E97: 12397.478 | F97: 0 | G97: 21466.125 | H97: 0 | I97: 2123595.9
A98: Sinistres payes Per. M07 | B98: 0 | C98: 2139111 | D98: 0 | E98: 13522.478 | F98: 0 | G98: 30822.345 | H98: 11250 | I98: 2135844.2
A99: Sinistres payes Per. M08 (2025) | B99: 130000000 | C99: 0 | D99: 0 | E99: -66475.833 | F99: 0 | G99: 0 | H99: 0 | I99: -78017870
A100: Sinistres payes Per. M09 | B100: 136128 | C100: 0 | D100: 0 | E100: 0 | F100: 0 | G100: 0 | H100: 0 | I100: 7425
A101: Sinistres payes Per. M10 | B101: 136128 | C101: 0 | D101: 0 | E101: 0 | F101: 0 | G101: 0 | H101: 84656.115 | I101: 0
... A142: REC Cloture M12 | B142: 25445466 | C142: 0 | D142: 427854.6 | E142: 1.2041145e+08 | F142: 34077911 | G142: 5361135.5 | H142: 6342166.8 | I142: 9895141.8
A146: 2026 FY / CIBLE 2027 par LoB (SAZ Marge Tech FORECAST.xlsx - CPC SAZ Local) | B146: Motor | C146: Health | D146: Worker injury | E146: Fire | F146: Engineering | G146: Liability | H146: Miscellaneous | I146: Transport
A147: Primes 2026 FY | B147: 6963552336 | C147: 4396984788 | D147: 77934224 | E147: 7485337118 | F147: 793216278 | G147: 3121991319 | H147: 1211281670 | I147: 2364392134 | J147: =SUM(B147:I147) -> 26414689867
A148: Primes 2027 cible | B148: 7.3631081e+09 | C148: 4.3768737e+09 | D148: 90955409 | E148: 8.9291791e+09 | F148: 9.3111724e+08 | G148: 2.2159648e+09 | H148: 2.4291132e+09 | I148: 2.8492332e+09 | J148: =SUM(B148:I148) -> 2.9185545e+10
A149: Sinistres payés Per. 2026 FY | B149: 751261000 | C149: 1.6291444e+09 | D149: 0 | E149: 510074000 | F149: 0 | G149: 5125000 | H149: 11362000 | I149: 701214000
A150: Sinistres payés Per. 2027 cible | B150: 8.758429e+08 | C150: 1.7211324e+09 | D150: 0 | E150: 6.8673507e+08 | F150: 0 | G150: 2101104.7 | H150: 15647616 | I150: 7.8096159e+08
A151: Sinistres payés Ant.2026 FY | B151: 2025211000 | C151: 1.1806529e+09 | D151: 0 | E151: 2201251000 | F151: 12354273 | G151: 174529000 | H151: 11770727 | I151: 221521000
A152: Sinistres payés Ant. 2027 cible | B152: 1.8279451e+09 | C152: 1.1364905e+09 | D152: 0 | E152: 3299675249 | F152: 16048201 | G152: 1.8290628e+08 | H152: 17644320 | I152: 2.9027191e+08
A153: Commissions 2026 FY | B153: 1.1385559e+09 | C153: 5.6877869e+08 | D153: 17323115 | E153: 1.0305258e+09 | F153: 1.0038341e+08 | G153: 2.0995857e+08 | H153: 2.8715247e+08 | I153: 4.8029452e+08
A154: Commissions 2027 cible | B154: 1.3424177e+09 | C154: 6.3810494e+08 | D154: 21104246 | E154: 1.2064072e+09 | F154: 1.2425175e+08 | G154: 2.8200432e+08 | H154: 3.5542921e+08 | I154: 5.3334201e+08
A156: REASS Primes cedees 2026 FY | B156: 2.6125045e+08 | C156: 1.8735719e+08 | D156: 2313826 | E156: 6.4192319e+09 | F156: 5.2882858e+08 | G156: 1.1188845e+09 | H156: 1.1432307e+09 | I156: 8.2503405e+08
A157: REASS Primes cedees 2027 cible | B157: 2.504032e+08 | C157: 2.0013495e+08 | D157: 2718005.2 | E157: 6.953183e+09 | F157: 6.0258201e+08 | G157: 1.3819004e+09 | H157: 1.294348e+09 | I157: 8.3791327e+08
A158: REASS Sin. exercice 2026 FY | B158: 0 | C158: 3250493.8 | D158: 0 | E158: 11476665 | F158: 0 | G158: 115312.5 | H158: 0 | I158: 15777315
A159: REASS Sin. exercice 2027 cible | B159: 0 | C159: 3434029.6 | D159: 0 | E159: 15451539 | F159: 0 | G159: 47274.856 | H159: 0 | I159: 17571636
A160: REASS Sin. anterieurs 2026 FY | B160: 2.820928e+08 | C160: 1.090675e+08 | D160: 0 | E160: 2.0465381e+09 | F160: 11848147 | G160: 11384706 | H160: 11726736 | I160: 9611360.1
A161: REASS Sin. anterieurs 2027 cible | B161: 2.5461553e+08 | C161: 1.0498782e+08 | D161: 0 | E161: 2.5398125e+09 | F161: 15390744 | G161: 11931165 | H161: 17578378 | I161: 12594327
... A163: REASS Commissions 2027 cible | B163: 35478765 | C163: 33978796 | D163: 504247.33 | E163: 1.6045393e+09 | F163: 87619245 | G163: 3.0710054e+08 | H163: 1.8294578e+08 | I163: 79011036
A165: MULTIPLICATEURS k = cible 2027 / 2026 FY (par LoB)
A166: k Primes | B166: =B148/B147 -> 1.0573781 | C166: =C148/C147 -> 0.99542618 | D166: =D148/D147 -> 1.1670792 | E166: =E148/E147 -> 1.1928894 | F166: =F148/F147 -> 1.1738504 | G166: =G148/G147 -> 0.7097921 | H166: =H148/H147 -> 2.0054074 | I166: =I148/I147 -> 1.2050595
A167: k Sin. Per. | B167: =IFERROR(B150/B149,0) -> 1.1658304 | C167: =IFERROR(C150/C149,0) -> 1.056464 | D167: =IFERROR(D150/D149,0) -> 0 | E167: =IFERROR(E150/E149,0) -> 1.346344 | F167: =IFERROR(F150/F149,0) -> 0 | G167: =IFERROR(G150/G149,0) -> 0.40997165 | H167: =IFERROR(H150/H149,0) -> 1.3771885 | I167: =IFERROR(I150/I149,0) -> 1.1137279
A168: k Sin. Ant. | B168: =IFERROR(B152/B151,0) -> 0.90259491 | C168: =IFERROR(C152/C151,0) -> 0.96259491 | D168: =IFERROR(D152/D151,0) -> 0 | E168: =IFERROR(E152/E151,0) -> 1.499 | F168: =IFERROR(F152/F151,0) -> 1.299 | G168: =IFERROR(G152/G151,0) -> 1.0479993 | H168: =IFERROR(H152/H151,0) -> 1.499 | I168: =IFERROR(I152/I151,0) -> 1.3103584
A169: taux commission | B169: 0.18231671 | C169: 0.14579012 | D169: 0.23202849 | E169: 0.13510841 | F169: 0.13344372 | G169: 0.12726029 | H169: 0.14632056 | I169: 0.18718791
A171: REASS k Primes | B171: =B157/B156 -> 0.95847951 | C171: =C157/C156 -> 1.0682 | D171: =D157/D156 -> 1.17468 | E171: =E157/E156 -> 1.0831799 | F171: =F157/F156 -> 1.1394657 | G171: =G157/G156 -> 1.2350698 | H171: =H157/H156 -> 1.1321844 | I171: =I157/I156 -> 1.0156105
A172: REASS k Sin. Per. | B172: =IFERROR(B159/B158,0) -> 0 | C172: =IFERROR(C159/C158,0) -> 1.056464 | D172: =IFERROR(D159/D158,0) -> 0 | E172: =IFERROR(E159/E158,0) -> 1.346344 | F172: =IFERROR(F159/F158,0) -> 0 | G172: =IFERROR(G159/G158,0) -> 0.40997165 | H172: =IFERROR(H159/H158,0) -> 0 | I172: =IFERROR(I159/I158,0) -> 1.1137279
A173: REASS k Sin. Ant. | B173: =IFERROR(B161/B160,0) -> 0.90259491 | C173: =IFERROR(C161/C160,0) -> 0.96259491 | D173: =IFERROR(D161/D160,0) -> 0 | E173: =IFERROR(E161/E160,0) -> 1.2410287 | F173: =IFERROR(F161/F160,0) -> 1.299 | G173: =IFERROR(G161/G160,0) -> 1.0479993 | H173: =IFERROR(H161/H160,0) -> 1.499 | I173: =IFERROR(I161/I160,0) -> 1.3103584
A174: REASS taux commission 2026 | B174: 0.17 | C174: 0.15 | D174: 0.18552111 | E174: 0.15 | F174: 0.14540634 | G174: 0.28 | H174: 0.28 | I174: 0.19
A176: REC CLOTURE 2026 FY par branche (ancrage de l ouverture, fige toute l annee) | B176: Motor | C176: Health | D176: Worker injury | E176: Fire | F176: Engineering | G176: Liability | H176: Miscellaneous | I176: Transport
A177: Direct REC cloture 2026 FY | B177: 1.5613983e+09 | C177: 6.6162882e+08 | D177: 6179130.4 | E177: 36234141 | F177: 1.1343105e+08 | G177: 88631742 | H177: -24009431 | I177: 64790567
A178: Reass REC cloture 2026 FY | B178: 25537397 | C178: 0 | D178: 152186.19 | E178: 7395698.1 | F178: 29903133 | G178: 3710677.5 | H178: -1017129.5 | I178: 1889056.9
A179: Direct REC cloture 2027 FY | B179: 1.5613983e+09 | C179: 6.6162882e+08 | D179: 6179130.4 | E179: 36234141 | F179: 1.1343105e+08 | G179: 88631742 | H179: -24009431 | I179: 64790567
A180: Reass REC cloture 2027 FY | B180: 25537397 | C180: 0 | D180: 152186.19 | E180: 7395698.1 | F180: 29903133 | G180: 3710677.5 | H180: -1017129.5 | I180: 1889056.9
A182: 2025 RE/ CIBLE 2027 par LoB (SAZ Marge Tech FORECAST.xlsx - CPC SAZ Local) | B182: Motor | C182: Health | D182: Worker injury | E182: Fire | F182: Engineering | G182: Liability | H182: Miscellaneous | I182: Transport
A183: Primes 2025 FY | B183: 6.6973877e+09 | C183: 4.0974291e+09 | D183: 77429946 | E183: 8.0370649e+09 | F183: 7.9265607e+08 | G183: 1.7384479e+09 | H183: 2.0678936e+09 | I183: 2.6267961e+09
A184: Primes 2027 cible | B184: 7.3631081e+09 | C184: 4.3768737e+09 | D184: 90955409 | E184: 8.9291791e+09 | F184: 9.3111724e+08 | G184: 2.2159648e+09 | H184: 2.4291132e+09 | I184: 2.8492332e+09
A185: Sinistres payés Per. 2025 FY | B185: 751261000 | C185: 1.6291444e+09 | D185: 0 | E185: 510074000 | F185: 0 | G185: 5125000 | H185: 11362000 | I185: 701214000
A186: Sinistres payés Per. 2027 cible | B186: 8.758429e+08 | C186: 1.7211324e+09 | D186: 0 | E186: 6.8673507e+08 | F186: 0 | G186: 2101104.7 | H186: 15647616 | I186: 7.8096159e+08
A187: Sinistres payés Ant.2025 FY | B187: 2025211000 | C187: 1.1806529e+09 | D187: 0 | E187: 2201251000 | F187: 12354273 | G187: 174529000 | H187: 11770727 | I187: 221521000
A188: Sinistres payés Ant. 2027 cible | B188: 1.8279451e+09 | C188: 1.1364905e+09 | D188: 0 | E188: 3299675249 | F188: 16048201 | G188: 1.8290628e+08 | H188: 17644320 | I188: 2.9027191e+08
A189: Commissions 2025 FY | B189: 1.1385559e+09 | C189: 5.6877869e+08 | D189: 17323115 | E189: 1.0305258e+09 | F189: 1.0038341e+08 | G189: 2.0995857e+08 | H189: 2.8715247e+08 | I189: 4.8029452e+08
A190: Commissions 2027 cible | B190: 1.3424177e+09 | C190: 6.3810494e+08 | D190: 21104246 | E190: 1.2064072e+09 | F190: 1.2425175e+08 | G190: 2.8200432e+08 | H190: 3.5542921e+08 | I190: 5.3334201e+08
A192: REASS Primes cedees 2025 FY | B192: 2.6125045e+08 | C192: 1.8735719e+08 | D192: 2313826 | E192: 6.4192319e+09 | F192: 5.2882858e+08 | G192: 1.1188845e+09 | H192: 1.1432307e+09 | I192: 8.2503405e+08
A193: REASS Primes cedees 2027 cible | B193: 2.504032e+08 | C193: 2.0013495e+08 | D193: 2718005.2 | E193: 6.953183e+09 | F193: 6.0258201e+08 | G193: 1.3819004e+09 | H193: 1.294348e+09 | I193: 8.3791327e+08
...

Sheet Direct Local
A1: =87% -> 0.87 | B1: 0.18231671 | C1: 0.14579012 | D1: 0.23202849 | E1: 0.13510841 | F1: 0.13344372 | G1: 0.12726029 | H1: 0.14632056 | I1: 0.18718791
B2: 0.0994 | C2: 0.0682 | D2: 0.17468 | E2: 0.111 | F2: 0.17468 | G2: 0.27468 | H2: 0.17468 | I2: 0.08468 | EJ2: =43550000/12 -> 3629166.7 | EK2: =25375000/7 -> 3625000
B3: 2619580477 | C3: 1563144534 | D3: 7138040 | E3: 618244114 | F3: 446111277 | G3: 32682196 | H3: 291876106 | I3: 13786899
A4: Local GAAP | B4: SanlamAllianz LIC Tool | E4: 46388 | M4: SanlamAllianz LIC Tool | P4: 46419 | Y4: SanlamAllianz LIC Tool | AC4: 46447 | AK4: SanlamAllianz LIC Tool | AO4: 46478 | AW4: SanlamAllianz LIC Tool | BA4: 46508 | BI4: SanlamAllianz LIC Tool | BM4: 46539 | BU4: SanlamAllianz LIC Tool | BY4: 46569 | CG4: SanlamAllianz LIC Tool | CK4: Aout 27 | CS4: SanlamAllianz LIC Tool | CW4: 46631 | DE4: SanlamAllianz LIC Tool | DI4: 46661 | DQ4: SanlamAllianz LIC Tool | DU4: 46692 | EC4: SanlamAllianz LIC Tool | EG4: 46722
A5: F CFA | B5: Motor | C5: Health | D5: Worker injury | E5: Fire | F5: Engineering | G5: Liability | H5: Miscellaneous | I5: Transport | M5: Motor | N5: Health | O5: Worker injury | P5: Fire | Q5: Engineering | R5: Liability | S5: Miscellaneous | T5: Transport | Y5: Motor | Z5: Health | AA5: Worker injury | AB5: Fire | AC5: Engineering | AD5: Liability | AE5: Miscellaneous | AF5: Transport | AK5: Motor | AL5: Health | AM5: Worker injury | AN5: Fire | AO5: Engineering | AP5: Liability | AQ5: Miscellaneous | AR5: Transport | AW5: Motor | AX5: Health | AY5: Worker injury | AZ5: Fire | BA5: Engineering | BB5: Liability | BC5: Miscellaneous | BD5: Transport | BI5: Motor | BJ5: Health | BK5: Worker injury | BL5: Fire | BM5: Engineering | BN5: Liability | BO5: Miscellaneous | BP5: Transport | BU5: Motor | BV5: Health | BW5: Worker injury | BX5: Fire | BY5: Engineering | BZ5: Liability | CA5: Miscellaneous | CB5: Transport | CG5: Motor | CH5: Health | CI5: Worker injury | CJ5: Fire | CK5: Engineering | CL5: Liability | CM5: Miscellaneous | CN5: Transport | CS5: Motor | CT5: Health | CU5: Worker injury | CV5: Fire | CW5: Engineering | CX5: Liability | CY5: Miscellaneous | CZ5: Transport | DE5: Motor | DF5: Health | DG5: Worker injury | DH5: Fire | DI5: Engineering | DJ5: Liability | DK5: Miscellaneous | DL5: Transport | DQ5: Motor | DR5: Health | DS5: Worker injury | DT5: Fire | DU5: Engineering | DV5: Liability | DW5: Miscellaneous | DX5: Transport | EC5: Motor | ED5: Health | EE5: Worker injury | EF5: Fire | EG5: Engineering | EH5: Liability | EI5: Miscellaneous | EJ5: Transport
B6: Automobile | C6: Santé | D6: Accident corporel | E6: Incendie | F6: BDM - Construction | G6: RC - RC Déc | H6: RD | I6: Transport | J6: Corporate | K6: Global | M6: Automobile | N6: Santé | O6: Accident corporel | P6: Incendie | Q6: BDM - Construction | R6: RC - RC Déc | S6: RD | T6: Transport | U6: Corporate | V6: Global | Y6: Automobile | Z6: Santé | AA6: Accident corporel | AB6: Incendie | AC6: BDM - Construction | AD6: RC - RC Déc | AE6: RD | AF6: Transport | AG6: Corporate | AH6: Global | AK6: Automobile | AL6: Santé | AM6: Accident corporel | AN6: Incendie | AO6: BDM - Construction | AP6: RC - RC Déc | AQ6: RD | AR6: Transport | AS6: Corporate | AT6: Global | AW6: Automobile | AX6: Santé | AY6: Accident corporel | AZ6: Incendie | BA6: BDM - Construction | BB6: RC - RC Déc | BC6: RD | BD6: Transport | BE6: Corporate | BF6: Global | BI6: Automobile | BJ6: Santé | BK6: Accident corporel | BL6: Incendie | BM6: BDM - Construction | BN6: RC - RC Déc | BO6: RD | BP6: Transport | BQ6: Corporate | BR6: Global | BU6: Automobile | BV6: Santé | BW6: Accident corporel | BX6: Incendie | BY6: BDM - Construction | BZ6: RC - RC Déc | CA6: RD | CB6: Transport | CC6: Corporate | CD6: Global | CG6: Automobile | CH6: Santé | CI6: Accident corporel | CJ6: Incendie | CK6: BDM - Construction | CL6: RC - RC Déc | CM6: RD | CN6: Transport | CO6: Corporate | CP6: Global | CS6: Automobile | CT6: Santé | CU6: Accident corporel | CV6: Incendie | CW6: BDM - Construction | CX6: RC - RC Déc | CY6: RD | CZ6: Transport | DA6: Corporate | DB6: Global | DE6: Automobile | DF6: Santé | DG6: Accident corporel | DH6: Incendie | DI6: BDM - Construction | DJ6: RC - RC Déc | DK6: RD | DL6: Transport | DM6: Corporate | DN6: Global | DQ6: Automobile | DR6: Santé | DS6: Accident corporel | DT6: Incendie | DU6: BDM - Construction | DV6: RC - RC Déc | DW6: RD | DX6: Transport | DY6: Corporate | DZ6: Global | EC6: Automobile | ED6: Santé | EE6: Accident corporel | EF6: Incendie | EG6: BDM - Construction | EH6: RC - RC Déc | EI6: RD | EJ6: Transport | EK6: Corporate | EL6: Global
A7: Primes Emises | B7: ='Hyp 2027'!B5*'Hyp 2027'!B166 -> 2.0666856e+09 | C7: ='Hyp 2027'!C5*'Hyp 2027'!C166 -> 1.8778018e+09 | D7: ='Hyp 2027'!D5*'Hyp 2027'!D166 -> 10053583 | E7: ='Hyp 2027'!E5*'Hyp 2027'!E166 -> 8.9002401e+08 | F7: ='Hyp 2027'!F5*'Hyp 2027'!F166 -> 1.2721586e+08 | G7: ='Hyp 2027'!G5*'Hyp 2027'!G166 -> 27995224 | H7: ='Hyp 2027'!H5*'Hyp 2027'!H166 -> 7.0638702e+08 | I7: ='Hyp 2027'!I5*'Hyp 2027'!I166 -> 20050105 | J7: =SUM(D7:I7) -> 1.7817258e+09 | K7: =B7+C7+J7 -> 5.7262132e+09 | L7: ok | M7: ='Hyp 2027'!B6*'Hyp 2027'!B166 -> 2.5488992e+09 | N7: ='Hyp 2027'!C6*'Hyp 2027'!C166 -> 2.1955344e+09 | O7: ='Hyp 2027'!D6*'Hyp 2027'!D166 -> 29287346 | P7: ='Hyp 2027'!E6*'Hyp 2027'!E166 -> 2.7677022e+09 | Q7: ='Hyp 2027'!F6*'Hyp 2027'!F166 -> 3.2537641e+08 | R7: ='Hyp 2027'!G6*'Hyp 2027'!G166 -> 1.4841429e+08 | S7: ='Hyp 2027'!H6*'Hyp 2027'!H166 -> 9.7934139e+08 | T7: ='Hyp 2027'!I6*'Hyp 2027'!I166 -> 1.2327826e+09 | U7: =SUM(O7:T7) -> 5.4829043e+09 | V7: =M7+N7+U7 -> 1.0227338e+10 | Y7: ='Hyp 2027'!B7*'Hyp 2027'!B$166 -> 3.0333946e+09 | Z7: ='Hyp 2027'!C7*'Hyp 2027'!C$166 -> 2.5452707e+09 | AA7: ='Hyp 2027'!D7*'Hyp 2027'!D$166 -> 30127265 | AB7: ='Hyp 2027'!E7*'Hyp 2027'!E$166 -> 4.6432515e+09 | AC7: ='Hyp 2027'!F7*'Hyp 2027'!F$166 -> 4.2712564e+08 | AD7: ='Hyp 2027'!G7*'Hyp 2027'!G$166 -> 1.6890644e+08 | AE7: ='Hyp 2027'!H7*'Hyp 2027'!H$166 -> 1.1984575e+09 | AF7: ='Hyp 2027'!I7*'Hyp 2027'!I$166 -> 1.3509593e+09 | AG7: =SUM(AA7:AF7) -> 7.8188276e+09 | AH7: =Y7+Z7+AG7 -> 1.3397493e+10 | AK7: ='Hyp 2027'!B8*'Hyp 2027'!B$166 -> 3.2600989e+09 | AL7: ='Hyp 2027'!C8*'Hyp 2027'!C$166 -> 2.7548907e+09 | AM7: ='Hyp 2027'!D8*'Hyp 2027'!D$166 -> 41721466 | AN7: ='Hyp 2027'!E8*'Hyp 2027'!E$166 -> 6.1361385e+09 | AO7: ='Hyp 2027'!F8*'Hyp 2027'!F$166 -> 5.276631e+08 | AP7: ='Hyp 2027'!G8*'Hyp 2027'!G$166 -> 4.9485857e+08 | AQ7: ='Hyp 2027'!H8*'Hyp 2027'!H$166 -> 1.3787138e+09 | AR7: ='Hyp 2027'!I8*'Hyp 2027'!I$166 -> 1.3675495e+09 | AS7: =SUM(AM7:AR7) -> 9.9466449e+09 | AT7: =AK7+AL7+AS7 -> 1.5961634e+10 | AW7: ='Hyp 2027'!B9*'Hyp 2027'!B$166 -> 4.3775806e+09 | AX7: ='Hyp 2027'!C9*'Hyp 2027'!C$166 -> 3.1809995e+09 | AY7: ='Hyp 2027'!D9*'Hyp 2027'!D$166 -> 56771021 | AZ7: ='Hyp 2027'!E9*'Hyp 2027'!E$166 -> 6.5221974e+09 | BA7: ='Hyp 2027'!F9*'Hyp 2027'!F$166 -> 6.5236958e+08 | BB7: ='Hyp 2027'!G9*'Hyp 2027'!G$166 -> 5.8494767e+08 | BC7: ='Hyp 2027'!H9*'Hyp 2027'!H$166 -> 1.5971969e+09 | BD7: ='Hyp 2027'!I9*'Hyp 2027'!I$166 -> 1.849841e+09 | BE7: =SUM(AY7:BD7) -> 1.1263323e+10 | BF7: =AW7+AX7+BE7 -> 1.8821904e+10 | BI7: ='Hyp 2027'!B10*'Hyp 2027'!B$166 -> 4.7250519e+09 | BJ7: ='Hyp 2027'!C10*'Hyp 2027'!C$166 -> 3.3125841e+09 | BK7: ='Hyp 2027'!D10*'Hyp 2027'!D$166 -> 71065615 | BL7: ='Hyp 2027'!E10*'Hyp 2027'!E$166 -> 7.5111084e+09 | BM7: ='Hyp 2027'!F10*'Hyp 2027'!F$166 -> 6.6439984e+08 | BN7: ='Hyp 2027'!G10*'Hyp 2027'!G$166 -> 6.2043728e+08 | BO7: ='Hyp 2027'!H10*'Hyp 2027'!H$166 -> 1.6774132e+09 | BP7: ='Hyp 2027'!I10*'Hyp 2027'!I166 -> 1.9679284e+09 | BQ7: =SUM(BK7:BP7) -> 1.2512353e+10 | BR7: =BI7+BJ7+BQ7 -> 2.0549989e+10 | BU7: ='Hyp 2027'!B11*'Hyp 2027'!B166 -> 5.0426794e+09 | BV7: ='Hyp 2027'!C11*'Hyp 2027'!C166 -> 3.507341e+09 | BW7: ='Hyp 2027'!D11*'Hyp 2027'!D166 -> 75735154 | BX7: ='Hyp 2027'!E11*'Hyp 2027'!E166 -> 7.6256043e+09 | BY7: ='Hyp 2027'!F11*'Hyp 2027'!F166 -> 7.0489351e+08 | BZ7: ='Hyp 2027'!G11*'Hyp 2027'!G166 -> 6.5144005e+08 | CA7: ='Hyp 2027'!H11*'Hyp 2027'!H166 -> 1.7500469e+09 | CB7: ='Hyp 2027'!I11*'Hyp 2027'!I166 -> 2.0924516e+09 | CC7: =SUM(BW7:CB7) -> 1.2900171e+10 | CD7: =BU7+BV7+CC7 -> 2.1450192e+10 | CG7: ='Hyp 2027'!B12*'Hyp 2027'!B166 -> 5.8325733e+09 | CH7: ='Hyp 2027'!C12*'Hyp 2027'!C166 -> 3.687902e+09 | CI7: ='Hyp 2027'!D12*'Hyp 2027'!D166 -> 76186845 | CJ7: ='Hyp 2027'!E12*'Hyp 2027'!E166 -> 7.7515327e+09 | CK7: ='Hyp 2027'!F12*'Hyp 2027'!F166 -> 8.0873244e+08 | CL7: ='Hyp 2027'!G12*'Hyp 2027'!G166 -> 1.7272506e+09 | CM7: ='Hyp 2027'!H12*'Hyp 2027'!H166 -> 1.8142738e+09 | CN7: ='Hyp 2027'!I12*'Hyp 2027'!I166 -> 2.1959177e+09 | CO7: =SUM(CI7:CN7) -> 1.4373894e+10 | CP7: =CG7+CH7+CO7 -> 2.3894369e+10 | CS7: ='Hyp 2027'!B13*'Hyp 2027'!B166 -> 6.1868053e+09 | CT7: ='Hyp 2027'!C13*'Hyp 2027'!C166 -> 3.8589292e+09 | CU7: ='Hyp 2027'!D13*'Hyp 2027'!D166 -> 78104401 | CV7: ='Hyp 2027'!E13*'Hyp 2027'!E166 -> 8.2211768e+09 | CW7: ='Hyp 2027'!F13*'Hyp 2027'!F166 -> 8.1306214e+08 | CX7: ='Hyp 2027'!G13*'Hyp 2027'!G166 -> 2.0575038e+09 | CY7: ='Hyp 2027'!H13*'Hyp 2027'!H166 -> 1.8676955e+09 | CZ7: ='Hyp 2027'!I13*'Hyp 2027'!I166 -> 2.3585336e+09 | DA7: =SUM(CU7:CZ7) -> 1.5396076e+10 | DB7: =CS7+CT7+DA7 -> 2.5441811e+10 | DE7: ='Hyp 2027'!B14*'Hyp 2027'!B166 -> 6.6191466e+09 | DF7: ='Hyp 2027'!C14*'Hyp 2027'!C166 -> 4.1293042e+09 | DG7: ='Hyp 2027'!D14*'Hyp 2027'!D166 -> 81844041 | DH7: ='Hyp 2027'!E14*'Hyp 2027'!E166 -> 8.5702584e+09 | DI7: ='Hyp 2027'!F14*'Hyp 2027'!F166 -> 8.2413417e+08 | DJ7: ='Hyp 2027'!G14*'Hyp 2027'!G166 -> 2.0938713e+09 | DK7: ='Hyp 2027'!H14*'Hyp 2027'!H166 -> 2.0055889e+09 | DL7: ='Hyp 2027'!I14*'Hyp 2027'!I166 -> 2.5246336e+09 | DM7: =SUM(DG7:DL7) -> 1.610033e+10 | DN7: =DE7+DF7+DM7 -> 2.6848781e+10 | DQ7: ='Hyp 2027'!B15*'Hyp 2027'!B166 -> 7.0399024e+09 | DR7: ='Hyp 2027'!C15*'Hyp 2027'!C166 -> 4.3226175e+09 | DS7: ='Hyp 2027'!D15*'Hyp 2027'!D166 -> 84926760 | DT7: ='Hyp 2027'!E15*'Hyp 2027'!E166 -> 8.7111604e+09 | DU7: ='Hyp 2027'!F15*'Hyp 2027'!F166 -> 8.6915286e+08 | DV7: ='Hyp 2027'!G15*'Hyp 2027'!G166 -> 2.1725233e+09 | DW7: ='Hyp 2027'!H15*'Hyp 2027'!H166 -> 2.3526152e+09 | DX7: ='Hyp 2027'!I15*'Hyp 2027'!I166 -> 2.7555055e+09 | DY7: =SUM(DS7:DX7) -> 1.6945884e+10 | DZ7: =DQ7+DR7+DY7 -> 2.8308404e+10 | EC7: ='Hyp 2027'!B16*'Hyp 2027'!B166 -> 7.3631081e+09 | ED7: ='Hyp 2027'!C16*'Hyp 2027'!C166 -> 4.3768737e+09 | EE7: ='Hyp 2027'!D16*'Hyp 2027'!D166 -> 90955409 | EF7: ='Hyp 2027'!E16*'Hyp 2027'!E166 -> 8.9291791e+09 | EG7: ='Hyp 2027'!F16*'Hyp 2027'!F166 -> 9.3111724e+08 | EH7: ='Hyp 2027'!G16*'Hyp 2027'!G166 -> 2.2159648e+09 | EI7: ='Hyp 2027'!H16*'Hyp 2027'!H166 -> 2.4291132e+09 | EJ7: ='Hyp 2027'!I16*'Hyp 2027'!I166 -> 2.8492332e+09 | EK7: =SUM(EE7:EJ7) -> 1.7445563e+10 | EL7: =EC7+ED7+EK7 -> 2.9185545e+10
A8: PAP Ouverture | B8: 0 | C8: 0 | D8: 0 | E8: 0 | F8: 0 | G8: 0 | H8: 0 | I8: 0 | J8: =SUM(D8:I8) -> 0 | K8: =B8+C8+J8 -> 0 | M8: =B8*M135 -> 0 | N8: =C8*N135 -> 0 | O8: =D8*O135 -> 0 | P8: =E8*P135 -> 0 | Q8: =F8*Q135 -> 0 | R8: =G8*R135 -> 0 | S8: =H8*S135 -> 0 | T8: =I8*T135 -> 0 | U8: =SUM(O8:T8) -> 0 | V8: =M8+N8+U8 -> 0 | Y8: =M8*Y135 -> 0 | Z8: =N8*Z135 -> 0 | AA8: =O8*AA135 -> 0 | AB8: =P8*AB135 -> 0 | AC8: =Q8*AC135 -> 0 | AD8: =R8*AD135 -> 0 | AE8: =S8*AE135 -> 0 | AF8: =T8*AF135 -> 0 | AG8: =SUM(AA8:AF8) -> 0 | AH8: =Y8+Z8+AG8 -> 0 | AK8: =Y8*AK135 -> 0 | AL8: =Z8*AL135 -> 0 | AM8: =AA8*AM135 -> 0 | AN8: =AB8*AN135 -> 0 | AO8: =AC8*AO135 -> 0 | AP8: =AD8*AP135 -> 0 | AQ8: =AE8*AQ135 -> 0 | AR8: =AF8*AR135 -> 0 | AS8: =AG8*AS135 -> 0 | AT8: =AK8+AL8+AS8 -> 0 | AW8: =AK8*AW135 -> 0 | AX8: =AL8*AX135 -> 0 | AY8: =AM8*AY135 -> 0 | AZ8: =AN8*AZ135 -> 0 | BA8: =AO8*BA135 -> 0 | BB8: =AP8*BB135 -> 0 | BC8: =AQ8*BC135 -> 0 | BD8: =AR8*BD135 -> 0 | BE8: =AS8*BE135 -> 0 | BF8: =AW8+AX8+BE8 -> 0 | BI8: =AW8*BI135 -> 0 | BJ8: =AX8*BJ135 -> 0 | BK8: =AY8*BK135 -> 0 | BL8: =AZ8*BL135 -> 0 | BM8: =BA8*BM135 -> 0 | BN8: =BB8*BN135 -> 0 | BO8: =BC8*BO135 -> 0 | BP8: =BD8*BP135 -> 0 | BQ8: =BE8*BQ135 -> 0 | BR8: =BI8+BJ8+BQ8 -> 0 | BU8: =BI8*BU135 -> 0 | BV8: =BJ8*BV135 -> 0 | BW8: =BK8*BW135 -> 0 | BX8: =BL8*BX135 -> 0 | BY8: =BM8*BY135 -> 0 | BZ8: =BN8*BZ135 -> 0 | CA8: =BO8*CA135 -> 0 | CB8: =BP8*CB135 -> 0 | CC8: =BQ8*CC135 -> 0 | CD8: =BU8+BV8+CC8 -> 0 | CG8: =BU8*CG135 -> 0 | CH8: =BV8*CH135 -> 0 | CI8: =BW8*CI135 -> 0 | CJ8: =BX8*CJ135 -> 0 | CK8: =BY8*CK135 -> 0 | CL8: =BZ8*CL135 -> 0 | CM8: =CA8*CM135 -> 0 | CN8: =CB8*CN135 -> 0 | CO8: =CC8*CO135 -> 0 | CP8: =CG8+CH8+CO8 -> 0 | CS8: =CG8*CS135 -> 0 | CT8: =CH8*CT135 -> 0 | CU8: =CI8*CU135 -> 0 | CV8: =CJ8*CV135 -> 0 | CW8: =CK8*CW135 -> 0 | CX8: =CL8*CX135 -> 0 | CY8: =CM8*CY135 -> 0 | CZ8: =CN8*CZ135 -> 0 | DA8: =CO8*DA135 -> 0 | DB8: =CS8+CT8+DA8 -> 0 | DE8: =CS8*DE135 -> 0 | DF8: =CT8*DF135 -> 0 | DG8: =CU8*DG135 -> 0 | DH8: =CV8*DH135 -> 0 | DI8: =CW8*DI135 -> 0 | DJ8: =CX8*DJ135 -> 0 | DK8: =CY8*DK135 -> 0 | DL8: =CZ8*DL135 -> 0 | DM8: =DA8*DM135 -> 0 | DN8: =DE8+DF8+DM8 -> 0 | DQ8: =DE8*DQ135 -> 0 | DR8: =DF8*DR135 -> 0 | DS8: =DG8*DS135 -> 0 | DT8: =DH8*DT135 -> 0 | DU8: =DI8*DU135 -> 0 | DV8: =DJ8*DV135 -> 0 | DW8: =DK8*DW135 -> 0 | DX8: =DL8*DX135 -> 0 | DY8: =DM8*DY135 -> 0 | DZ8: =DQ8+DR8+DY8 -> 0 | EC8: =DQ8*EC135 -> 0 | ED8: =DR8*ED135 -> 0 | EE8: =DS8*EE135 -> 0 | EF8: =DT8*EF135 -> 0 | EG8: =DU8*EG135 -> 0 | EH8: =DV8*EH135 -> 0 | EI8: =DW8*EI135 -> 0 | EJ8: =DX8*EJ135 -> 0 | EK8: =DY8*EK135 -> 0 | EL8: =EC8+ED8+EK8 -> 0
A9: PAP Clôture | B9: 0 | C9: 0 | D9: 0 | E9: 0 | F9: 0 | G9: 0 | H9: 0 | I9: 0 | J9: =SUM(D9:I9) -> 0 | K9: =B9+C9+J9 -> 0 | M9: =B9*M136 -> 0 | N9: =C9*N136 -> 0 | O9: =D9*O136 -> 0 | P9: =E9*P136 -> 0 | Q9: =F9*Q136 -> 0 | R9: =G9*R136 -> 0 | S9: =H9*S136 -> 0 | T9: =I9*T136 -> 0 | U9: =SUM(O9:T9) -> 0 | V9: =M9+N9+U9 -> 0 | Y9: =M9*Y136 -> 0 | Z9: =N9*Z136 -> 0 | AA9: =O9*AA136 -> 0 | AB9: =P9*AB136 -> 0 | AC9: =Q9*AC136 -> 0 | AD9: =R9*AD136 -> 0 | AE9: =S9*AE136 -> 0 | AF9: =T9*AF136 -> 0 | AG9: =SUM(AA9:AF9) -> 0 | AH9: =Y9+Z9+AG9 -> 0 | AK9: =Y9*AK136 -> 0 | AL9: =Z9*AL136 -> 0 | AM9: =AA9*AM136 -> 0 | AN9: =AB9*AN136 -> 0 | AO9: =AC9*AO136 -> 0 | AP9: =AD9*AP136 -> 0 | AQ9: =AE9*AQ136 -> 0 | AR9: =AF9*AR136 -> 0 | AS9: =AG9*AS136 -> 0 | AT9: =AK9+AL9+AS9 -> 0 | AW9: =AK9*AW136 -> 0 | AX9: =AL9*AX136 -> 0 | AY9: =AM9*AY136 -> 0 | AZ9: =AN9*AZ136 -> 0 | BA9: =AO9*BA136 -> 0 | BB9: =AP9*BB136 -> 0 | BC9: =AQ9*BC136 -> 0 | BD9: =AR9*BD136 -> 0 | BE9: =AS9*BE136 -> 0 | BF9: =AW9+AX9+BE9 -> 0 | BI9: =AW9*BI136 -> 0 | BJ9: =AX9*BJ136 -> 0 | BK9: =AY9*BK136 -> 0 | BL9: =AZ9*BL136 -> 0 | BM9: =BA9*BM136 -> 0 | BN9: =BB9*BN136 -> 0 | BO9: =BC9*BO136 -> 0 | BP9: =BD9*BP136 -> 0 | BQ9: =BE9*BQ136 -> 0 | BR9: =BI9+BJ9+BQ9 -> 0 | BU9: =BI9*BU136 -> 0 | BV9: =BJ9*BV136 -> 0 | BW9: =BK9*BW136 -> 0 | BX9: =BL9*BX136 -> 0 | BY9: =BM9*BY136 -> 0 | BZ9: =BN9*BZ136 -> 0 | CA9: =BO9*CA136 -> 0 | CB9: =BP9*CB136 -> 0 | CC9: =BQ9*CC136 -> 0 | CD9: =BU9+BV9+CC9 -> 0 | CG9: =BU9*CG136 -> 0 | CH9: =BV9*CH136 -> 0 | CI9: =BW9*CI136 -> 0 | CJ9: =BX9*CJ136 -> 0 | CK9: =BY9*CK136 -> 0 | CL9: =BZ9*CL136 -> 0 | CM9: =CA9*CM136 -> 0 | CN9: =CB9*CN136 -> 0 | CO9: =CC9*CO136 -> 0 | CP9: =CG9+CH9+CO9 -> 0 | CS9: =CG9*CS136 -> 0 | CT9: =CH9*CT136 -> 0 | CU9: =CI9*CU136 -> 0 | CV9: =CJ9*CV136 -> 0 | CW9: =CK9*CW136 -> 0 | CX9: =CL9*CX136 -> 0 | CY9: =CM9*CY136 -> 0 | CZ9: =CN9*CZ136 -> 0 | DA9: =CO9*DA136 -> 0 | DB9: =CS9+CT9+DA9 -> 0 | DE9: =CS9*DE136 -> 0 | DF9: =CT9*DF136 -> 0 | DG9: =CU9*DG136 -> 0 | DH9: =CV9*DH136 -> 0 | DI9: =CW9*DI136 -> 0 | DJ9: =CX9*DJ136 -> 0 | DK9: =CY9*DK136 -> 0 | DL9: =CZ9*DL136 -> 0 | DM9: =DA9*DM136 -> 0 | DN9: =DE9+DF9+DM9 -> 0 | DQ9: =DE9*DQ136 -> 0 | DR9: =DF9*DR136 -> 0 | DS9: =DG9*DS136 -> 0 | DT9: =DH9*DT136 -> 0 | DU9: =DI9*DU136 -> 0 | DV9: =DJ9*DV136 -> 0 | DW9: =DK9*DW136 -> 0 | DX9: =DL9*DX136 -> 0 | DY9: =DM9*DY136 -> 0 | DZ9: =DQ9+DR9+DY9 -> 0 | EC9: =DQ9*EC136 -> 0 | ED9: =DR9*ED136 -> 0 | EE9: =DS9*EE136 -> 0 | EF9: =DT9*EF136 -> 0 | EG9: =DU9*EG136 -> 0 | EH9: =DV9*EH136 -> 0 | EI9: =DW9*EI136 -> 0 | EJ9: =DX9*EJ136 -> 0 | EK9: =DY9*EK136 -> 0 | EL9: =EC9+ED9+EK9 -> 0
A10: PANE Ouverture | B10: 1.4188283e+08 | C10: 2.8667051e+08 | D10: 9709029.5 | E10: 46246309 | F10: 1964921.2 | G10: 91870726 | H10: 6721131.9 | I10: 1.4284885e+08 | J10: =SUM(D10:I10) -> 2.9936097e+08 | K10: =B10+C10+J10 -> 7.279143e+08 | L10: ok | M10: =B11 -> 1.4188283e+08 | N10: =C11 -> 2.8667051e+08 | O10: =D11 -> 9709029.5 | P10: =E11 -> 46246309 | Q10: =F11 -> 1964921.2 | R10: =G11 -> 91870726 | S10: =H11 -> 6721131.9 | T10: =I11 -> 1.4284885e+08 | U10: =SUM(O10:T10) -> 2.9936097e+08 | V10: =M10+N10+U10 -> 7.279143e+08 | W10: =V10=K10 -> TRUE | Y10: =M10 -> 1.4188283e+08 | Z10: =N10 -> 2.8667051e+08 | AA10: =O10 -> 9709029.5 | AB10: =P10 -> 46246309 | AC10: =Q10 -> 1964921.2 | AD10: =R10 -> 91870726 | AE10: =S10 -> 6721131.9 | AF10: =T10 -> 1.4284885e+08 | AG10: =SUM(AA10:AF10) -> 2.9936097e+08 | AH10: =Y10+Z10+AG10 -> 7.279143e+08 | AI10: =AH10=V10 -> TRUE | AK10: =Y11*AK137 -> 1.4188283e+08 | AL10: =Z11*AL137 -> 2.8667051e+08 | AM10: =AA11*AM137 -> 9709029.5 | AN10: =AB11*AN137 -> 46246309 | AO10: =AC11*AO137 -> 1964921.2 | AP10: =AD11*AP137 -> 91870726 | AQ10: =AE11*AQ137 -> 6721131.9 | AR10: =AF11*AR137 -> 1.4284885e+08 | AS10: =SUM(AM10:AR10) -> 2.9936097e+08 | AT10: =AK10+AL10+AS10 -> 7.279143e+08 | AU10: =AT10=AH10 -> TRUE | AW10: =AK11*AW137 -> 1.4188283e+08 | AX10: =AL11*AX137 -> 2.8667051e+08 | AY10: =AM11*AY137 -> 9709029.5 | AZ10: =AN11*AZ137 -> 46246309 | BA10: =AO11*BA137 -> 1964921.2 | BB10: =AP11*BB137 -> 91870726 | BC10: =AQ11*BC137 -> 6721131.9 | BD10: =AR11*BD137 -> 1.4284885e+08 | BE10: =SUM(AY10:BD10) -> 2.9936097e+08 | BF10: =AW10+AX10+BE10 -> 7.279143e+08 | BG10: =BF10=AW10 -> FALSE | BI10: =AW11*BI137 -> 1.4188283e+08 | BJ10: =AX11*BJ137 -> 2.8667051e+08 | BK10: =AY11*BK137 -> 9709029.5 | BL10: =AZ11*BL137 -> 46246309 | BM10: =BA11*BM137 -> 1964921.2 | BN10: =BB11*BN137 -> 91870726 | BO10: =BC11*BO137 -> 6721131.9 | BP10: =BD11*BP137 -> 1.4284885e+08 | BQ10: =SUM(BK10:BP10) -> 2.9936097e+08 | BR10: =BI10+BJ10+BQ10 -> 7.279143e+08 | BU10: =BI11*BU137 -> 1.4188283e+08 | BV10: =BJ11*BV137 -> 2.8667051e+08 | BW10: =BK11*BW137 -> 9709029.5 | BX10: =BL11*BX137 -> 46246309 | BY10: =BM11*BY137 -> 1964921.2 | BZ10: =BN11*BZ137 -> 91870726 | CA10: =BO11*CA137 -> 6721131.9 | CB10: =BP11*CB137 -> 1.4284885e+08 | CC10: =SUM(BW10:CB10) -> 2.9936097e+08 | CD10: =BU10+BV10+CC10 -> 7.279143e+08 | CE10: =CD10=BU10 -> FALSE | CG10: =BU11*CG137 -> 1.4188283e+08 | CH10: =BV11*CH137 -> 2.8667051e+08 | CI10: =BW11*CI137 -> 9709029.5 | CJ10: =BX11*CJ137 -> 46246309 | CK10: =BY11*CK137 -> 1964921.2 | CL10: =BZ11*CL137 -> 91870726 | CM10: =CA11*CM137 -> 6721131.9 | CN10: =CB11*CN137 -> 1.4284885e+08 | CO10: =SUM(CI10:CN10) -> 2.9936097e+08 | CP10: =CG10+CH10+CO10 -> 7.279143e+08 | CS10: =CG11*CS137 -> 1.4188283e+08 | CT10: =CH11*CT137 -> 2.8667051e+08 | CU10: =CI11*CU137 -> 9709029.5 | CV10: =CJ11*CV137 -> 46246309 | CW10: =CK11*CW137 -> 1964921.2 | CX10: =CL11*CX137 -> 91870726 | CY10: =CM11*CY137 -> 6721131.9 | CZ10: =CN11*CZ137 -> 1.4284885e+08 | DA10: =SUM(CU10:CZ10) -> 2.9936097e+08 | DB10: =CS10+CT10+DA10 -> 7.279143e+08 | DE10: =CS11*DE137 -> 1.4188283e+08 | DF10: =CT11*DF137 -> 2.8667051e+08 | DG10: =CU11*DG137 -> 9709029.5 | DH10: =CV11*DH137 -> 46246309 | DI10: =CW11*DI137 -> 1964921.2 | DJ10: =CX11*DJ137 -> 91870726 | DK10: =CY11*DK137 -> 6721131.9 | DL10: =CZ11*DL137 -> 1.4284885e+08 | DM10: =SUM(DG10:DL10) -> 2.9936097e+08 | DN10: =DE10+DF10+DM10 -> 7.279143e+08 | DQ10: =DE11*DQ137 -> 1.4188283e+08 | DR10: =DF11*DR137 -> 2.8667051e+08 | DS10: =DG11*DS137 -> 9709029.5 | DT10: =DH11*DT137 -> 46246309 | DU10: =DI11*DU137 -> 1964921.2 | DV10: =DJ11*DV137 -> 91870726 | DW10: =DK11*DW137 -> 6721131.9 | DX10: =DL11*DX137 -> 1.4284885e+08 | DY10: =SUM(DS10:DX10) -> 2.9936097e+08 | DZ10: =DQ10+DR10+DY10 -> 7.279143e+08 | EC10: =DQ11*EC137 -> 1.4188283e+08 | ED10: =DR11*ED137 -> 2.8667051e+08 | EE10: =DS11*EE137 -> 9709029.5 | EF10: =DT11*EF137 -> 46246309 | EG10: =DU11*EG137 -> 1964921.2 | EH10: =DV11*EH137 -> 91870726 | EI10: =DW11*EI137 -> 6721131.9 | EJ10: =DX11*EJ137 -> 1.4284885e+08 | EK10: =SUM(EE10:EJ10) -> 2.9936097e+08 | EL10: =EC10+ED10+EK10 -> 7.279143e+08
A11: PANE Clôture | B11: =B10 -> 1.4188283e+08 | C11: =C10 -> 2.8667051e+08 | D11: =D10 -> 9709029.5 | E11: =E10 -> 46246309 | F11: =F10 -> 1964921.2 | G11: =G10 -> 91870726 | H11: =H10 -> 6721131.9 | I11: =I10 -> 1.4284885e+08 | J11: =SUM(D11:I11) -> 2.9936097e+08 | K11: =B11+C11+J11 -> 7.279143e+08 | L11: ok | M11: =M10 -> 1.4188283e+08 | N11: =N10 -> 2.8667051e+08 | O11: =O10 -> 9709029.5 | P11: =P10 -> 46246309 | Q11: =Q10 -> 1964921.2 | R11: =R10 -> 91870726 | S11: =S10 -> 6721131.9 | T11: =T10 -> 1.4284885e+08 | U11: =SUM(O11:T11) -> 2.9936097e+08 | V11: =M11+N11+U11 -> 7.279143e+08 | W11: =V11=K11 -> TRUE | Y11: =M11 -> 1.4188283e+08 | Z11: =N11*Z138 -> 2.8667051e+08 | AA11: =O11*AA138 -> 9709029.5 | AB11: =P11*AB138 -> 46246309 | AC11: =Q11*AC138 -> 1964921.2 | AD11: =R11*AD138 -> 91870726 | AE11: =S11*AE138 -> 6721131.9 | AF11: =T11*AF138 -> 1.4284885e+08 | AG11: =SUM(AA11:AF11) -> 2.9936097e+08 | AH11: =Y11+Z11+AG11 -> 7.279143e+08 | AI11: =AH11=V11 -> TRUE | AK11: =Y11*AK138 -> 1.4188283e+08 | AL11: =Z11*AL138 -> 2.8667051e+08 | AM11: =AA11*AM138 -> 9709029.5 | AN11: =AB11*AN138 -> 46246309 | AO11: =AC11*AO138 -> 1964921.2 | AP11: =AD11*AP138 -> 91870726 | AQ11: =AE11*AQ138 -> 6721131.9 | AR11: =AF11*AR138 -> 1.4284885e+08 | AS11: =SUM(AM11:AR11) -> 2.9936097e+08 | AT11: =AK11+AL11+AS11 -> 7.279143e+08 | AU11: =AT11=AH11 -> TRUE | AW11: =AK11*AW138 -> 1.4188283e+08 | AX11: =AL11*AX138 -> 2.8667051e+08 | AY11: =AM11*AY138 -> 9709029.5 | AZ11: =AN11*AZ138 -> 46246309 | BA11: =AO11*BA138 -> 1964921.2 | BB11: =AP11*BB138 -> 91870726 | BC11: =AQ11*BC138 -> 6721131.9 | BD11: =AR11*BD138 -> 1.4284885e+08 | BE11: =SUM(AY11:BD11) -> 2.9936097e+08 | BF11: =AW11+AX11+BE11 -> 7.279143e+08 | BG11: =BF11=AW11 -> FALSE | BI11: =AW11*BI138 -> 1.4188283e+08 | BJ11: =AX11*BJ138 -> 2.8667051e+08 | BK11: =AY11*BK138 -> 9709029.5 | BL11: =AZ11*BL138 -> 46246309 | BM11: =BA11*BM138 -> 1964921.2 | BN11: =BB11*BN138 -> 91870726 | BO11: =BC11*BO138 -> 6721131.9 | BP11: =BD11*BP138 -> 1.4284885e+08 | BQ11: =SUM(BK11:BP11) -> 2.9936097e+08 | BR11: =BI11+BJ11+BQ11 -> 7.279143e+08 | BU11: =BI11*BU138 -> 1.4188283e+08 | BV11: =BJ11*BV138 -> 2.8667051e+08 | BW11: =BK11*BW138 -> 9709029.5 | BX11: =BL11*BX138 -> 46246309 | BY11: =BM11*BY138 -> 1964921.2 | BZ11: =BN11*BZ138 -> 91870726 | CA11: =BO11*CA138 -> 6721131.9 | CB11: =BP11*CB138 -> 1.4284885e+08 | CC11: =SUM(BW11:CB11) -> 2.9936097e+08 | CD11: =BU11+BV11+CC11 -> 7.279143e+08 | CE11: =CD11=BU11 -> FALSE | CG11: =BU11*CG138 -> 1.4188283e+08 | CH11: =BV11*CH138 -> 2.8667051e+08 | CI11: =BW11*CI138 -> 9709029.5 | CJ11: =BX11*CJ138 -> 46246309 | CK11: =BY11*CK138 -> 1964921.2 | CL11: =BZ11*CL138 -> 91870726 | CM11: =CA11*CM138 -> 6721131.9 | CN11: =CB11*CN138 -> 1.4284885e+08 | CO11: =SUM(CI11:CN11) -> 2.9936097e+08 | CP11: =CG11+CH11+CO11 -> 7.279143e+08 | CS11: =CG11*CS138 -> 1.4188283e+08 | CT11: =CH11*CT138 -> 2.8667051e+08 | CU11: =CI11*CU138 -> 9709029.5 | CV11: =CJ11*CV138 -> 46246309 | CW11: =CK11*CW138 -> 1964921.2 | CX11: =CL11*CX138 -> 91870726 | CY11: =CM11*CY138 -> 6721131.9 | CZ11: =CN11*CZ138 -> 1.4284885e+08 | DA11: =SUM(CU11:CZ11) -> 2.9936097e+08 | DB11: =CS11+CT11+DA11 -> 7.279143e+08 | DE11: =CS11*DE138 -> 1.4188283e+08 | DF11: =CT11*DF138 -> 2.8667051e+08 | DG11: =CU11*DG138 -> 9709029.5 | DH11: =CV11*DH138 -> 46246309 | DI11: =CW11*DI138 -> 1964921.2 | DJ11: =CX11*DJ138 -> 91870726 | DK11: =CY11*DK138 -> 6721131.9 | DL11: =CZ11*DL138 -> 1.4284885e+08 | DM11: =SUM(DG11:DL11) -> 2.9936097e+08 | DN11: =DE11+DF11+DM11 -> 7.279143e+08 | DQ11: =DE11*DQ138 -> 1.4188283e+08 | DR11: =DF11*DR138 -> 2.8667051e+08 | DS11: =DG11*DS138 -> 9709029.5 | DT11: =DH11*DT138 -> 46246309 | DU11: =DI11*DU138 -> 1964921.2 | DV11: =DJ11*DV138 -> 91870726 | DW11: =DK11*DW138 -> 6721131.9 | DX11: =DL11*DX138 -> 1.4284885e+08 | DY11: =SUM(DS11:DX11) -> 2.9936097e+08 | DZ11: =DQ11+DR11+DY11 -> 7.279143e+08 | EC11: 1.4897697e+08 | ED11: 3.0100404e+08 | EE11: 10194481 | EF11: 48558624 | EG11: 2063167.3 | EH11: 96464262 | EI11: 7057188.5 | EJ11: 1.4999129e+08 | EK11: =SUM(EE11:EJ11) -> 3.1432902e+08 | EL11: =EC11+ED11+EK11 -> 7.6431002e+08
A12: Chiffre d'Affaire | B12: =B7-B8+B9-B10+B11 -> 2.0666856e+09 | C12: =C7-C8+C9-C10+C11 -> 1.8778018e+09 | D12: =D7-D8+D9-D10+D11 -> 10053583 | E12: =E7-E8+E9-E10+E11 -> 8.9002401e+08 | F12: =F7-F8+F9-F10+F11 -> 1.2721586e+08 | G12: =G7-G8+G9-G10+G11 -> 27995224 | H12: =H7-H8+H9-H10+H11 -> 7.0638702e+08 | I12: =I7-I8+I9-I10+I11 -> 20050105 | ... K12: =K7-K8+K9-K10+K11 -> 5.7262132e+09 | M12: =M7-M8+M9-M10+M11 -> 2.5488992e+09 | N12: =N7-N8+N9-N10+N11 -> 2.1955344e+09 | O12: =O7-O8+O9-O10+O11 -> 29287346 | P12: =P7-P8+P9-P10+P11 -> 2.7677022e+09 | Q12: =Q7-Q8+Q9-Q10+Q11 -> 3.2537641e+08 | R12: =R7-R8+R9-R10+R11 -> 1.4841429e+08 | S12: =S7-S8+S9-S10+S11 -> 9.7934139e+08 | T12: =T7-T8+T9-T10+T11 -> 1.2327826e+09 | ... V12: =V7-V8+V9-V10+V11 -> 1.0227338e+10 | Y12: =Y7-Y8+Y9-Y10+Y11 -> 3.0333946e+09 | Z12: =Z7-Z8+Z9-Z10+Z11 -> 2.5452707e+09 | AA12: =AA7-AA8+AA9-AA10+AA11 -> 30127265 | AB12: =AB7-AB8+AB9-AB10+AB11 -> 4.6432515e+09 | AC12: =AC7-AC8+AC9-AC10+AC11 -> 4.2712564e+08 | AD12: =AD7-AD8+AD9-AD10+AD11 -> 1.6890644e+08 | AE12: =AE7-AE8+AE9-AE10+AE11 -> 1.1984575e+09 | AF12: =AF7-AF8+AF9-AF10+AF11 -> 1.3509593e+09 | ... AH12: =AH7-AH8+AH9-AH10+AH11 -> 1.3397493e+10 | AK12: =AK7-AK8+AK9-AK10+AK11 -> 3.2600989e+09 | AL12: =AL7-AL8+AL9-AL10+AL11 -> 2.7548907e+09 | AM12: =AM7-AM8+AM9-AM10+AM11 -> 41721466 | AN12: =AN7-AN8+AN9-AN10+AN11 -> 6.1361385e+09 | AO12: =AO7-AO8+AO9-AO10+AO11 -> 5.276631e+08 | AP12: =AP7-AP8+AP9-AP10+AP11 -> 4.9485857e+08 | AQ12: =AQ7-AQ8+AQ9-AQ10+AQ11 -> 1.3787138e+09 | AR12: =AR7-AR8+AR9-AR10+AR11 -> 1.3675495e+09 | ... AT12: =AT7-AT8+AT9-AT10+AT11 -> 1.5961634e+10 | AW12: =AW7-AW8+AW9-AW10+AW11 -> 4.3775806e+09 | AX12: =AX7-AX8+AX9-AX10+AX11 -> 3.1809995e+09 | AY12: =AY7-AY8+AY9-AY10+AY11 -> 56771021 | AZ12: =AZ7-AZ8+AZ9-AZ10+AZ11 -> 6.5221974e+09 | BA12: =BA7-BA8+BA9-BA10+BA11 -> 6.5236958e+08 | BB12: =BB7-BB8+BB9-BB10+BB11 -> 5.8494767e+08 | BC12: =BC7-BC8+BC9-BC10+BC11 -> 1.5971969e+09 | BD12: =BD7-BD8+BD9-BD10+BD11 -> 1.849841e+09 | ... BF12: =BF7-BF8+BF9-BF10+BF11 -> 1.8821904e+10 | BI12: =BI7-BI8+BI9-BI10+BI11 -> 4.7250519e+09 | BJ12: =BJ7-BJ8+BJ9-BJ10+BJ11 -> 3.3125841e+09 | BK12: =BK7-BK8+BK9-BK10+BK11 -> 71065615 | BL12: =BL7-BL8+BL9-BL10+BL11 -> 7.5111084e+09 | BM12: =BM7-BM8+BM9-BM10+BM11 -> 6.6439984e+08 | BN12: =BN7-BN8+BN9-BN10+BN11 -> 6.2043728e+08 | BO12: =BO7-BO8+BO9-BO10+BO11 -> 1.6774132e+09 | BP12: =BP7-BP8+BP9-BP10+BP11 -> 1.9679284e+09 | ... BR12: =BR7-BR8+BR9-BR10+BR11 -> 2.0549989e+10 | BU12: =BU7-BU8+BU9-BU10+BU11 -> 5.0426794e+09 | BV12: =BV7-BV8+BV9-BV10+BV11 -> 3.507341e+09 | BW12: =BW7-BW8+BW9-BW10+BW11 -> 75735154 | BX12: =BX7-BX8+BX9-BX10+BX11 -> 7.6256043e+09 | BY12: =BY7-BY8+BY9-BY10+BY11 -> 7.0489351e+08 | BZ12: =BZ7-BZ8+BZ9-BZ10+BZ11 -> 6.5144005e+08 | CA12: =CA7-CA8+CA9-CA10+CA11 -> 1.7500469e+09 | CB12: =CB7-CB8+CB9-CB10+CB11 -> 2.0924516e+09 | ... CD12: =CD7-CD8+CD9-CD10+CD11 -> 2.1450192e+10 | CG12: =CG7-CG8+CG9-CG10+CG11 -> 5.8325733e+09 | CH12: =CH7-CH8+CH9-CH10+CH11 -> 3.687902e+09 | CI12: =CI7-CI8+CI9-CI10+CI11 -> 76186845 | CJ12: =CJ7-CJ8+CJ9-CJ10+CJ11 -> 7.7515327e+09 | CK12: =CK7-CK8+CK9-CK10+CK11 -> 8.0873244e+08 | CL12: =CL7-CL8+CL9-CL10+CL11 -> 1.7272506e+09 | CM12: =CM7-CM8+CM9-CM10+CM11 -> 1.8142738e+09 | CN12: =CN7-CN8+CN9-CN10+CN11 -> 2.1959177e+09 | ... CP12: =CP7-CP8+CP9-CP10+CP11 -> 2.3894369e+10 | CS12: =CS7-CS8+CS9-CS10+CS11 -> 6.1868053e+09 | CT12: =CT7-CT8+CT9-CT10+CT11 -> 3.8589292e+09 | CU12: =CU7-CU8+CU9-CU10+CU11 -> 78104401 | CV12: =CV7-CV8+CV9-CV10+CV11 -> 8.2211768e+09 | CW12: =CW7-CW8+CW9-CW10+CW11 -> 8.1306214e+08 | CX12: =CX7-CX8+CX9-CX10+CX11 -> 2.0575038e+09 | CY12: =CY7-CY8+CY9-CY10+CY11 -> 1.8676955e+09 | CZ12: =CZ7-CZ8+CZ9-CZ10+CZ11 -> 2.3585336e+09 | ... DB12: =DB7-DB8+DB9-DB10+DB11 -> 2.5441811e+10 | DE12: =DE7-DE8+DE9-DE10+DE11 -> 6.6191466e+09 | DF12: =DF7-DF8+DF9-DF10+DF11 -> 4.1293042e+09 | DG12: =DG7-DG8+DG9-DG10+DG11 -> 81844041 | DH12: =DH7-DH8+DH9-DH10+DH11 -> 8.5702584e+09 | DI12: =DI7-DI8+DI9-DI10+DI11 -> 8.2413417e+08 | DJ12: =DJ7-DJ8+DJ9-DJ10+DJ11 -> 2.0938713e+09 | DK12: =DK7-DK8+DK9-DK10+DK11 -> 2.0055889e+09 | DL12: =DL7-DL8+DL9-DL10+DL11 -> 2.5246336e+09 | ... DN12: =DN7-DN8+DN9-DN10+DN11 -> 2.6848781e+10 | DQ12: =DQ7-DQ8+DQ9-DQ10+DQ11 -> 7.0399024e+09 | DR12: =DR7-DR8+DR9-DR10+DR11 -> 4.3226175e+09 | DS12: =DS7-DS8+DS9-DS10+DS11 -> 84926760 | DT12: =DT7-DT8+DT9-DT10+DT11 -> 8.7111604e+09 | DU12: =DU7-DU8+DU9-DU10+DU11 -> 8.6915286e+08 | DV12: =DV7-DV8+DV9-DV10+DV11 -> 2.1725233e+09 | DW12: =DW7-DW8+DW9-DW10+DW11 -> 2.3526152e+09 | DX12: =DX7-DX8+DX9-DX10+DX11 -> 2.7555055e+09 | ... DZ12: =DZ7-DZ8+DZ9-DZ10+DZ11 -> 2.8308404e+10 | EC12: =EC7-EC8+EC9-EC10+EC11 -> 7.3702022e+09 | ED12: =ED7-ED8+ED9-ED10+ED11 -> 4.3912073e+09 | EE12: =EE7-EE8+EE9-EE10+EE11 -> 91440861 | EF12: =EF7-EF8+EF9-EF10+EF11 -> 8.9314915e+09 | EG12: =EG7-EG8+EG9-EG10+EG11 -> 9.3121548e+08 | EH12: =EH7-EH8+EH9-EH10+EH11 -> 2.2205583e+09 | EI12: =EI7-EI8+EI9-EI10+EI11 -> 2.4294493e+09 | EJ12: =EJ7-EJ8+EJ9-EJ10+EJ11 -> 2.8563756e+09 | ... EL12: =EL7-EL8+EL9-EL10+EL11 -> 2.9221941e+10
A14: Sinistres payés Per. | B14: ='Hyp 2027'!B264 -> 2.8513607e+08 | C14: ='Hyp 2027'!C264 -> 2.490522e+08 | D14: ='Hyp 2027'!D264 -> 1521445.7 | E14: ='Hyp 2027'!E264 -> 4.2015486e+08 | F14: ='Hyp 2027'!F264 -> 9177868.9 | G14: ='Hyp 2027'!G264 -> 37725355 | H14: ='Hyp 2027'!H264 -> 46900845 | I14: ='Hyp 2027'!I264 -> 78664185 | J14: =SUM(D14:I14) -> 5.9414456e+08 | K14: =B14+C14+J14 -> 1.1283328e+09 | M14: =B14+'Hyp 2027'!B265 -> 5.7027214e+08 | N14: =C14+'Hyp 2027'!C265 -> 4.981044e+08 | O14: =D14+'Hyp 2027'!D265 -> 3042891.4 | P14: =E14+'Hyp 2027'!E265 -> 8.4030972e+08 | Q14: =F14+'Hyp 2027'!F265 -> 18355738 | R14: =G14+'Hyp 2027'!G265 -> 75450710 | S14: =H14+'Hyp 2027'!H265 -> 93801691 | T14: =I14+'Hyp 2027'!I265 -> 1.5732837e+08 | U14: =SUM(O14:T14) -> 1.1882891e+09 | V14: =M14+N14+U14 -> 2.2566657e+09 | Y14: =M14+'Hyp 2027'!B265 -> 8.5540821e+08 | Z14: =N14+'Hyp 2027'!C265 -> 7.4715661e+08 | AA14: =O14+'Hyp 2027'!D265 -> 4564337.1 | AB14: =P14+'Hyp 2027'!E265 -> 1.2604646e+09 | AC14: =Q14+'Hyp 2027'!F265 -> 27533607 | AD14: =R14+'Hyp 2027'!G265 -> 1.1317607e+08 | AE14: =S14+'Hyp 2027'!H265 -> 1.4070254e+08 | AF14: =T14+'Hyp 2027'!I265 -> 2.3599255e+08 | AG14: =SUM(AA14:AF14) -> 1.7824337e+09 | AH14: =Y14+Z14+AG14 -> 3.3849985e+09 | AK14: =Y14+'Hyp 2027'!B265 -> 1.1405443e+09 | AL14: =Z14+'Hyp 2027'!C265 -> 9.9620881e+08 | AM14: =AA14+'Hyp 2027'!D265 -> 6085782.9 | AN14: =AB14+'Hyp 2027'!E265 -> 1.6806194e+09 | AO14: =AC14+'Hyp 2027'!F265 -> 36711476 | AP14: =AD14+'Hyp 2027'!G265 -> 1.5090142e+08 | AQ14: =AE14+'Hyp 2027'!H265 -> 1.8760338e+08 | AR14: =AF14+'Hyp 2027'!I265 -> 3.1465674e+08 | AS14: =SUM(AM14:AR14) -> 2.3765782e+09 | AT14: =AK14+AL14+AS14 -> 4.5133313e+09 | AW14: =AK14+'Hyp 2027'!B265 -> 1.4256803e+09 | AX14: =AL14+'Hyp 2027'!C265 -> 1.245261e+09 | AY14: =AM14+'Hyp 2027'!D265 -> 7607228.6 | AZ14: =AN14+'Hyp 2027'!E265 -> 2.1007743e+09 | BA14: =AO14+'Hyp 2027'!F265 -> 45889345 | BB14: =AP14+'Hyp 2027'!G265 -> 1.8862678e+08 | BC14: =AQ14+'Hyp 2027'!H265 -> 2.3450423e+08 | BD14: =AR14+'Hyp 2027'!I265 -> 3.9332092e+08 | BE14: =SUM(AY14:BD14) -> 2.9707228e+09 | BF14: =AW14+AX14+BE14 -> 5.6416642e+09 | BI14: =AW14+'Hyp 2027'!B265 -> 1.7108164e+09 | BJ14: =AX14+'Hyp 2027'!C265 -> 1.4943132e+09 | BK14: =AY14+'Hyp 2027'!D265 -> 9128674.3 | BL14: =AZ14+'Hyp 2027'!E265 -> 2.5209292e+09 | BM14: =BA14+'Hyp 2027'!F265 -> 55067214 | BN14: =BB14+'Hyp 2027'!G265 -> 2.2635213e+08 | BO14: =BC14+'Hyp 2027'!H265 -> 2.8140507e+08 | BP14: =BD14+'Hyp 2027'!I265 -> 4.7198511e+08 | BQ14: =SUM(BK14:BP14) -> 3.5648674e+09 | BR14: =BI14+BJ14+BQ14 -> 6.769997e+09 | BU14: =BI14+'Hyp 2027'!B265 -> 1.9959525e+09 | BV14: =BJ14+'Hyp 2027'!C265 -> 1.7433654e+09 | BW14: =BK14+'Hyp 2027'!D265 -> 10650120 | BX14: =BL14+'Hyp 2027'!E265 -> 2.941084e+09 | BY14: =BM14+'Hyp 2027'!F265 -> 64245083 | BZ14: =BN14+'Hyp 2027'!G265 -> 2.6407749e+08 | CA14: =BO14+'Hyp 2027'!H265 -> 3.2830592e+08 | CB14: =BP14+'Hyp 2027'!I265 -> 5.5064929e+08 | CC14: =SUM(BW14:CB14) -> 4.1590119e+09 | CD14: =BU14+BV14+CC14 -> 7.8983298e+09 | CG14: =BU14+'Hyp 2027'!B265 -> 2.2810886e+09 | CH14: =BV14+'Hyp 2027'!C265 -> 1.9924176e+09 | CI14: =BW14+'Hyp 2027'!D265 -> 12171566 | CJ14: =BX14+'Hyp 2027'!E265 -> 3.3612389e+09 | CK14: =BY14+'Hyp 2027'!F265 -> 73422952 | CL14: =BZ14+'Hyp 2027'!G265 -> 3.0180284e+08 | CM14: =CA14+'Hyp 2027'!H265 -> 3.7520676e+08 | CN14: =CB14+'Hyp 2027'!I265 -> 6.2931348e+08 | CO14: =SUM(CI14:CN14) -> 4.7531565e+09 | CP14: =CG14+CH14+CO14 -> 9.0266627e+09 | CS14: =CG14+'Hyp 2027'!B265 -> 2.5662246e+09 | CT14: =CH14+'Hyp 2027'!C265 -> 2.2414698e+09 | CU14: =CI14+'Hyp 2027'!D265 -> 13693011 | CV14: =CJ14+'Hyp 2027'!E265 -> 3.7813938e+09 | CW14: =CK14+'Hyp 2027'!F265 -> 82600821 | CX14: =CL14+'Hyp 2027'!G265 -> 3.395282e+08 | CY14: =CM14+'Hyp 2027'!H265 -> 4.2210761e+08 | CZ14: =CN14+'Hyp 2027'!I265 -> 7.0797766e+08 | DA14: =SUM(CU14:CZ14) -> 5.3473011e+09 | DB14: =CS14+CT14+DA14 -> 1.0154995e+10 | DE14: =CS14+'Hyp 2027'!B265 -> 2.8513607e+09 | DF14: =CT14+'Hyp 2027'!C265 -> 2.490522e+09 | DG14: =CU14+'Hyp 2027'!D265 -> 15214457 | DH14: =CV14+'Hyp 2027'!E265 -> 4.2015486e+09 | DI14: =CW14+'Hyp 2027'!F265 -> 91778689 | DJ14: =CX14+'Hyp 2027'!G265 -> 3.7725355e+08 | DK14: =CY14+'Hyp 2027'!H265 -> 4.6900845e+08 | DL14: =CZ14+'Hyp 2027'!I265 -> 7.8664185e+08 | DM14: =DA14*(1+'Hyp 2027'!J265) -> 6.0335354e+18 | DN14: =DE14+DF14+DM14 -> 6.0335354e+18 | DQ14: =DE14+'Hyp 2027'!B265 -> 3.1364968e+09 | DR14: =DF14+'Hyp 2027'!C265 -> 2.7395742e+09 | DS14: =DG14+'Hyp 2027'!D265 -> 16735903 | DT14: =DH14+'Hyp 2027'!E265 -> 4.6217035e+09 | DU14: =DI14+'Hyp 2027'!F265 -> 1.0095656e+08 | DV14: =DJ14+'Hyp 2027'!G265 -> 4.1497891e+08 | DW14: =DK14+'Hyp 2027'!H265 -> 5.159093e+08 | DX14: =DL14+'Hyp 2027'!I265 -> 8.6530603e+08 | DY14: =SUM(DS14:DX14) -> 6.5355902e+09 | DZ14: =DQ14+DR14+DY14 -> 1.2411661e+10 | EC14: =DQ14+'Hyp 2027'!B265 -> 3.4216328e+09 | ED14: =DR14+'Hyp 2027'!C265 -> 2.9886264e+09 | EE14: =DS14+'Hyp 2027'!D265 -> 18257349 | EF14: =DT14+'Hyp 2027'!E265 -> 5.0418583e+09 | EG14: =DU14+'Hyp 2027'!F265 -> 1.1013443e+08 | EH14: =DV14+'Hyp 2027'!G265 -> 4.5270426e+08 | EI14: =DW14+'Hyp 2027'!H265 -> 5.6281014e+08 | EJ14: =DX14+'Hyp 2027'!I265 -> 9.4397021e+08 | EK14: =SUM(EE14:EJ14) -> 7.1297347e+09 | EL14: =EC14+ED14+EK14 -> 1.3539994e+10
A15: Sinistres payés Ant. | J15: =SUM(D15:I15) -> 0 | K15: =B15+C15+J15 -> 0 | M15: =B15*(1+M$118) -> 0 | N15: =C15*(1+N$118) -> 0 | O15: =D15*(1+O$118) -> 0 | P15: =E15*(1+P$118) -> 0 | Q15: =F15*(1+Q$118) -> 0 | R15: =G15*(1+R$118) -> 0 | S15: =H15*(1+S$118) -> 0 | T15: =I15*(1+T$118) -> 0 | U15: =SUM(O15:T15) -> 0 | V15: =M15+N15+U15 -> 0 | AG15: =SUM(AA15:AF15) -> 0 | AH15: =Y15+Z15+AG15 -> 0 | AS15: =SUM(AM15:AR15) -> 0 | AT15: =AK15+AL15+AS15 -> 0 | BE15: =SUM(AY15:BD15) -> 0 | BF15: =AW15+AX15+BE15 -> 0 | BQ15: =SUM(BK15:BP15) -> 0 | BR15: =BI15+BJ15+BQ15 -> 0 | CC15: =SUM(BW15:CB15) -> 0 | CD15: =BU15+BV15+CC15 -> 0 | CG15: =BU15*CG140 -> 0 | CH15: =BV15*CH140 -> 0 | CI15: =BW15*CI140 -> 0 | CJ15: =BX15*CJ140 -> 0 | CK15: =BY15*CK140 -> 0 | CL15: =BZ15*CL140 -> 0 | CM15: =CA15*CM140 -> 0 | CN15: =CB15*CN140 -> 0 | CO15: =SUM(CI15:CN15) -> 0 | CP15: =CG15+CH15+CO15 -> 0 | CS15: =CG15*CS140 -> 0 | CT15: =CH15*CT140 -> 0 | CU15: =CI15*CU140 -> 0 | CV15: =CJ15*CV140 -> 0 | CW15: =CK15*CW140 -> 0 | CX15: =CL15*CX140 -> 0 | CY15: =CM15*CY140 -> 0 | CZ15: =CN15*CZ140 -> 0 | DA15: =SUM(CU15:CZ15) -> 0 | DB15: =CS15+CT15+DA15 -> 0 | DE15: =CS15*DE140 -> 0 | DF15: =CT15*DF140 -> 0 | DG15: =CU15*DG140 -> 0 | DH15: =CV15*DH140 -> 0 | DI15: =CW15*DI140 -> 0 | DJ15: =CX15*DJ140 -> 0 | DK15: =CY15*DK140 -> 0 | DL15: =CZ15*DL140 -> 0 | DM15: =SUM(DG15:DL15) -> 0 | DN15: =DE15+DF15+DM15 -> 0 | DQ15: =DE15*DQ140 -> 0 | DR15: =DF15*DR140 -> 0 | DS15: =DG15*DS140 -> 0 | DT15: =DH15*DT140 -> 0 | DU15: =DI15*DU140 -> 0 | DV15: =DJ15*DV140 -> 0 | DW15: =DK15*DW140 -> 0 | DX15: =DL15*DX140 -> 0 | DY15: =SUM(DS15:DX15) -> 0 | DZ15: =DQ15+DR15+DY15 -> 0 | EC15: =DQ15*EC140 -> 0 | ED15: =DR15*ED140 -> 0 | EE15: =DS15*EE140 -> 0 | EF15: =DT15*EF140 -> 0 | EG15: =DU15*EG140 -> 0 | EH15: =DV15*EH140 -> 0 | EI15: =DW15*EI140 -> 0 | EJ15: =DX15*EJ140 -> 0 | EK15: =SUM(EE15:EJ15) -> 0 | EL15: =EC15+ED15+EK15 -> 0
A16: Sinistres Payés net des recours | B16: =B14+B15 -> 2.8513607e+08 | C16: =C14+C15 -> 2.490522e+08 | D16: =D14+D15 -> 1521445.7 | E16: =E14+E15 -> 4.2015486e+08 | F16: =F14+F15 -> 9177868.9 | G16: =G14+G15 -> 37725355 | H16: =H14+H15 -> 46900845 | I16: =I14+I15 -> 78664185 | ... K16: =K14+K15 -> 1.1283328e+09 | M16: =M14+M15 -> 5.7027214e+08 | N16: =N14+N15 -> 4.981044e+08 | O16: =O14+O15 -> 3042891.4 | P16: =P14+P15 -> 8.4030972e+08 | Q16: =Q14+Q15 -> 18355738 | R16: =R14+R15 -> 75450710 | S16: =S14+S15 -> 93801691 | T16: =T14+T15 -> 1.5732837e+08 | ... V16: =V14+V15 -> 2.2566657e+09 | Y16: =Y14+Y15 -> 8.5540821e+08 | Z16: =Z14+Z15 -> 7.4715661e+08 | AA16: =AA14+AA15 -> 4564337.1 | AB16: =AB14+AB15 -> 1.2604646e+09 | AC16: =AC14+AC15 -> 27533607 | AD16: =AD14+AD15 -> 1.1317607e+08 | AE16: =AE14+AE15 -> 1.4070254e+08 | AF16: =AF14+AF15 -> 2.3599255e+08 | ... AH16: =AH14+AH15 -> 3.3849985e+09 | AK16: =AK14+AK15 -> 1.1405443e+09 | AL16: =AL14+AL15 -> 9.9620881e+08 | AM16: =AM14+AM15 -> 6085782.9 | AN16: =AN14+AN15 -> 1.6806194e+09 | AO16: =AO14+AO15 -> 36711476 | AP16: =AP14+AP15 -> 1.5090142e+08 | AQ16: =AQ14+AQ15 -> 1.8760338e+08 | AR16: =AR14+AR15 -> 3.1465674e+08 | ... AT16: =AT14+AT15 -> 4.5133313e+09 | AW16: =AW14+AW15 -> 1.4256803e+09 | AX16: =AX14+AX15 -> 1.245261e+09 | AY16: =AY14+AY15 -> 7607228.6 | AZ16: =AZ14+AZ15 -> 2.1007743e+09 | BA16: =BA14+BA15 -> 45889345 | BB16: =BB14+BB15 -> 1.8862678e+08 | BC16: =BC14+BC15 -> 2.3450423e+08 | BD16: =BD14+BD15 -> 3.9332092e+08 | ... BF16: =BF14+BF15 -> 5.6416642e+09 | BI16: =BI14+BI15 -> 1.7108164e+09 | BJ16: =BJ14+BJ15 -> 1.4943132e+09 | BK16: =BK14+BK15 -> 9128674.3 | BL16: =BL14+BL15 -> 2.5209292e+09 | BM16: =BM14+BM15 -> 55067214 | BN16: =BN14+BN15 -> 2.2635213e+08 | BO16: =BO14+BO15 -> 2.8140507e+08 | BP16: =BP14+BP15 -> 4.7198511e+08 | ... BR16: =BR14+BR15 -> 6.769997e+09 | BU16: =BU14+BU15 -> 1.9959525e+09 | BV16: =BV14+BV15 -> 1.7433654e+09 | BW16: =BW14+BW15 -> 10650120 | BX16: =BX14+BX15 -> 2.941084e+09 | BY16: =BY14+BY15 -> 64245083 | BZ16: =BZ14+BZ15 -> 2.6407749e+08 | CA16: =CA14+CA15 -> 3.2830592e+08 | CB16: =CB14+CB15 -> 5.5064929e+08 | ... CD16: =CD14+CD15 -> 7.8983298e+09 | CG16: =CG14+CG15 -> 2.2810886e+09 | CH16: =CH14+CH15 -> 1.9924176e+09 | CI16: =CI14+CI15 -> 12171566 | CJ16: =CJ14+CJ15 -> 3.3612389e+09 | CK16: =CK14+CK15 -> 73422952 | CL16: =CL14+CL15 -> 3.0180284e+08 | CM16: =CM14+CM15 -> 3.7520676e+08 | CN16: =CN14+CN15 -> 6.2931348e+08 | ... CP16: =CP14+CP15 -> 9.0266627e+09 | CS16: =CS14+CS15 -> 2.5662246e+09 | CT16: =CT14+CT15 -> 2.2414698e+09 | CU16: =CU14+CU15 -> 13693011 | CV16: =CV14+CV15 -> 3.7813938e+09 | CW16: =CW14+CW15 -> 82600821 | CX16: =CX14+CX15 -> 3.395282e+08 | CY16: =CY14+CY15 -> 4.2210761e+08 | CZ16: =CZ14+CZ15 -> 7.0797766e+08 | ... DB16: =DB14+DB15 -> 1.0154995e+10 | DE16: =DE14+DE15 -> 2.8513607e+09 | DF16: =DF14+DF15 -> 2.490522e+09 | DG16: =DG14+DG15 -> 15214457 | DH16: =DH14+DH15 -> 4.2015486e+09 | DI16: =DI14+DI15 -> 91778689 | DJ16: =DJ14+DJ15 -> 3.7725355e+08 | DK16: =DK14+DK15 -> 4.6900845e+08 | DL16: =DL14+DL15 -> 7.8664185e+08 | ... DN16: =DN14+DN15 -> 6.0335354e+18 | DQ16: =DQ14+DQ15 -> 3.1364968e+09 | DR16: =DR14+DR15 -> 2.7395742e+09 | DS16: =DS14+DS15 -> 16735903 | DT16: =DT14+DT15 -> 4.6217035e+09 | DU16: =DU14+DU15 -> 1.0095656e+08 | DV16: =DV14+DV15 -> 4.1497891e+08 | DW16: =DW14+DW15 -> 5.159093e+08 | DX16: =DX14+DX15 -> 8.6530603e+08 | ... DZ16: =DZ14+DZ15 -> 1.2411661e+10 | EC16: =EC14+EC15 -> 3.4216328e+09 | ED16: =ED14+ED15 -> 2.9886264e+09 | EE16: =EE14+EE15 -> 18257349 | EF16: =EF14+EF15 -> 5.0418583e+09 | EG16: =EG14+EG15 -> 1.1013443e+08 | EH16: =EH14+EH15 -> 4.5270426e+08 | EI16: =EI14+EI15 -> 5.6281014e+08 | EJ16: =EJ14+EJ15 -> 9.4397021e+08 | ... EL16: =EL14+EL15 -> 1.3539994e+10
A18: Commisions | B18: =B7*'Hyp 2027'!B206 -> 2.8933599e+08 | C18: =C7*'Hyp 2027'!C206 -> 2.6289225e+08 | D18: =D7*'Hyp 2027'!D206 -> 2284409.8 | E18: =E7*'Hyp 2027'!E206 -> 1.3164869e+08 | F18: =F7*'Hyp 2027'!F206 -> 14407617 | G18: =G7*'Hyp 2027'!G206 -> 5478482.6 | H18: =H7*'Hyp 2027'!H206 -> 86839861 | I18: =I7*'Hyp 2027'!I206 -> 3831707.1 | J18: =SUM(D18:I18) -> 2.4449077e+08 | K18: =B18+C18+J18 -> 7.9671901e+08 | L18: ok | M18: =M7*'Hyp 2027'!B207 -> 3.058679e+08 | N18: =N7*'Hyp 2027'!C207 -> 2.8541947e+08 | O18: =O7*'Hyp 2027'!D207 -> 6654772 | P18: =P7*'Hyp 2027'!E207 -> 5.2586342e+08 | Q18: =Q7*'Hyp 2027'!F207 -> 58567754 | R18: =R7*'Hyp 2027'!G207 -> 29043706 | S18: =S7*'Hyp 2027'!H207 -> 1.7628145e+08 | T18: =T7*'Hyp 2027'!I207 -> 1.9971079e+08 | U18: =SUM(O18:T18) -> 9.9612189e+08 | V18: =M18+N18+U18 -> 1.5874093e+09 | Y18: =Y7*'Hyp 2027'!B208 -> 4.5500919e+08 | Z18: =Z7*'Hyp 2027'!C208 -> 3.563379e+08 | AA18: =AA7*'Hyp 2027'!D208 -> 6845621.4 | AB18: =AB7*'Hyp 2027'!E208 -> 6.8681066e+08 | AC18: =AC7*'Hyp 2027'!F208 -> 85425129 | AD18: =AD7*'Hyp 2027'!G208 -> 33053886 | AE18: =AE7*'Hyp 2027'!H208 -> 2.396915e+08 | AF18: =AF7*'Hyp 2027'!I208 -> 2.5817722e+08 | AG18: =SUM(AA18:AF18) -> 1.310004e+09 | AH18: =Y18+Z18+AG18 -> 2.1213511e+09 | AK18: ='Hyp 2027'!B209*AK7 -> 4.8901483e+08 | AL18: ='Hyp 2027'!C209*AL7 -> 3.8568469e+08 | AM18: ='Hyp 2027'!D209*AM7 -> 9480095.8 | AN18: ='Hyp 2027'!E209*AN7 -> 9.0763237e+08 | AO18: ='Hyp 2027'!F209*AO7 -> 1.0553262e+08 | AP18: ='Hyp 2027'!G209*AP7 -> 96840590 | AQ18: ='Hyp 2027'!H209*AQ7 -> 2.7574275e+08 | AR18: ='Hyp 2027'!I209*AR7 -> 2.6134773e+08 | AS18: =SUM(AM18:AR18) -> 1.6565762e+09 | AT18: =AK18+AL18+AS18 -> 2.5312757e+09 | AW18: =AW7*'Hyp 2027'!B210 -> 6.1286128e+08 | AX18: =AX7*'Hyp 2027'!C210 -> 4.4533993e+08 | AY18: =AY7*'Hyp 2027'!D210 -> 12899708 | AZ18: =AZ7*'Hyp 2027'!E210 -> 9.6473661e+08 | BA18: =BA7*'Hyp 2027'!F210 -> 1.3047392e+08 | BB18: =BB7*'Hyp 2027'!G210 -> 1.1447044e+08 | BC18: =BC7*'Hyp 2027'!H210 -> 1.9635179e+08 | BD18: =BD7*'Hyp 2027'!I210 -> 3.5351681e+08 | BE18: ='Hyp 2027'!J82*'Hyp 2027'!J166 -> 0 | BF18: =AW18+AX18+BE18 -> 1.0582012e+09 | BI18: =BI7*'Hyp 2027'!B211 -> 6.6150726e+08 | BJ18: =BJ7*'Hyp 2027'!C211 -> 4.6376177e+08 | BK18: =BK7*'Hyp 2027'!D211 -> 16147775 | BL18: =BL7*'Hyp 2027'!E211 -> 1.1110123e+09 | BM18: =BM7*'Hyp 2027'!F211 -> 1.3287997e+08 | BN18: =BN7*'Hyp 2027'!G211 -> 1.2141552e+08 | BO18: =BO7*'Hyp 2027'!H211 -> 2.0621319e+08 | BP18: =BP7*'Hyp 2027'!I211 -> 3.7608409e+08 | BQ18: =SUM(BK18:BP18) -> 1.9637528e+09 | BR18: =BI18+BJ18+BQ18 -> 3.0890219e+09 | BU18: =BU7*'Hyp 2027'!B212 -> 7.0597512e+08 | BV18: =BV7*'Hyp 2027'!C212 -> 4.9102774e+08 | BW18: =BW7*'Hyp 2027'!D212 -> 17208804 | BX18: =BX7*'Hyp 2027'!E212 -> 1.127948e+09 | BY18: =BY7*'Hyp 2027'!F212 -> 1.409787e+08 | BZ18: =BZ7*'Hyp 2027'!G212 -> 1.2748256e+08 | CA18: =CA7*'Hyp 2027'!H212 -> 2.1514244e+08 | CB18: =CB7*'Hyp 2027'!I212 -> 3.9988129e+08 | CC18: =SUM(BW18:CB18) -> 2.0286418e+09 | CD18: =BU18+BV18+CC18 -> 3.2256447e+09 | CG18: =CG7*'Hyp 2027'!B169 -> 1.0633756e+09 | CH18: =CH7*'Hyp 2027'!C169 -> 5.3765967e+08 | CI18: =CI7*'Hyp 2027'!D169 -> 17677519 | CJ18: =CJ7*'Hyp 2027'!E169 -> 1.0472973e+09 | CK18: =CK7*'Hyp 2027'!F169 -> 1.0792026e+08 | CL18: =CL7*'Hyp 2027'!G169 -> 2.1981041e+08 | CM18: =CM7*'Hyp 2027'!H169 -> 2.6546557e+08 | CN18: =CN7*'Hyp 2027'!I169 -> 4.1104925e+08 | CO18: =SUM(CI18:CN18) -> 2.0692203e+09 | CP18: =CG18+CH18+CO18 -> 3.6702555e+09 | CS18: =CS7*'Hyp 2027'!B169 -> 1.127958e+09 | CT18: =CT7*'Hyp 2027'!C169 -> 5.6259375e+08 | CU18: =CU7*'Hyp 2027'!D169 -> 18122446 | CV18: =CV7*'Hyp 2027'!E169 -> 1.1107501e+09 | CW18: =CW7*'Hyp 2027'!F169 -> 1.0849804e+08 | CX18: =CX7*'Hyp 2027'!G169 -> 2.6183853e+08 | CY18: =CY7*'Hyp 2027'!H169 -> 2.7328225e+08 | CZ18: =CZ7*'Hyp 2027'!I169 -> 4.4148898e+08 | DA18: =SUM(CU18:CZ18) -> 2.2139804e+09 | DB18: =CS18+CT18+DA18 -> 3.9045321e+09 | DE18: =DE7*'Hyp 2027'!B169 -> 1.2067811e+09 | DF18: =DF7*'Hyp 2027'!C169 -> 6.0201175e+08 | DG18: =DG7*'Hyp 2027'!D169 -> 18990149 | DH18: =DH7*'Hyp 2027'!E169 -> 1.157914e+09 | DI18: =DI7*'Hyp 2027'!F169 -> 1.0997553e+08 | DJ18: =DJ7*'Hyp 2027'!G169 -> 2.6646666e+08 | DK18: =DK7*'Hyp 2027'!H169 -> 2.934589e+08 | DL18: =DL7*'Hyp 2027'!I169 -> 4.7258089e+08 | DM18: =SUM(DG18:DL18) -> 2.3193861e+09 | DN18: =DE18+DF18+DM18 -> 4.1281789e+09 | DQ18: =DQ7*'Hyp 2027'!B169 -> 1.2834919e+09 | DR18: =DR7*'Hyp 2027'!C169 -> 6.3019492e+08 | DS18: =DS7*'Hyp 2027'!D169 -> 19705428 | DT18: =DT7*'Hyp 2027'!E169 -> 1.176951e+09 | DU18: =DU7*'Hyp 2027'!F169 -> 1.1598299e+08 | DV18: =DV7*'Hyp 2027'!G169 -> 2.7647594e+08 | DW18: =DW7*'Hyp 2027'!H169 -> 3.4423599e+08 | DX18: =DX7*'Hyp 2027'!I169 -> 5.1579732e+08 | DY18: =SUM(DS18:DX18) -> 2.4491487e+09 | DZ18: =DQ18+DR18+DY18 -> 4.3628355e+09 | EC18: ='Hyp 2027'!B169*'Direct Local'!EC7 -> 1.3424177e+09 | ED18: ='Hyp 2027'!C169*'Direct Local'!ED7 -> 6.3810494e+08 | EE18: ='Hyp 2027'!D169*'Direct Local'!EE7 -> 21104246 | EF18: ='Hyp 2027'!E169*'Direct Local'!EF7 -> 1.2064072e+09 | EG18: ='Hyp 2027'!F169*'Direct Local'!EG7 -> 1.2425175e+08 | EH18: ='Hyp 2027'!G169*'Direct Local'!EH7 -> 2.8200432e+08 | EI18: ='Hyp 2027'!H169*'Direct Local'!EI7 -> 3.5542921e+08 | EJ18: ='Hyp 2027'!I169*'Direct Local'!EJ7 -> 5.3334201e+08 | EK18: =SUM(EE18:EJ18) -> 2.5225387e+09 | EL18: =EC18+ED18+EK18 -> 4.5030614e+09
A20: REC Ouverture | B20: ='Hyp 2027'!B$177 -> 1.5613983e+09 | C20: ='Hyp 2027'!C$177 -> 6.6162882e+08 | D20: ='Hyp 2027'!D$177 -> 6179130.4 | E20: ='Hyp 2027'!E$177 -> 36234141 | F20: ='Hyp 2027'!F$177 -> 1.1343105e+08 | G20: ='Hyp 2027'!G$177 -> 88631742 | H20: ='Hyp 2027'!H$177 -> -24009431 | I20: ='Hyp 2027'!I$177 -> 64790567 | J20: =SUM(D20:I20) -> 2.852572e+08 | K20: =B20+C20+J20 -> 2.5082843e+09 | L20: ok | M20: =B20 -> 1.5613983e+09 | N20: =C20 -> 6.6162882e+08 | O20: =D20 -> 6179130.4 | P20: =E20 -> 36234141 | Q20: =F20 -> 1.1343105e+08 | R20: =G20 -> 88631742 | S20: =H20 -> -24009431 | T20: =I20 -> 64790567 | U20: =SUM(O20:T20) -> 2.852572e+08 | V20: =M20+N20+U20 -> 2.5082843e+09 | W20: =V20=K20 -> TRUE | Y20: =M20 -> 1.5613983e+09 | Z20: =N20 -> 6.6162882e+08 | AA20: =O20 -> 6179130.4 | AB20: =P20 -> 36234141 | AC20: =Q20 -> 1.1343105e+08 | AD20: =R20 -> 88631742 | AE20: =S20 -> -24009431 | AF20: =T20 -> 64790567 | AG20: =SUM(AA20:AF20) -> 2.852572e+08 | AH20: =Y20+Z20+AG20 -> 2.5082843e+09 | AI20: =AH20=V20 -> TRUE | AK20: ='Hyp 2027'!B$177 -> 1.5613983e+09 | AL20: ='Hyp 2027'!C$177 -> 6.6162882e+08 | AM20: ='Hyp 2027'!D$177 -> 6179130.4 | AN20: ='Hyp 2027'!E$177 -> 36234141 | AO20: ='Hyp 2027'!F$177 -> 1.1343105e+08 | AP20: ='Hyp 2027'!G$177 -> 88631742 | AQ20: ='Hyp 2027'!H$177 -> -24009431 | AR20: ='Hyp 2027'!I$177 -> 64790567 | AS20: =SUM(AM20:AR20) -> 2.852572e+08 | AT20: =AK20+AL20+AS20 -> 2.5082843e+09 | AU20: =AT20=AH20 -> TRUE | AW20: ='Hyp 2027'!B$177 -> 1.5613983e+09 | AX20: ='Hyp 2027'!C$177 -> 6.6162882e+08 | AY20: ='Hyp 2027'!D$177 -> 6179130.4 | AZ20: ='Hyp 2027'!E$177 -> 36234141 | BA20: ='Hyp 2027'!F$177 -> 1.1343105e+08 | BB20: ='Hyp 2027'!G$177 -> 88631742 | BC20: ='Hyp 2027'!H$177 -> -24009431 | BD20: ='Hyp 2027'!I$177 -> 64790567 | BE20: =SUM(AY20:BD20) -> 2.852572e+08 | BF20: =AW20+AX20+BE20 -> 2.5082843e+09 | BG20: =BF20=AT20 -> TRUE | BI20: ='Hyp 2027'!B$177 -> 1.5613983e+09 | BJ20: ='Hyp 2027'!C$177 -> 6.6162882e+08 | BK20: ='Hyp 2027'!D$177 -> 6179130.4 | BL20: ='Hyp 2027'!E$177 -> 36234141 | BM20: ='Hyp 2027'!F$177 -> 1.1343105e+08 | BN20: ='Hyp 2027'!G$177 -> 88631742 | BO20: ='Hyp 2027'!H$177 -> -24009431 | BP20: ='Hyp 2027'!I$177 -> 64790567 | BQ20: =SUM(BK20:BP20) -> 2.852572e+08 | BR20: =BI20+BJ20+BQ20 -> 2.5082843e+09 | BU20: =BI20 -> 1.5613983e+09 | BV20: =BJ20 -> 6.6162882e+08 | BW20: =BK20 -> 6179130.4 | BX20: =BL20 -> 36234141 | BY20: =BM20 -> 1.1343105e+08 | BZ20: =BN20 -> 88631742 | CA20: =BO20 -> -24009431 | CB20: =BP20 -> 64790567 | CC20: =SUM(BW20:CB20) -> 2.852572e+08 | CD20: =BU20+BV20+CC20 -> 2.5082843e+09 | CE20: =CD20=BR20 -> TRUE | CG20: =BU20 -> 1.5613983e+09 | CH20: =BV20 -> 6.6162882e+08 | CI20: =BW20 -> 6179130.4 | CJ20: =BX20 -> 36234141 | CK20: =BY20 -> 1.1343105e+08 | CL20: =BZ20 -> 88631742 | CM20: =CA20 -> -24009431 | CN20: =CB20 -> 64790567 | CO20: =SUM(CI20:CN20) -> 2.852572e+08 | CP20: =CG20+CH20+CO20 -> 2.5082843e+09 | CS20: =CG20 -> 1.5613983e+09 | CT20: =CH20 -> 6.6162882e+08 | CU20: =CI20 -> 6179130.4 | CV20: =CJ20 -> 36234141 | CW20: =CK20 -> 1.1343105e+08 | CX20: =CL20 -> 88631742 | CY20: =CM20 -> -24009431 | CZ20: =CN20 -> 64790567 | DA20: =SUM(CU20:CZ20) -> 2.852572e+08 | DB20: =CS20+CT20+DA20 -> 2.5082843e+09 | DE20: =CS20 -> 1.5613983e+09 | DF20: =CT20 -> 6.6162882e+08 | DG20: =CU20 -> 6179130.4 | DH20: =CV20 -> 36234141 | DI20: =CW20 -> 1.1343105e+08 | DJ20: =CX20 -> 88631742 | DK20: =CY20 -> -24009431 | DL20: =CZ20 -> 64790567 | DM20: =SUM(DG20:DL20) -> 2.852572e+08 | DN20: =DE20+DF20+DM20 -> 2.5082843e+09 | DQ20: =DE20 -> 1.5613983e+09 | DR20: =DF20 -> 6.6162882e+08 | DS20: =DG20 -> 6179130.4 | DT20: =DH20 -> 36234141 | DU20: =DI20 -> 1.1343105e+08 | DV20: =DJ20 -> 88631742 | DW20: =DK20 -> -24009431 | DX20: =DL20 -> 64790567 | DY20: =SUM(DS20:DX20) -> 2.852572e+08 | DZ20: =DQ20+DR20+DY20 -> 2.5082843e+09 | EC20: =DQ20 -> 1.5613983e+09 | ED20: =DR20 -> 6.6162882e+08 | EE20: =DS20 -> 6179130.4 | EF20: =DT20 -> 36234141 | EG20: =DU20 -> 1.1343105e+08 | EH20: =DV20 -> 88631742 | EI20: =DW20 -> -24009431 | EJ20: =DX20 -> 64790567 | EK20: =DY20 -> 2.852572e+08 | EL20: =EC20+ED20+EK20 -> 2.5082843e+09
A21: REC Clôture | B21: =B7*'Hyp 2027'!B315 -> 2.1710107e+09 | C21: =C7*'Hyp 2027'!C315 -> 1.6393341e+09 | D21: =D7*'Hyp 2027'!D315 -> 13611705 | E21: =E7*'Hyp 2027'!E315 -> 4.9420916e+08 | F21: =F7*'Hyp 2027'!F315 -> 56119663 | G21: =G7*'Hyp 2027'!G315 -> 46087732 | H21: =H7*'Hyp 2027'!H315 -> 8.6722088e+08 | I21: =I7*'Hyp 2027'!I315 -> 54105979 | J21: =J20+'Hyp 2027'!J65*'Hyp 2027'!J166 -> 2.852572e+08 | K21: =B21+C21+J21 -> 4.0956021e+09 | M21: =M7*'Hyp 2027'!B316 -> 2.8290977e+09 | N21: =N7*'Hyp 2027'!C316 -> 1.5757505e+09 | O21: =O7*'Hyp 2027'!D316 -> 22937551 | P21: =P7*'Hyp 2027'!E316 -> 7.8840821e+08 | Q21: =Q7*'Hyp 2027'!F316 -> 3.1263436e+08 | R21: =R7*'Hyp 2027'!G316 -> 48469452 | S21: =S7*'Hyp 2027'!H316 -> 2.2361555e+08 | T21: =T7*'Hyp 2027'!I316 -> 6.9278278e+08 | U21: =SUM(O21:T21) -> 2.0888479e+09 | V21: =M21+N21+U21 -> 6.493696e+09 | Y21: =Y7*'Hyp 2027'!B317 -> 2.3903706e+09 | Z21: =Z7*'Hyp 2027'!C317 -> 1.4806352e+09 | AA21: =AA7*'Hyp 2027'!D317 -> 20111403 | AB21: =AB7*'Hyp 2027'!E317 -> 1.2172012e+09 | AC21: =AC7*'Hyp 2027'!F317 -> 98165146 | AD21: =AD7*'Hyp 2027'!G317 -> 86735082 | AE21: =AE7*'Hyp 2027'!H317 -> 1.5940633e+08 | AF21: =AF7*'Hyp 2027'!I317 -> 2.6280436e+08 | AG21: =SUM(AA21:AF21) -> 1.8444236e+09 | AH21: =Y21+Z21+AG21 -> 5.7154294e+09 | AK21: ='Hyp 2027'!B318*AK7 -> 2.4631061e+09 | AL21: ='Hyp 2027'!C318*AL7 -> 1.3509859e+09 | AM21: ='Hyp 2027'!D318*AM7 -> 23634524 | AN21: ='Hyp 2027'!E318*AN7 -> 7.3491819e+08 | AO21: ='Hyp 2027'!F318*AO7 -> 1.3821676e+08 | AP21: ='Hyp 2027'!G318*AP7 -> 1.1345685e+08 | AQ21: ='Hyp 2027'!H318*AQ7 -> 2.0680706e+08 | AR21: ='Hyp 2027'!I318*AR7 -> 2.5376047e+08 | AS21: =SUM(AM21:AR21) -> 1.4707939e+09 | AT21: =AK21+AL21+AS21 -> 5.2848859e+09 | AW21: =AW7*'Hyp 2027'!B319 -> 2.7971378e+09 | AX21: =AX7*'Hyp 2027'!C319 -> 1.3215068e+09 | AY21: =AY7*'Hyp 2027'!D319 -> 25212992 | AZ21: =AZ7*'Hyp 2027'!E319 -> 9.1360784e+08 | BA21: =BA7*'Hyp 2027'!F319 -> 1.3879017e+08 | BB21: =BB7*'Hyp 2027'!G319 -> 1.2371825e+08 | BC21: =BC7*'Hyp 2027'!H319 -> 3.2912212e+08 | BD21: =BD7*'Hyp 2027'!I319 -> 3.8846661e+08 | BE21: =SUM(AY21:BD21) -> 1.918918e+09 | BF21: =AW21+AX21+BE21 -> 6.0375626e+09 | BI21: =BI7*'Hyp 2027'!B320 -> 2.6154072e+09 | BJ21: =BJ7*'Hyp 2027'!C320 -> 1.1402189e+09 | BK21: =BK7*'Hyp 2027'!D320 -> 27394916 | BL21: =BL7*'Hyp 2027'!E320 -> 8.7180114e+08 | BM21: =BM7*'Hyp 2027'!F320 -> 1.6112846e+08 | BN21: =BN7*'Hyp 2027'!G320 -> 1.2020842e+08 | BO21: =BO7*'Hyp 2027'!H320 -> 3.472604e+08 | BP21: =BP7*'Hyp 2027'!I320 -> 6.4995247e+08 | BQ21: =SUM(BK21:BP21) -> 2.1777458e+09 | BR21: =BI21+BJ21+BQ21 -> 5.9333719e+09 | BU21: =BU7*'Hyp 2027'!B321 -> 2.4142136e+09 | BV21: =BV7*'Hyp 2027'!C321 -> 9.4907547e+08 | BW21: =BW7*'Hyp 2027'!D321 -> 24451060 | BX21: =BX7*'Hyp 2027'!E321 -> 8.3618047e+08 | BY21: =BY7*'Hyp 2027'!F321 -> 1.6678163e+08 | BZ21: =BZ7*'Hyp 2027'!G321 -> 1.2097443e+08 | CA21: =CA7*'Hyp 2027'!H321 -> 3.4025948e+08 | CB21: ='Hyp 2027'!I275*5/12+'Hyp 2027'!I276*6/12+'Hyp 2027'!I277*7/12+'Hyp 2027'!I278*8/12+'Hyp 2027'!I279*9/12+'Hyp 2027'!I280*10/12+'Hyp 2027'!I281*11/12 -> 1.2668648e+09 | CC21: =SUM(BW21:CB21) -> 2.7555119e+09 | CD21: =BU21+BV21+CC21 -> 6.118801e+09 | CG21: =CG7*'Hyp 2027'!B322 -> 2.4941585e+09 | CH21: =CH7*'Hyp 2027'!C322 -> 9.1565238e+08 | CI21: =CI7*'Hyp 2027'!D322 -> 21025392 | CJ21: =CJ7*'Hyp 2027'!E322 -> 6.8818282e+08 | CK21: =CK7*'Hyp 2027'!F322 -> 1.7873736e+08 | CL21: =CL7*'Hyp 2027'!G322 -> 2.7735898e+08 | CM21: =CM7*'Hyp 2027'!H322 -> 2.7752772e+08 | CN21: =CN7*'Hyp 2027'!I322 -> 5.1075295e+08 | CO21: =SUM(CI21:CN21) -> 1.9535852e+09 | CP21: =CG21+CH21+CO21 -> 5.3633961e+09 | CS21: =CS7*'Hyp 2027'!B323 -> 2.3293036e+09 | CT21: =CT7*'Hyp 2027'!C323 -> 8.7201776e+08 | CU21: =CU7*'Hyp 2027'!D323 -> 17893196 | CV21: =CV7*'Hyp 2027'!E323 -> 5.5826828e+08 | CW21: =CW7*'Hyp 2027'!F323 -> 1.6701361e+08 | CX21: =CX7*'Hyp 2027'!G323 -> 2.7869616e+08 | CY21: =CY7*'Hyp 2027'!H323 -> 2.0826539e+08 | CZ21: =CZ7*'Hyp 2027'!I323 -> 4.2889067e+08 | DA21: =SUM(CU21:CZ21) -> 1.6590273e+09 | DB21: =CS21+CT21+DA21 -> 4.8603487e+09 | DE21: ='Hyp 2027'!B324*DE7 -> 2.1536387e+09 | DF21: ='Hyp 2027'!C324*DF7 -> 8.4098487e+08 | DG21: ='Hyp 2027'!D324*DG7 -> 14913228 | DH21: ='Hyp 2027'!E324*DH7 -> 4.0307666e+08 | DI21: ='Hyp 2027'!F324*DI7 -> 1.5643462e+08 | DJ21: ='Hyp 2027'!G324*DJ7 -> 2.3101421e+08 | DK21: ='Hyp 2027'!H324*DK7 -> 1.4049058e+08 | DL21: ='Hyp 2027'!I324*DL7 -> 3.3098102e+08 | DM21: =SUM(DG21:DL21) -> 1.2769103e+09 | DN21: =DE21+DF21+DM21 -> 4.2715339e+09 | DQ21: =DQ7*'Hyp 2027'!B325 -> 1.9305851e+09 | DR21: =DR7*'Hyp 2027'!C325 -> 7.8391182e+08 | DS21: =DS7*'Hyp 2027'!D325 -> 11493739 | DT21: =DT7*'Hyp 2027'!E325 -> 2.2786596e+08 | DU21: =DU7*'Hyp 2027'!F325 -> 1.5142448e+08 | DV21: =DV7*'Hyp 2027'!G325 -> 1.8510762e+08 | DW21: =DW7*'Hyp 2027'!H325 -> 67260779 | DX21: =DX7*'Hyp 2027'!I325 -> 2.214184e+08 | DY21: =SUM(DS21:DX21) -> 8.6457098e+08 | DZ21: =DQ21+DR21+DY21 -> 3.5790679e+09 | EC21: =EC7*'Hyp 2027'!B326 -> 1.6427409e+09 | ED21: =ED7*'Hyp 2027'!C326 -> 6.96097e+08 | EE21: =EE7*'Hyp 2027'!D326 -> 8045820.6 | EF21: =EF7*'Hyp 2027'!E326 -> 47180328 | EG21: =EG7*'Hyp 2027'!F326 -> 1.4769811e+08 | EH21: =EH7*'Hyp 2027'!G326 -> 1.3313338e+08 | EI21: =EI7*'Hyp 2027'!H326 -> -31262582 | EJ21: =EJ7*'Hyp 2027'!I326 -> 84363535 | EK21: =SUM(EE21:EJ21) -> 3.8915859e+08 | EL21: =EC21+ED21+EK21 -> 2.7279964e+09
A22: Variation de REC CIMA 72% | B22: =B21-B20 -> 6.096124e+08 | C22: =C21-C20 -> 9.7770532e+08 | D22: =D21-D20 -> 7432574.5 | E22: =E21-E20 -> 4.5797502e+08 | F22: =F21-F20 -> -57311384 | G22: =G21-G20 -> -42544010 | H22: =H21-H20 -> 8.9123031e+08 | I22: =I21-I20 -> -10684588 | ... K22: =K21-K20 -> 1.5873177e+09 | M22: =M21-M20 -> 1.2676993e+09 | N22: =N21-N20 -> 9.1412164e+08 | O22: =O21-O20 -> 16758420 | P22: =P21-P20 -> 7.5217407e+08 | Q22: =Q21-Q20 -> 1.9920332e+08 | R22: =R21-R20 -> -40162290 | S22: =S21-S20 -> 2.4762498e+08 | T22: =T21-T20 -> 6.2799221e+08 | ... V22: =V21-V20 -> 3.9854117e+09 | Y22: =Y21-Y20 -> 8.2897225e+08 | Z22: =Z21-Z20 -> 8.1900643e+08 | AA22: =AA21-AA20 -> 13932273 | AB22: =AB21-AB20 -> 1.1809671e+09 | AC22: =AC21-AC20 -> -15265901 | AD22: =AD21-AD20 -> -1896660 | AE22: =AE21-AE20 -> 1.8341576e+08 | AF22: =AF21-AF20 -> 1.9801379e+08 | ... AH22: =AH21-AH20 -> 3.207145e+09 | AK22: =AK21-AK20 -> 9.0170779e+08 | AL22: =AL21-AL20 -> 6.8935706e+08 | AM22: =AM21-AM20 -> 17455394 | AN22: =AN21-AN20 -> 6.9868405e+08 | AO22: =AO21-AO20 -> 24785714 | AP22: =AP21-AP20 -> 24825110 | AQ22: =AQ21-AQ20 -> 2.3081649e+08 | AR22: =AR21-AR20 -> 1.889699e+08 | ... AT22: =AT21-AT20 -> 2.7766015e+09 | AW22: =AW21-AW20 -> 1.2357395e+09 | AX22: =AX21-AX20 -> 6.5987801e+08 | AY22: =AY21-AY20 -> 19033862 | AZ22: =AZ21-AZ20 -> 8.773737e+08 | BA22: =BA21-BA20 -> 25359121 | BB22: =BB21-BB20 -> 35086507 | BC22: =BC21-BC20 -> 3.5313155e+08 | BD22: =BD21-BD20 -> 3.2367605e+08 | ... BF22: =BF21-BF20 -> 3.5292783e+09 | BI22: =BI21-BI20 -> 1.0540089e+09 | BJ22: =BJ21-BJ20 -> 4.7859005e+08 | BK22: =BK21-BK20 -> 21215786 | BL22: =BL21-BL20 -> 8.35567e+08 | BM22: =BM21-BM20 -> 47697410 | BN22: =BN21-BN20 -> 31576678 | BO22: =BO21-BO20 -> 3.7126983e+08 | BP22: =BP21-BP20 -> 5.8516191e+08 | ... BR22: =BR21-BR20 -> 3.4250876e+09 | BU22: =BU21-BU20 -> 8.5281528e+08 | BV22: =BV21-BV20 -> 2.8744665e+08 | BW22: =BW21-BW20 -> 18271930 | BX22: =BX21-BX20 -> 7.9994633e+08 | BY22: =BY21-BY20 -> 53350580 | BZ22: =BZ21-BZ20 -> 32342688 | CA22: =CA21-CA20 -> 3.6426891e+08 | CB22: =CB21-CB20 -> 1.2020743e+09 | ... CD22: =CD21-CD20 -> 3.6105166e+09 | CG22: =CG21-CG20 -> 9.3276019e+08 | CH22: =CH21-CH20 -> 2.5402356e+08 | CI22: =CI21-CI20 -> 14846262 | CJ22: =CJ21-CJ20 -> 6.5194867e+08 | CK22: =CK21-CK20 -> 65306311 | CL22: =CL21-CL20 -> 1.8872724e+08 | CM22: =CM21-CM20 -> 3.0153715e+08 | CN22: =CN21-CN20 -> 4.4596238e+08 | ... CP22: =CP21-CP20 -> 2.8551118e+09 | CS22: =CS21-CS20 -> 7.6790527e+08 | CT22: =CT21-CT20 -> 2.1038894e+08 | CU22: =CU21-CU20 -> 11714065 | CV22: =CV21-CV20 -> 5.2203414e+08 | CW22: =CW21-CW20 -> 53582565 | CX22: =CX21-CX20 -> 1.9006441e+08 | CY22: =CY21-CY20 -> 2.3227482e+08 | CZ22: =CZ21-CZ20 -> 3.641001e+08 | ... DB22: =DB21-DB20 -> 2.3520643e+09 | DE22: =DE21-DE20 -> 5.9224037e+08 | DF22: =DF21-DF20 -> 1.7935605e+08 | DG22: =DG21-DG20 -> 8734097.2 | DH22: =DH21-DH20 -> 3.6684252e+08 | DI22: =DI21-DI20 -> 43003574 | DJ22: =DJ21-DJ20 -> 1.4238246e+08 | DK22: =DK21-DK20 -> 1.6450001e+08 | DL22: =DL21-DL20 -> 2.6619046e+08 | ... DN22: =DN21-DN20 -> 1.7632495e+09 | DQ22: =DQ21-DQ20 -> 3.6918678e+08 | DR22: =DR21-DR20 -> 1.22283e+08 | DS22: =DS21-DS20 -> 5314608.9 | DT22: =DT21-DT20 -> 1.9163182e+08 | DU22: =DU21-DU20 -> 37993435 | DV22: =DV21-DV20 -> 96475874 | DW22: =DW21-DW20 -> 91270210 | DX22: =DX21-DX20 -> 1.5662783e+08 | ... DZ22: =DZ21-DZ20 -> 1.0707836e+09 | EC22: =EC21-EC20 -> 81342525 | ED22: =ED21-ED20 -> 34468180 | EE22: =EE21-EE20 -> 1866690.2 | EF22: =EF21-EF20 -> 10946187 | EG22: =EG21-EG20 -> 34267060 | EH22: =EH21-EH20 -> 44501638 | EI22: =EI21-EI20 -> -7253151.7 | EJ22: =EJ21-EJ20 -> 19572968 | ... EL22: =EL21-EL20 -> 2.197121e+08
A24: REC Ouverture | B24: =B20/0.72 -> 2.1686088e+09 | C24: =C20/0.72 -> 9.1892892e+08 | D24: =D20/0.72 -> 8582125.5 | E24: =E20/0.72 -> 50325196 | F24: =F20/0.72 -> 1.5754312e+08 | G24: =G20/0.72 -> 1.2309964e+08 | H24: =H20/0.72 -> -33346431 | I24: =I20/0.72 -> 89986898 | J24: =SUM(D24:I24) -> 3.9619055e+08 | K24: =B24+C24+J24 -> 3.4837283e+09 | L24: ok | M24: =M20/0.72 -> 2.1686088e+09 | N24: =N20/0.72 -> 9.1892892e+08 | O24: =O20/0.72 -> 8582125.5 | P24: =P20/0.72 -> 50325196 | Q24: =Q20/0.72 -> 1.5754312e+08 | R24: =R20/0.72 -> 1.2309964e+08 | S24: =S20/0.72 -> -33346431 | T24: =T20/0.72 -> 89986898 | U24: =SUM(O24:T24) -> 3.9619055e+08 | V24: =M24+N24+U24 -> 3.4837283e+09 | W24: =V24=K24 -> TRUE | Y24: =Y20/0.72 -> 2.1686088e+09 | Z24: =Z20/0.72 -> 9.1892892e+08 | AA24: =AA20/0.72 -> 8582125.5 | AB24: =AB20/0.72 -> 50325196 | AC24: =AC20/0.72 -> 1.5754312e+08 | AD24: =AD20/0.72 -> 1.2309964e+08 | AE24: =AE20/0.72 -> -33346431 | AF24: =AF20/0.72 -> 89986898 | AG24: =SUM(AA24:AF24) -> 3.9619055e+08 | AH24: =Y24+Z24+AG24 -> 3.4837283e+09 | AI24: =AH24=V24 -> TRUE | AK24: =AK20/0.72 -> 2.1686088e+09 | AL24: =AL20/0.72 -> 9.1892892e+08 | AM24: =AM20/0.72 -> 8582125.5 | AN24: =AN20/0.72 -> 50325196 | AO24: =AO20/0.72 -> 1.5754312e+08 | AP24: =AP20/0.72 -> 1.2309964e+08 | AQ24: =AQ20/0.72 -> -33346431 | AR24: =AR20/0.72 -> 89986898 | AS24: =SUM(AM24:AR24) -> 3.9619055e+08 | AT24: =AK24+AL24+AS24 -> 3.4837283e+09 | AU24: =AT24=AH24 -> TRUE | AW24: =AW20/0.72 -> 2.1686088e+09 | AX24: =AX20/0.72 -> 9.1892892e+08 | AY24: =AY20/0.72 -> 8582125.5 | AZ24: =AZ20/0.72 -> 50325196 | BA24: =BA20/0.72 -> 1.5754312e+08 | BB24: =BB20/0.72 -> 1.2309964e+08 | BC24: =BC20/0.72 -> -33346431 | BD24: =BD20/0.72 -> 89986898 | BE24: =SUM(AY24:BD24) -> 3.9619055e+08 | BF24: =AW24+AX24+BE24 -> 3.4837283e+09 | BG24: =BF24=AT24 -> TRUE | BI24: =BI20/0.72 -> 2.1686088e+09 | BJ24: =BJ20/0.72 -> 9.1892892e+08 | BK24: =BK20/0.72 -> 8582125.5 | BL24: =BL20/0.72 -> 50325196 | BM24: =BM20/0.72 -> 1.5754312e+08 | BN24: =BN20/0.72 -> 1.2309964e+08 | BO24: =BO20/0.72 -> -33346431 | BP24: =BP20/0.72 -> 89986898 | BQ24: =SUM(BK24:BP24) -> 3.9619055e+08 | BR24: =BI24+BJ24+BQ24 -> 3.4837283e+09 | BU24: =BU20/0.72 -> 2.1686088e+09 | BV24: =BV20/0.72 -> 9.1892892e+08 | BW24: =BW20/0.72 -> 8582125.5 | BX24: =BX20/0.72 -> 50325196 | BY24: =BY20/0.72 -> 1.5754312e+08 | BZ24: =BZ20/0.72 -> 1.2309964e+08 | CA24: =CA20/0.72 -> -33346431 | CB24: =CB20/0.72 -> 89986898 | CC24: =SUM(BW24:CB24) -> 3.9619055e+08 | CD24: =BU24+BV24+CC24 -> 3.4837283e+09 | CE24: =CD24=BR24 -> TRUE | CG24: =CG20/0.72 -> 2.1686088e+09 | CH24: =CH20/0.72 -> 9.1892892e+08 | CI24: =CI20/0.72 -> 8582125.5 | CJ24: =CJ20/0.72 -> 50325196 | CK24: =CK20/0.72 -> 1.5754312e+08 | CL24: =CL20/0.72 -> 1.2309964e+08 | CM24: =CM20/0.72 -> -33346431 | CN24: =CN20/0.72 -> 89986898 | CO24: =SUM(CI24:CN24) -> 3.9619055e+08 | CP24: =CG24+CH24+CO24 -> 3.4837283e+09 | CS24: =CS20/0.72 -> 2.1686088e+09 | CT24: =CT20/0.72 -> 9.1892892e+08 | CU24: =CU20/0.72 -> 8582125.5 | CV24: =CV20/0.72 -> 50325196 | CW24: =CW20/0.72 -> 1.5754312e+08 | CX24: =CX20/0.72 -> 1.2309964e+08 | CY24: =CY20/0.72 -> -33346431 | CZ24: =CZ20/0.72 -> 89986898 | DA24: =SUM(CU24:CZ24) -> 3.9619055e+08 | DB24: =CS24+CT24+DA24 -> 3.4837283e+09 | DE24: =DE20/0.72 -> 2.1686088e+09 | DF24: =DF20/0.72 -> 9.1892892e+08 | DG24: =DG20/0.72 -> 8582125.5 | DH24: =DH20/0.72 -> 50325196 | DI24: =DI20/0.72 -> 1.5754312e+08 | DJ24: =DJ20/0.72 -> 1.2309964e+08 | DK24: =DK20/0.72 -> -33346431 | DL24: =DL20/0.72 -> 89986898 | DM24: =SUM(DG24:DL24) -> 3.9619055e+08 | DN24: =DE24+DF24+DM24 -> 3.4837283e+09 | DQ24: =DQ20/0.72 -> 2.1686088e+09 | DR24: =DR20/0.72 -> 9.1892892e+08 | DS24: =DS20/0.72 -> 8582125.5 | DT24: =DT20/0.72 -> 50325196 | DU24: =DU20/0.72 -> 1.5754312e+08 | DV24: =DV20/0.72 -> 1.2309964e+08 | DW24: =DW20/0.72 -> -33346431 | DX24: =DX20/0.72 -> 89986898 | DY24: =SUM(DS24:DX24) -> 3.9619055e+08 | DZ24: =DQ24+DR24+DY24 -> 3.4837283e+09 | EC24: =EC20/0.72 -> 2.1686088e+09 | ED24: =ED20/0.72 -> 9.1892892e+08 | EE24: =EE20/0.72 -> 8582125.5 | EF24: =EF20/0.72 -> 50325196 | EG24: =EG20/0.72 -> 1.5754312e+08 | EH24: =EH20/0.72 -> 1.2309964e+08 | EI24: =EI20/0.72 -> -33346431 | EJ24: =EJ20/0.72 -> 89986898 | EK24: =SUM(EE24:EJ24) -> 3.9619055e+08 | EL24: =EC24+ED24+EK24 -> 3.4837283e+09
A25: REC Clôture | B25: =B21/0.72 -> 3.0152927e+09 | C25: =C21/0.72 -> 2.276853e+09 | D25: =D21/0.72 -> 18905146 | E25: =E21/0.72 -> 6.8640162e+08 | F25: =F21/0.72 -> 77943977 | G25: =G21/0.72 -> 64010739 | H25: =H21/0.72 -> 1.2044734e+09 | I25: =I21/0.72 -> 75147192 | J25: =SUM(D25:I25) -> 2.1268821e+09 | K25: =B25+C25+J25 -> 7.4190278e+09 | M25: =M21/0.72 -> 3.9293023e+09 | N25: =N21/0.72 -> 2.1885423e+09 | O25: =O21/0.72 -> 31857709 | P25: =P21/0.72 -> 1.0950114e+09 | Q25: =Q21/0.72 -> 4.342144e+08 | R25: =R21/0.72 -> 67318683 | S25: =S21/0.72 -> 3.1057716e+08 | T25: =T21/0.72 -> 9.621983e+08 | U25: =SUM(O25:T25) -> 2.9011777e+09 | V25: =M25+N25+U25 -> 9.0190223e+09 | Y25: =Y21/0.72 -> 3.3199591e+09 | Z25: =Z21/0.72 -> 2.0564378e+09 | AA25: =AA21/0.72 -> 27932505 | AB25: =AB21/0.72 -> 1.6905573e+09 | AC25: =AC21/0.72 -> 1.3634048e+08 | AD25: =AD21/0.72 -> 1.2046539e+08 | AE25: =AE21/0.72 -> 2.2139768e+08 | AF25: =AF21/0.72 -> 3.6500606e+08 | AG25: =SUM(AA25:AF25) -> 2.5616994e+09 | AH25: =Y25+Z25+AG25 -> 7.9380964e+09 | AK25: =AK21/0.72 -> 3.4209807e+09 | AL25: =AL21/0.72 -> 1.8763693e+09 | AM25: =AM21/0.72 -> 32825728 | AN25: =AN21/0.72 -> 1.0207197e+09 | AO25: =AO21/0.72 -> 1.9196772e+08 | AP25: =AP21/0.72 -> 1.5757896e+08 | AQ25: =AQ21/0.72 -> 2.8723203e+08 | AR25: =AR21/0.72 -> 3.524451e+08 | AS25: =SUM(AM25:AR25) -> 2.0427693e+09 | AT25: =AK25+AL25+AS25 -> 7.3401193e+09 | AW25: =AW21/0.72 -> 3.8849136e+09 | AX25: =AX21/0.72 -> 1.8354262e+09 | AY25: =AY21/0.72 -> 35018045 | AZ25: =AZ21/0.72 -> 1.2688998e+09 | BA25: =BA21/0.72 -> 1.9276412e+08 | BB25: =BB21/0.72 -> 1.718309e+08 | BC25: =BC21/0.72 -> 4.5711405e+08 | BD25: =BD21/0.72 -> 5.3953696e+08 | BE25: =SUM(AY25:BD25) -> 2.6651639e+09 | BF25: =AW25+AX25+BE25 -> 8.3855037e+09 | BI25: =BI21/0.72 -> 3.63251e+09 | BJ25: =BJ21/0.72 -> 1.5836373e+09 | BK25: =BK21/0.72 -> 38048495 | BL25: =BL21/0.72 -> 1.2108349e+09 | BM25: =BM21/0.72 -> 2.2378952e+08 | BN25: =BN21/0.72 -> 1.6695614e+08 | BO25: =BO21/0.72 -> 4.8230611e+08 | BP25: =BP21/0.72 -> 9.0271177e+08 | BQ25: =SUM(BK25:BP25) -> 3.024647e+09 | BR25: =BI25+BJ25+BQ25 -> 8.2407943e+09 | BU25: =BU21/0.72 -> 3.3530745e+09 | BV25: =BV21/0.72 -> 1.3181604e+09 | BW25: =BW21/0.72 -> 33959805 | BX25: =BX21/0.72 -> 1.1613618e+09 | BY25: =BY21/0.72 -> 2.3164115e+08 | BZ25: =BZ21/0.72 -> 1.6802004e+08 | CA25: =CA21/0.72 -> 4.7258261e+08 | CB25: =CB21/0.72 -> 1.7595345e+09 | CC25: =SUM(BW25:CB25) -> 3.8270999e+09 | CD25: =BU25+BV25+CC25 -> 8.4983347e+09 | CG25: =CG21/0.72 -> 3.4641091e+09 | CH25: =CH21/0.72 -> 1.2717394e+09 | CI25: =CI21/0.72 -> 29201934 | CJ25: =CJ21/0.72 -> 9.5580947e+08 | CK25: =CK21/0.72 -> 2.4824633e+08 | CL25: =CL21/0.72 -> 3.852208e+08 | CM25: =CM21/0.72 -> 3.8545517e+08 | CN25: =CN21/0.72 -> 7.093791e+08 | CO25: =SUM(CI25:CN25) -> 2.7133128e+09 | CP25: =CG25+CH25+CO25 -> 7.4491613e+09 | CS25: =CS21/0.72 -> 3.2351439e+09 | CT25: =CT21/0.72 -> 1.2111358e+09 | CU25: =CU21/0.72 -> 24851661 | CV25: =CV21/0.72 -> 7.7537262e+08 | CW25: =CW21/0.72 -> 2.3196335e+08 | CX25: =CX21/0.72 -> 3.8707799e+08 | CY25: =CY21/0.72 -> 2.8925749e+08 | CZ25: =CZ21/0.72 -> 5.9568148e+08 | DA25: =SUM(CU25:CZ25) -> 2.3042046e+09 | DB25: =CS25+CT25+DA25 -> 6.7504843e+09 | DE25: =DE21/0.72 -> 2.9911649e+09 | DF25: =DF21/0.72 -> 1.1680345e+09 | DG25: =DG21/0.72 -> 20712816 | DH25: =DH21/0.72 -> 5.598287e+08 | DI25: =DI21/0.72 -> 2.1727031e+08 | DJ25: =DJ21/0.72 -> 3.2085306e+08 | DK25: =DK21/0.72 -> 1.951258e+08 | DL25: =DL21/0.72 -> 4.5969586e+08 | DM25: =SUM(DG25:DL25) -> 1.7734866e+09 | DN25: =DE25+DF25+DM25 -> 5.932686e+09 | DQ25: =DQ21/0.72 -> 2.6813682e+09 | DR25: =DR21/0.72 -> 1.0887664e+09 | DS25: =DS21/0.72 -> 15963527 | DT25: =DT21/0.72 -> 3.164805e+08 | DU25: =DU21/0.72 -> 2.1031178e+08 | DV25: =DV21/0.72 -> 2.5709391e+08 | DW25: =DW21/0.72 -> 93417748 | DX25: =DX21/0.72 -> 3.0752556e+08 | DY25: =SUM(DS25:DX25) -> 1.200793e+09 | DZ25: =DQ25+DR25+DY25 -> 4.9709277e+09 | EC25: =EC21/0.72 -> 2.2815845e+09 | ED25: =ED21/0.72 -> 9.6680139e+08 | EE25: =EE21/0.72 -> 11174751 | EF25: =EF21/0.72 -> 65528234 | EG25: =EG21/0.72 -> 2.0513626e+08 | EH25: =EH21/0.72 -> 1.8490747e+08 | EI25: =EI21/0.72 -> -43420253 | EJ25: =EJ21/0.72 -> 1.1717158e+08 | EK25: =SUM(EE25:EJ25) -> 5.4049804e+08 | EL25: =EC25+ED25+EK25 -> 3.788884e+09
A26: Variation de REC prorata | B26: =B25-B24 -> 8.4668389e+08 | C26: =C25-C24 -> 1.3579241e+09 | D26: =D25-D24 -> 10323020 | E26: =E25-E24 -> 6.3607642e+08 | F26: =F25-F24 -> -79599145 | G26: =G25-G24 -> -59088903 | H26: =H25-H24 -> 1.2378199e+09 | I26: =I25-I24 -> -14839706 | ... K26: =K25-K24 -> 3.9352995e+09 | M26: =M25-M24 -> 1.7606935e+09 | N26: =N25-N24 -> 1.2696134e+09 | O26: =O25-O24 -> 23275584 | P26: =P25-P24 -> 1.0446862e+09 | Q26: =Q25-Q24 -> 2.7667127e+08 | R26: =R25-R24 -> -55780959 | S26: =S25-S24 -> 3.4392359e+08 | T26: =T25-T24 -> 8.7221141e+08 | ... V26: =V25-V24 -> 5.535294e+09 | Y26: =Y25-Y24 -> 1.1513504e+09 | Z26: =Z25-Z24 -> 1.1375089e+09 | AA26: =AA25-AA24 -> 19350379 | AB26: =AB25-AB24 -> 1.6402321e+09 | AC26: =AC25-AC24 -> -21202641 | AD26: =AD25-AD24 -> -2634250 | AE26: =AE25-AE24 -> 2.5474411e+08 | AF26: =AF25-AF24 -> 2.7501916e+08 | ... AH26: =AH25-AH24 -> 4.4543681e+09 | AK26: =AK25-AK24 -> 1.2523719e+09 | AL26: =AL25-AL24 -> 9.5744036e+08 | AM26: =AM25-AM24 -> 24243603 | AN26: =AN25-AN24 -> 9.7039452e+08 | AO26: =AO25-AO24 -> 34424603 | AP26: =AP25-AP24 -> 34479320 | AQ26: =AQ25-AQ24 -> 3.2057847e+08 | AR26: =AR25-AR24 -> 2.624582e+08 | ... AT26: =AT25-AT24 -> 3.856391e+09 | AW26: =AW25-AW24 -> 1.7163048e+09 | AX26: =AX25-AX24 -> 9.1649724e+08 | AY26: =AY25-AY24 -> 26435919 | AZ26: =AZ25-AZ24 -> 1.2185746e+09 | BA26: =BA25-BA24 -> 35221001 | BB26: =BB25-BB24 -> 48731260 | BC26: =BC25-BC24 -> 4.9046048e+08 | BD26: =BD25-BD24 -> 4.4955007e+08 | ... BF26: =BF25-BF24 -> 4.9017754e+09 | BI26: =BI25-BI24 -> 1.4639012e+09 | BJ26: =BJ25-BJ24 -> 6.647084e+08 | BK26: =BK25-BK24 -> 29466369 | BL26: =BL25-BL24 -> 1.1605097e+09 | BM26: =BM25-BM24 -> 66246403 | BN26: =BN25-BN24 -> 43856497 | BO26: =BO25-BO24 -> 5.1565254e+08 | BP26: =BP25-BP24 -> 8.1272487e+08 | ... BR26: =BR25-BR24 -> 4.7570661e+09 | BU26: =BU25-BU24 -> 1.1844657e+09 | BV26: =BV25-BV24 -> 3.9923146e+08 | BW26: =BW25-BW24 -> 25377680 | BX26: =BX25-BX24 -> 1.1110366e+09 | BY26: =BY25-BY24 -> 74098028 | BZ26: =BZ25-BZ24 -> 44920400 | CA26: =CA25-CA24 -> 5.0592905e+08 | CB26: =CB25-CB24 -> 1.6695476e+09 | ... CD26: =CD25-CD24 -> 5.0146065e+09 | CG26: =CG25-CG24 -> 1.2955003e+09 | CH26: =CH25-CH24 -> 3.5281049e+08 | CI26: =CI25-CI24 -> 20619808 | CJ26: =CJ25-CJ24 -> 9.0548427e+08 | CK26: =CK25-CK24 -> 90703210 | CL26: =CL25-CL24 -> 2.6212116e+08 | CM26: =CM25-CM24 -> 4.188016e+08 | CN26: =CN25-CN24 -> 6.193922e+08 | ... CP26: =CP25-CP24 -> 3.965433e+09 | CS26: =CS25-CS24 -> 1.0665351e+09 | CT26: =CT25-CT24 -> 2.9220687e+08 | CU26: =CU25-CU24 -> 16269535 | CV26: =CV25-CV24 -> 7.2504742e+08 | CW26: =CW25-CW24 -> 74420229 | CX26: =CX25-CX24 -> 2.6397835e+08 | CY26: =CY25-CY24 -> 3.2260392e+08 | CZ26: =CZ25-CZ24 -> 5.0569458e+08 | ... DB26: =DB25-DB24 -> 3.266756e+09 | DE26: =DE25-DE24 -> 8.2255607e+08 | DF26: =DF25-DF24 -> 2.4910562e+08 | DG26: =DG25-DG24 -> 12130691 | DH26: =DH25-DH24 -> 5.095035e+08 | DI26: =DI25-DI24 -> 59727187 | DJ26: =DJ25-DJ24 -> 1.9775342e+08 | DK26: =DK25-DK24 -> 2.2847223e+08 | DL26: =DL25-DL24 -> 3.6970897e+08 | ... DN26: =DN25-DN24 -> 2.4489577e+09 | DQ26: =DQ25-DQ24 -> 5.1275941e+08 | DR26: =DR25-DR24 -> 1.698375e+08 | DS26: =DS25-DS24 -> 7381401.2 | DT26: =DT25-DT24 -> 2.6615531e+08 | DU26: =DU25-DU24 -> 52768659 | DV26: =DV25-DV24 -> 1.3399427e+08 | DW26: =DW25-DW24 -> 1.2676418e+08 | DX26: =DX25-DX24 -> 2.1753866e+08 | ... DZ26: =DZ25-DZ24 -> 1.4871994e+09 | EC26: =EC25-EC24 -> 1.1297573e+08 | ED26: =ED25-ED24 -> 47872472 | EE26: =EE25-EE24 -> 2592625.3 | EF26: =EF25-EF24 -> 15203038 | EG26: =EG25-EG24 -> 47593138 | EH26: =EH25-EH24 -> 61807831 | EI26: =EI25-EI24 -> -10073822 | EJ26: =EJ25-EJ24 -> 27184677 | ... EL26: =EL25-EL24 -> 3.0515569e+08
A28: DAC Ouv | J28: =SUM(D28:I28) -> 0 | K28: =B28+C28+J28 -> 0 | U28: =SUM(O28:T28) -> 0 | V28: =M28+N28+U28 -> 0 | AG28: =SUM(AA28:AF28) -> 0 | AH28: =Y28+Z28+AG28 -> 0 | AS28: =SUM(AM28:AR28) -> 0 | AT28: =AK28+AL28+AS28 -> 0 | BE28: =SUM(AY28:BD28) -> 0 | BF28: =AW28+AX28+BE28 -> 0 | BQ28: =SUM(BK28:BP28) -> 0 | BR28: =BI28+BJ28+BQ28 -> 0 | CC28: =SUM(BW28:CB28) -> 0 | CD28: =BU28+BV28+CC28 -> 0 | CO28: =SUM(CI28:CN28) -> 0 | CP28: =CG28+CH28+CO28 -> 0 | DA28: =SUM(CU28:CZ28) -> 0 | DB28: =CS28+CT28+DA28 -> 0 | DM28: =SUM(DG28:DL28) -> 0 | DN28: =DE28+DF28+DM28 -> 0 | DY28: =SUM(DS28:DX28) -> 0 | DZ28: =DQ28+DR28+DY28 -> 0 | EK28: =SUM(EE28:EJ28) -> 0 | EL28: =EC28+ED28+EK28 -> 0
A29: DAC Clo | J29: =SUM(D29:I29) -> 0 | K29: =B29+C29+J29 -> 0 | U29: =SUM(O29:T29) -> 0 | V29: =M29+N29+U29 -> 0 | AG29: =SUM(AA29:AF29) -> 0 | AH29: =Y29+Z29+AG29 -> 0 | AS29: =SUM(AM29:AR29) -> 0 | AT29: =AK29+AL29+AS29 -> 0 | BE29: =SUM(AY29:BD29) -> 0 | BF29: =AW29+AX29+BE29 -> 0 | BQ29: =SUM(BK29:BP29) -> 0 | BR29: =BI29+BJ29+BQ29 -> 0 | CC29: =SUM(BW29:CB29) -> 0 | CD29: =BU29+BV29+CC29 -> 0 | CO29: =SUM(CI29:CN29) -> 0 | CP29: =CG29+CH29+CO29 -> 0 | DA29: =SUM(CU29:CZ29) -> 0 | DB29: =CS29+CT29+DA29 -> 0 | DM29: =SUM(DG29:DL29) -> 0 | DN29: =DE29+DF29+DM29 -> 0 | DY29: =SUM(DS29:DX29) -> 0 | DZ29: =DQ29+DR29+DY29 -> 0 | EK29: =SUM(EE29:EJ29) -> 0 | EL29: =EC29+ED29+EK29 -> 0
A30: Var DAC | B30: =B28-B29 -> 0 | C30: =C28-C29 -> 0 | D30: =D28-D29 -> 0 | E30: =E28-E29 -> 0 | F30: =F28-F29 -> 0 | G30: =G28-G29 -> 0 | H30: =H28-H29 -> 0 | I30: =I28-I29 -> 0 | ... K30: =K28-K29 -> 0 | M30: =M28-M29 -> 0 | N30: =N28-N29 -> 0 | O30: =O28-O29 -> 0 | P30: =P28-P29 -> 0 | Q30: =Q28-Q29 -> 0 | R30: =R28-R29 -> 0 | S30: =S28-S29 -> 0 | T30: =T28-T29 -> 0 | ... V30: =V28-V29 -> 0 | Y30: =Y28-Y29 -> 0 | Z30: =Z28-Z29 -> 0 | AA30: =AA28-AA29 -> 0 | AB30: =AB28-AB29 -> 0 | AC30: =AC28-AC29 -> 0 | AD30: =AD28-AD29 -> 0 | AE30: =AE28-AE29 -> 0 | AF30: =AF28-AF29 -> 0 | ... AH30: =AH28-AH29 -> 0 | AK30: =AK28-AK29 -> 0 | AL30: =AL28-AL29 -> 0 | AM30: =AM28-AM29 -> 0 | AN30: =AN28-AN29 -> 0 | AO30: =AO28-AO29 -> 0 | AP30: =AP28-AP29 -> 0 | AQ30: =AQ28-AQ29 -> 0 | AR30: =AR28-AR29 -> 0 | ... AT30: =AT28-AT29 -> 0 | AW30: =AW28-AW29 -> 0 | AX30: =AX28-AX29 -> 0 | AY30: =AY28-AY29 -> 0 | AZ30: =AZ28-AZ29 -> 0 | BA30: =BA28-BA29 -> 0 | BB30: =BB28-BB29 -> 0 | BC30: =BC28-BC29 -> 0 | BD30: =BD28-BD29 -> 0 | ... BF30: =BF28-BF29 -> 0 | BI30: =BI28-BI29 -> 0 | BJ30: =BJ28-BJ29 -> 0 | BK30: =BK28-BK29 -> 0 | BL30: =BL28-BL29 -> 0 | BM30: =BM28-BM29 -> 0 | BN30: =BN28-BN29 -> 0 | BO30: =BO28-BO29 -> 0 | BP30: =BP28-BP29 -> 0 | ... BR30: =BR28-BR29 -> 0 | BU30: =BU28-BU29 -> 0 | BV30: =BV28-BV29 -> 0 | BW30: =BW28-BW29 -> 0 | BX30: =BX28-BX29 -> 0 | BY30: =BY28-BY29 -> 0 | BZ30: =BZ28-BZ29 -> 0 | CA30: =CA28-CA29 -> 0 | CB30: =CB28-CB29 -> 0 | ... CD30: =CD28-CD29 -> 0 | CG30: =CG28-CG29 -> 0 | CH30: =CH28-CH29 -> 0 | CI30: =CI28-CI29 -> 0 | CJ30: =CJ28-CJ29 -> 0 | CK30: =CK28-CK29 -> 0 | CL30: =CL28-CL29 -> 0 | CM30: =CM28-CM29 -> 0 | CN30: =CN28-CN29 -> 0 | ... CP30: =CP28-CP29 -> 0 | CS30: =CS28-CS29 -> 0 | CT30: =CT28-CT29 -> 0 | CU30: =CU28-CU29 -> 0 | CV30: =CV28-CV29 -> 0 | CW30: =CW28-CW29 -> 0 | CX30: =CX28-CX29 -> 0 | CY30: =CY28-CY29 -> 0 | CZ30: =CZ28-CZ29 -> 0 | ... DB30: =DB28-DB29 -> 0 | DE30: =DE28-DE29 -> 0 | DF30: =DF28-DF29 -> 0 | DG30: =DG28-DG29 -> 0 | DH30: =DH28-DH29 -> 0 | DI30: =DI28-DI29 -> 0 | DJ30: =DJ28-DJ29 -> 0 | DK30: =DK28-DK29 -> 0 | DL30: =DL28-DL29 -> 0 | ... DN30: =DN28-DN29 -> 0 | DQ30: =DQ28-DQ29 -> 0 | DR30: =DR28-DR29 -> 0 | DS30: =DS28-DS29 -> 0 | DT30: =DT28-DT29 -> 0 | DU30: =DU28-DU29 -> 0 | DV30: =DV28-DV29 -> 0 | DW30: =DW28-DW29 -> 0 | DX30: =DX28-DX29 -> 0 | ... DZ30: =DZ28-DZ29 -> 0 | EC30: =EC28-EC29 -> 0 | ED30: =ED28-ED29 -> 0 | EE30: =EE28-EE29 -> 0 | EF30: =EF28-EF29 -> 0 | EG30: =EG28-EG29 -> 0 | EH30: =EH28-EH29 -> 0 | EI30: =EI28-EI29 -> 0 | EJ30: =EJ28-EJ29 -> 0 | ... EL30: =EL28-EL29 -> 0
A32: REC Ouverture | B32: =B24-B20 -> 6.0721046e+08 | C32: =C24-C20 -> 2.573001e+08 | D32: =D24-D20 -> 2402995.1 | E32: =E24-E20 -> 14091055 | F32: =F24-F20 -> 44112074 | G32: =G24-G20 -> 34467900 | H32: =H24-H20 -> -9337000.8 | I32: =I24-I20 -> 25196332 | J32: =SUM(D32:I32) -> 1.1093335e+08 | K32: =B32+C32+J32 -> 9.7544391e+08 | M32: =M24-M20 -> 6.0721046e+08 | N32: =N24-N20 -> 2.573001e+08 | O32: =O24-O20 -> 2402995.1 | P32: =P24-P20 -> 14091055 | Q32: =Q24-Q20 -> 44112074 | R32: =R24-R20 -> 34467900 | S32: =S24-S20 -> -9337000.8 | T32: =T24-T20 -> 25196332 | U32: =SUM(O32:T32) -> 1.1093335e+08 | V32: =M32+N32+U32 -> 9.7544391e+08 | Y32: =Y24-Y20 -> 6.0721046e+08 | Z32: =Z24-Z20 -> 2.573001e+08 | AA32: =AA24-AA20 -> 2402995.1 | AB32: =AB24-AB20 -> 14091055 | AC32: =AC24-AC20 -> 44112074 | AD32: =AD24-AD20 -> 34467900 | AE32: =AE24-AE20 -> -9337000.8 | AF32: =AF24-AF20 -> 25196332 | AG32: =SUM(AA32:AF32) -> 1.1093335e+08 | AH32: =Y32+Z32+AG32 -> 9.7544391e+08 | AK32: =AK24-AK20 -> 6.0721046e+08 | AL32: =AL24-AL20 -> 2.573001e+08 | AM32: =AM24-AM20 -> 2402995.1 | AN32: =AN24-AN20 -> 14091055 | AO32: =AO24-AO20 -> 44112074 | AP32: =AP24-AP20 -> 34467900 | AQ32: =AQ24-AQ20 -> -9337000.8 | AR32: =AR24-AR20 -> 25196332 | AS32: =SUM(AM32:AR32) -> 1.1093335e+08 | AT32: =AK32+AL32+AS32 -> 9.7544391e+08 | AW32: =AW24-AW20 -> 6.0721046e+08 | AX32: =AX24-AX20 -> 2.573001e+08 | AY32: =AY24-AY20 -> 2402995.1 | AZ32: =AZ24-AZ20 -> 14091055 | BA32: =BA24-BA20 -> 44112074 | BB32: =BB24-BB20 -> 34467900 | BC32: =BC24-BC20 -> -9337000.8 | BD32: =BD24-BD20 -> 25196332 | BE32: =SUM(AY32:BD32) -> 1.1093335e+08 | BF32: =AW32+AX32+BE32 -> 9.7544391e+08 | BI32: =BI24-BI20 -> 6.0721046e+08 | BJ32: =BJ24-BJ20 -> 2.573001e+08 | BK32: =BK24-BK20 -> 2402995.1 | BL32: =BL24-BL20 -> 14091055 | BM32: =BM24-BM20 -> 44112074 | BN32: =BN24-BN20 -> 34467900 | BO32: =BO24-BO20 -> -9337000.8 | BP32: =BP24-BP20 -> 25196332 | BQ32: =SUM(BK32:BP32) -> 1.1093335e+08 | BR32: =BI32+BJ32+BQ32 -> 9.7544391e+08 | BU32: =BU24-BU20 -> 6.0721046e+08 | BV32: =BV24-BV20 -> 2.573001e+08 | BW32: =BW24-BW20 -> 2402995.1 | BX32: =BX24-BX20 -> 14091055 | BY32: =BY24-BY20 -> 44112074 | BZ32: =BZ24-BZ20 -> 34467900 | CA32: =CA24-CA20 -> -9337000.8 | CB32: =CB24-CB20 -> 25196332 | CC32: =SUM(BW32:CB32) -> 1.1093335e+08 | CD32: =BU32+BV32+CC32 -> 9.7544391e+08 | CG32: =CG24-CG20 -> 6.0721046e+08 | CH32: =CH24-CH20 -> 2.573001e+08 | CI32: =CI24-CI20 -> 2402995.1 | CJ32: =CJ24-CJ20 -> 14091055 | CK32: =CK24-CK20 -> 44112074 | CL32: =CL24-CL20 -> 34467900 | CM32: =CM24-CM20 -> -9337000.8 | CN32: =CN24-CN20 -> 25196332 | CO32: =SUM(CI32:CN32) -> 1.1093335e+08 | CP32: =CG32+CH32+CO32 -> 9.7544391e+08 | CS32: =CS24-CS20 -> 6.0721046e+08 | CT32: =CT24-CT20 -> 2.573001e+08 | CU32: =CU24-CU20 -> 2402995.1 | CV32: =CV24-CV20 -> 14091055 | CW32: =CW24-CW20 -> 44112074 | CX32: =CX24-CX20 -> 34467900 | CY32: =CY24-CY20 -> -9337000.8 | CZ32: =CZ24-CZ20 -> 25196332 | DA32: =SUM(CU32:CZ32) -> 1.1093335e+08 | DB32: =CS32+CT32+DA32 -> 9.7544391e+08 | DE32: =DE24-DE20 -> 6.0721046e+08 | DF32: =DF24-DF20 -> 2.573001e+08 | DG32: =DG24-DG20 -> 2402995.1 | DH32: =DH24-DH20 -> 14091055 | DI32: =DI24-DI20 -> 44112074 | DJ32: =DJ24-DJ20 -> 34467900 | DK32: =DK24-DK20 -> -9337000.8 | DL32: =DL24-DL20 -> 25196332 | DM32: =SUM(DG32:DL32) -> 1.1093335e+08 | DN32: =DE32+DF32+DM32 -> 9.7544391e+08 | DQ32: =DQ24-DQ20 -> 6.0721046e+08 | DR32: =DR24-DR20 -> 2.573001e+08 | DS32: =DS24-DS20 -> 2402995.1 | DT32: =DT24-DT20 -> 14091055 | DU32: =DU24-DU20 -> 44112074 | DV32: =DV24-DV20 -> 34467900 | DW32: =DW24-DW20 -> -9337000.8 | DX32: =DX24-DX20 -> 25196332 | DY32: =SUM(DS32:DX32) -> 1.1093335e+08 | DZ32: =DQ32+DR32+DY32 -> 9.7544391e+08 | EC32: =EC24-EC20 -> 6.0721046e+08 | ED32: =ED24-ED20 -> 2.573001e+08 | EE32: =EE24-EE20 -> 2402995.1 | EF32: =EF24-EF20 -> 14091055 | EG32: =EG24-EG20 -> 44112074 | EH32: =EH24-EH20 -> 34467900 | EI32: =EI24-EI20 -> -9337000.8 | EJ32: =EJ24-EJ20 -> 25196332 | EK32: =SUM(EE32:EJ32) -> 1.1093335e+08 | EL32: =EC32+ED32+EK32 -> 9.7544391e+08
A33: REC Clôture | B33: =B25-B21 -> 8.4428195e+08 | C33: =C25-C21 -> 6.3751883e+08 | D33: =D25-D21 -> 5293440.8 | E33: =E25-E21 -> 1.9219245e+08 | F33: =F25-F21 -> 21824313 | G33: =G25-G21 -> 17923007 | H33: =H25-H21 -> 3.3725256e+08 | I33: =I25-I21 -> 21041214 | J33: =SUM(D33:I33) -> 5.9552699e+08 | K33: =B33+C33+J33 -> 2.0773278e+09 | M33: =M25-M21 -> 1.1002047e+09 | N33: =N25-N21 -> 6.1279185e+08 | O33: =O25-O21 -> 8920158.5 | P33: =P25-P21 -> 3.0660319e+08 | Q33: =Q25-Q21 -> 1.2158003e+08 | R33: =R25-R21 -> 18849231 | S33: =S25-S21 -> 86961603 | T33: =T25-T21 -> 2.6941553e+08 | U33: =SUM(O33:T33) -> 8.1232974e+08 | V33: =M33+N33+U33 -> 2.5253262e+09 | Y33: =Y25-Y21 -> 9.2958856e+08 | Z33: =Z25-Z21 -> 5.758026e+08 | AA33: =AA25-AA21 -> 7821101.3 | AB33: =AB25-AB21 -> 4.7335604e+08 | AC33: =AC25-AC21 -> 38175335 | AD33: =AD25-AD21 -> 33730310 | AE33: =AE25-AE21 -> 61991350 | AF33: =AF25-AF21 -> 1.022017e+08 | AG33: =SUM(AA33:AF33) -> 7.1727583e+08 | AH33: =Y33+Z33+AG33 -> 2.222667e+09 | AK33: =AK25-AK21 -> 9.578746e+08 | AL33: =AL25-AL21 -> 5.253834e+08 | AM33: =AM25-AM21 -> 9191203.9 | AN33: =AN25-AN21 -> 2.8580152e+08 | AO33: =AO25-AO21 -> 53750963 | AP33: =AP25-AP21 -> 44122109 | AQ33: =AQ25-AQ21 -> 80424969 | AR33: =AR25-AR21 -> 98684628 | AS33: =SUM(AM33:AR33) -> 5.7197539e+08 | AT33: =AK33+AL33+AS33 -> 2.0552334e+09 | AW33: =AW25-AW21 -> 1.0877758e+09 | AX33: =AX25-AX21 -> 5.1391932e+08 | AY33: =AY25-AY21 -> 9805052.6 | AZ33: =AZ25-AZ21 -> 3.5529194e+08 | BA33: =BA25-BA21 -> 53973954 | BB33: =BB25-BB21 -> 48112652 | BC33: =BC25-BC21 -> 1.2799193e+08 | BD33: =BD25-BD21 -> 1.5107035e+08 | BE33: =SUM(AY33:BD33) -> 7.4624588e+08 | BF33: =AW33+AX33+BE33 -> 2.347941e+09 | BI33: =BI25-BI21 -> 1.0171028e+09 | BJ33: =BJ25-BJ21 -> 4.4341845e+08 | BK33: =BK25-BK21 -> 10653579 | BL33: =BL25-BL21 -> 3.3903378e+08 | BM33: =BM25-BM21 -> 62661067 | BN33: =BN25-BN21 -> 46747719 | BO33: =BO25-BO21 -> 1.3504571e+08 | BP33: =BP25-BP21 -> 2.527593e+08 | BQ33: =SUM(BK33:BP33) -> 8.4690115e+08 | BR33: =BI33+BJ33+BQ33 -> 2.3074224e+09 | BU33: =BU25-BU21 -> 9.3886085e+08 | BV33: =BV25-BV21 -> 3.6908491e+08 | BW33: =BW25-BW21 -> 9508745.5 | BX33: =BX25-BX21 -> 3.251813e+08 | BY33: =BY25-BY21 -> 64859522 | BZ33: =BZ25-BZ21 -> 47045612 | CA33: =CA25-CA21 -> 1.3232313e+08 | CB33: =CB25-CB21 -> 4.9266966e+08 | CC33: =SUM(BW33:CB33) -> 1.071588e+09 | CD33: =BU33+BV33+CC33 -> 2.3795337e+09 | CG33: =CG25-CG21 -> 9.6995054e+08 | CH33: =CH25-CH21 -> 3.5608704e+08 | CI33: =CI25-CI21 -> 8176541.5 | CJ33: =CJ25-CJ21 -> 2.6762665e+08 | CK33: =CK25-CK21 -> 69508973 | CL33: =CL25-CL21 -> 1.0786183e+08 | CM33: =CM25-CM21 -> 1.0792745e+08 | CN33: =CN25-CN21 -> 1.9862615e+08 | CO33: =SUM(CI33:CN33) -> 7.5972758e+08 | CP33: =CG33+CH33+CO33 -> 2.0857652e+09 | CS33: =CS25-CS21 -> 9.0584029e+08 | CT33: =CT25-CT21 -> 3.3911802e+08 | CU33: =CU25-CU21 -> 6958465 | CV33: =CV25-CV21 -> 2.1710433e+08 | CW33: =CW25-CW21 -> 64949738 | CX33: =CX25-CX21 -> 1.0838184e+08 | CY33: =CY25-CY21 -> 80992097 | CZ33: =CZ25-CZ21 -> 1.6679081e+08 | DA33: =SUM(CU33:CZ33) -> 6.4517729e+08 | DB33: =CS33+CT33+DA33 -> 1.8901356e+09 | DE33: =DE25-DE21 -> 8.3752616e+08 | DF33: =DF25-DF21 -> 3.2704967e+08 | DG33: =DG25-DG21 -> 5799588.5 | DH33: =DH25-DH21 -> 1.5675204e+08 | DI33: =DI25-DI21 -> 60835686 | DJ33: =DJ25-DJ21 -> 89838858 | DK33: =DK25-DK21 -> 54635225 | DL33: =DL25-DL21 -> 1.2871484e+08 | DM33: =SUM(DG33:DL33) -> 4.9657624e+08 | DN33: =DE33+DF33+DM33 -> 1.6611521e+09 | DQ33: =DQ25-DQ21 -> 7.507831e+08 | DR33: =DR25-DR21 -> 3.048546e+08 | DS33: =DS25-DS21 -> 4469787.5 | DT33: =DT25-DT21 -> 88614540 | DU33: =DU25-DU21 -> 58887299 | DV33: =DV25-DV21 -> 71986295 | DW33: =DW25-DW21 -> 26156970 | DX33: =DX25-DX21 -> 86107156 | DY33: =SUM(DS33:DX33) -> 3.3622205e+08 | DZ33: =DQ33+DR33+DY33 -> 1.3918597e+09 | EC33: =EC25-EC21 -> 6.3884367e+08 | ED33: =ED25-ED21 -> 2.7070439e+08 | EE33: =EE25-EE21 -> 3128930.2 | EF33: =EF25-EF21 -> 18347906 | EG33: =EG25-EG21 -> 57438153 | EH33: =EH25-EH21 -> 51774092 | EI33: =EI25-EI21 -> -12157671 | EJ33: =EJ25-EJ21 -> 32808041 | EK33: =SUM(EE33:EJ33) -> 1.5133945e+08 | EL33: =EC33+ED33+EK33 -> 1.0608875e+09
A34: Variation des FAR 28% | B34: =B33-B32 -> 2.3707149e+08 | C34: =C33-C32 -> 3.8021874e+08 | D34: =D33-D32 -> 2890445.6 | E34: =E33-E32 -> 1.781014e+08 | F34: =F33-F32 -> -22287760 | G34: =G33-G32 -> -16544893 | H34: =H33-H32 -> 3.4658957e+08 | I34: =I33-I32 -> -4155117.7 | J34: =SUM(D34:I34) -> 4.8459364e+08 | K34: =B34+C34+J34 -> 1.1018839e+09 | M34: =M33-M32 -> 4.9299419e+08 | N34: =N33-N32 -> 3.5549175e+08 | O34: =O33-O32 -> 6517163.4 | P34: =P33-P32 -> 2.9251214e+08 | Q34: =Q33-Q32 -> 77467957 | R34: =R33-R32 -> -15618668 | S34: =S33-S32 -> 96298604 | T34: =T33-T32 -> 2.4421919e+08 | U34: =SUM(O34:T34) -> 7.0139639e+08 | V34: =M34+N34+U34 -> 1.5498823e+09 | Y34: =Y33-Y32 -> 3.223781e+08 | Z34: =Z33-Z32 -> 3.185025e+08 | AA34: =AA33-AA32 -> 5418106.2 | AB34: =AB33-AB32 -> 4.5926498e+08 | AC34: =AC33-AC32 -> -5936739.4 | AD34: =AD33-AD32 -> -737590.01 | AE34: =AE33-AE32 -> 71328351 | AF34: =AF33-AF32 -> 77005365 | AG34: =SUM(AA34:AF34) -> 6.0634247e+08 | AH34: =Y34+Z34+AG34 -> 1.2472231e+09 | AK34: =AK33-AK32 -> 3.5066414e+08 | AL34: =AL33-AL32 -> 2.680833e+08 | AM34: =AM33-AM32 -> 6788208.8 | AN34: =AN33-AN32 -> 2.7171046e+08 | AO34: =AO33-AO32 -> 9638888.9 | AP34: =AP33-AP32 -> 9654209.6 | AQ34: =AQ33-AQ32 -> 89761970 | AR34: =AR33-AR32 -> 73488296 | AS34: =SUM(AM34:AR34) -> 4.6104204e+08 | AT34: =AK34+AL34+AS34 -> 1.0797895e+09 | AW34: =AW33-AW32 -> 4.8056536e+08 | AX34: =AX33-AX32 -> 2.5661923e+08 | AY34: =AY33-AY32 -> 7402057.4 | AZ34: =AZ33-AZ32 -> 3.4120088e+08 | BA34: =BA33-BA32 -> 9861880.2 | BB34: =BB33-BB32 -> 13644753 | BC34: =BC33-BC32 -> 1.3732893e+08 | BD34: =BD33-BD32 -> 1.2587402e+08 | BE34: =SUM(AY34:BD34) -> 6.3531252e+08 | BF34: =AW34+AX34+BE34 -> 1.3724971e+09 | BI34: =BI33-BI32 -> 4.0989235e+08 | BJ34: =BJ33-BJ32 -> 1.8611835e+08 | BK34: =BK33-BK32 -> 8250583.4 | BL34: =BL33-BL32 -> 3.2494272e+08 | BM34: =BM33-BM32 -> 18548993 | BN34: =BN33-BN32 -> 12279819 | BO34: =BO33-BO32 -> 1.4438271e+08 | BP34: =BP33-BP32 -> 2.2756296e+08 | BQ34: =SUM(BK34:BP34) -> 7.3596779e+08 | BR34: =BI34+BJ34+BQ34 -> 1.3319785e+09 | BU34: =BU33-BU32 -> 3.3165039e+08 | BV34: =BV33-BV32 -> 1.1178481e+08 | BW34: =BW33-BW32 -> 7105750.4 | BX34: =BX33-BX32 -> 3.1109024e+08 | BY34: =BY33-BY32 -> 20747448 | BZ34: =BZ33-BZ32 -> 12577712 | CA34: =CA33-CA32 -> 1.4166013e+08 | CB34: =CB33-CB32 -> 4.6747333e+08 | CC34: =SUM(BW34:CB34) -> 9.6065461e+08 | CD34: =BU34+BV34+CC34 -> 1.4040898e+09 | CG34: =CG33-CG32 -> 3.6274008e+08 | CH34: =CH33-CH32 -> 98786938 | CI34: =CI33-CI32 -> 5773546.3 | CJ34: =CJ33-CJ32 -> 2.535356e+08 | CK34: =CK33-CK32 -> 25396899 | CL34: =CL33-CL32 -> 73393925 | CM34: =CM33-CM32 -> 1.1726445e+08 | CN34: =CN33-CN32 -> 1.7342982e+08 | CO34: =SUM(CI34:CN34) -> 6.4879423e+08 | CP34: =CG34+CH34+CO34 -> 1.1103212e+09 | CS34: =CS33-CS32 -> 2.9862983e+08 | CT34: =CT33-CT32 -> 81817923 | CU34: =CU33-CU32 -> 4555469.8 | CV34: =CV33-CV32 -> 2.0301328e+08 | CW34: =CW33-CW32 -> 20837664 | CX34: =CX33-CX32 -> 73913939 | CY34: =CY33-CY32 -> 90329098 | CZ34: =CZ33-CZ32 -> 1.4159448e+08 | DA34: =SUM(CU34:CZ34) -> 5.3424393e+08 | DB34: =CS34+CT34+DA34 -> 9.1469168e+08 | DE34: =DE33-DE32 -> 2.303157e+08 | DF34: =DF33-DF32 -> 69749573 | DG34: =DG33-DG32 -> 3396593.4 | DH34: =DH33-DH32 -> 1.4266098e+08 | DI34: =DI33-DI32 -> 16723612 | DJ34: =DJ33-DJ32 -> 55370958 | DK34: =DK33-DK32 -> 63972226 | DL34: =DL33-DL32 -> 1.0351851e+08 | DM34: =SUM(DG34:DL34) -> 3.8564288e+08 | DN34: =DE34+DF34+DM34 -> 6.8570815e+08 | DQ34: =DQ33-DQ32 -> 1.4357264e+08 | DR34: =DR33-DR32 -> 47554501 | DS34: =DS33-DS32 -> 2066792.3 | DT34: =DT33-DT32 -> 74523485 | DU34: =DU33-DU32 -> 14775225 | DV34: =DV33-DV32 -> 37518395 | DW34: =DW33-DW32 -> 35493970 | DX34: =DX33-DX32 -> 60910825 | DY34: =SUM(DS34:DX34) -> 2.2528869e+08 | DZ34: =DQ34+DR34+DY34 -> 4.1641583e+08 | EC34: =EC33-EC32 -> 31633204 | ED34: =ED33-ED32 -> 13404292 | EE34: =EE33-EE32 -> 725935.09 | EF34: =EF33-EF32 -> 4256850.6 | EG34: =EG33-EG32 -> 13326079 | EH34: =EH33-EH32 -> 17306193 | EI34: =EI33-EI32 -> -2820670.1 | EJ34: =EJ33-EJ32 -> 7611709.6 | EK34: =SUM(EE34:EJ34) -> 40406097 | EL34: =EC34+ED34+EK34 -> 85443593
A36: IBNR Ouverture | B36: 5.885438e+08 | C36: 1.2476529e+09 | D36: 11812.5 | E36: 1.7030127e+08 | F36: 22345782 | G36: 37981871 | H36: 8357006.9 | I36: 1.3441797e+08 | J36: =SUM(D36:I36) -> 3.7341572e+08 | K36: =B36+C36+J36 -> 2.2096124e+09 | L36: ok | M36: =B36 -> 5.885438e+08 | N36: =C36 -> 1.2476529e+09 | O36: =D36 -> 11812.5 | P36: =E36 -> 1.7030127e+08 | Q36: =F36 -> 22345782 | R36: =G36 -> 37981871 | S36: =H36 -> 8357006.9 | T36: =I36 -> 1.3441797e+08 | U36: =SUM(O36:T36) -> 3.7341572e+08 | V36: =M36+N36+U36 -> 2.2096124e+09 | W36: =V36=K36 -> TRUE | Y36: =M37 -> 5.885438e+08 | Z36: =N37 -> 1.2476529e+09 | AA36: =O37 -> 11812.5 | AB36: =P37 -> 1.7030127e+08 | AC36: =Q37 -> 22345782 | AD36: =R37 -> 37981871 | AE36: =S37 -> 8357006.9 | AF36: =T37 -> 1.3441797e+08 | AG36: =SUM(AA36:AF36) -> 3.7341572e+08 | AH36: =Y36+Z36+AG36 -> 2.2096124e+09 | AI36: =AH36=V36 -> TRUE | AK36: =Y37 -> 5.885438e+08 | AL36: =Z37 -> 1.2476529e+09 | AM36: =AA37 -> 11812.5 | AN36: =AB37 -> 1.7030127e+08 | AO36: =AC37 -> 22345782 | AP36: =AD37 -> 37981871 | AQ36: =AE37 -> 8357006.9 | AR36: =AF37 -> 1.3441797e+08 | AS36: =SUM(AM36:AR36) -> 3.7341572e+08 | AT36: =AK36+AL36+AS36 -> 2.2096124e+09 | AU36: =AT36=AH36 -> TRUE | AW36: =AK37 -> 5.885438e+08 | AX36: =AL37 -> 1.2476529e+09 | AY36: =AM37 -> 11812.5 | AZ36: =AN37 -> 1.7030127e+08 | BA36: =AO37 -> 22345782 | BB36: =AP37 -> 37981871 | BC36: =AQ37 -> 8357006.9 | BD36: =AR37 -> 1.3441797e+08 | BE36: =SUM(AY36:BD36) -> 3.7341572e+08 | BF36: =AW36+AX36+BE36 -> 2.2096124e+09 | BG36: =BF36=AT36 -> TRUE | BI36: =AW37 -> 5.885438e+08 | BJ36: =AX37 -> 1.2476529e+09 | BK36: =AY37 -> 11812.5 | BL36: =AZ37 -> 1.7030127e+08 | BM36: =BA37 -> 22345782 | BN36: =BB37 -> 37981871 | BO36: =BC37 -> 8357006.9 | BP36: =BD37 -> 1.3441797e+08 | BQ36: =SUM(BK36:BP36) -> 3.7341572e+08 | BR36: =BI36+BJ36+BQ36 -> 2.2096124e+09 | BU36: =BI37 -> 5.885438e+08 | BV36: =BJ37 -> 1.2476529e+09 | BW36: =BK37 -> 11812.5 | BX36: =BL37 -> 1.7030127e+08 | BY36: =BM37 -> 22345782 | BZ36: =BN37 -> 37981871 | CA36: =BO37 -> 8357006.9 | CB36: =BP37 -> 1.3441797e+08 | CC36: =SUM(BW36:CB36) -> 3.7341572e+08 | CD36: =BU36+BV36+CC36 -> 2.2096124e+09 | CE36: =CD36=BR36 -> TRUE | CG36: =BU37 -> 5.885438e+08 | CH36: =BV37 -> 1.2476529e+09 | CI36: =BW37 -> 11812.5 | CJ36: =BX37 -> 1.7030127e+08 | CK36: =BY37 -> 22345782 | CL36: =BZ37 -> 37981871 | CM36: =CA37 -> 8357006.9 | CN36: =CB37 -> 1.3441797e+08 | CO36: =SUM(CI36:CN36) -> 3.7341572e+08 | CP36: =CG36+CH36+CO36 -> 2.2096124e+09 | CS36: =CG37 -> 5.885438e+08 | CT36: =CH37 -> 1.2476529e+09 | CU36: =CI37 -> 11812.5 | CV36: =CJ37 -> 1.7030127e+08 | CW36: =CK37 -> 22345782 | CX36: =CL37 -> 37981871 | CY36: =CM37 -> 8357006.9 | CZ36: =CN37 -> 1.3441797e+08 | DA36: =SUM(CU36:CZ36) -> 3.7341572e+08 | DB36: =CS36+CT36+DA36 -> 2.2096124e+09 | DE36: =CS37 -> 5.885438e+08 | DF36: =CT37 -> 1.2476529e+09 | DG36: =CU37 -> 11812.5 | DH36: =CV37 -> 1.7030127e+08 | DI36: =CW37 -> 22345782 | DJ36: =CX37 -> 37981871 | DK36: =CY37 -> 8357006.9 | DL36: =CZ37 -> 1.3441797e+08 | DM36: =SUM(DG36:DL36) -> 3.7341572e+08 | DN36: =DE36+DF36+DM36 -> 2.2096124e+09 | DQ36: =DE37 -> 5.885438e+08 | DR36: =DF37 -> 1.2476529e+09 | DS36: =DG37 -> 11812.5 | DT36: =DH37 -> 1.7030127e+08 | DU36: =DI37 -> 22345782 | DV36: =DJ37 -> 37981871 | DW36: =DK37 -> 8357006.9 | DX36: =DL37 -> 1.3441797e+08 | DY36: =SUM(DS36:DX36) -> 3.7341572e+08 | DZ36: =DQ36+DR36+DY36 -> 2.2096124e+09 | EC36: =DQ37 -> 5.885438e+08 | ED36: =DR37 -> 1.2476529e+09 | EE36: =DS37 -> 11812.5 | EF36: =DT37 -> 1.7030127e+08 | EG36: =DU37 -> 22345782 | EH36: =DV37 -> 37981871 | EI36: =DW37 -> 8357006.9 | EJ36: =DX37 -> 1.3441797e+08 | EK36: =SUM(EE36:EJ36) -> 3.7341572e+08 | EL36: =EC36+ED36+EK36 -> 2.2096124e+09
A37: IBNR Clôture | B37: =B36 -> 5.885438e+08 | C37: =C36 -> 1.2476529e+09 | D37: =D36 -> 11812.5 | E37: =E36 -> 1.7030127e+08 | F37: =F36 -> 22345782 | G37: =G36 -> 37981871 | H37: =H36 -> 8357006.9 | I37: =I36 -> 1.3441797e+08 | J37: =SUM(D37:I37) -> 3.7341572e+08 | K37: =B37+C37+J37 -> 2.2096124e+09 | L37: ok | M37: =B37 -> 5.885438e+08 | N37: =C37 -> 1.2476529e+09 | O37: =D37 -> 11812.5 | P37: =E37 -> 1.7030127e+08 | Q37: =F37 -> 22345782 | R37: =G37 -> 37981871 | S37: =H37 -> 8357006.9 | T37: =I37 -> 1.3441797e+08 | U37: =SUM(O37:T37) -> 3.7341572e+08 | V37: =M37+N37+U37 -> 2.2096124e+09 | W37: =V37=K37 -> TRUE | Y37: =Y36 -> 5.885438e+08 | Z37: =Z36 -> 1.2476529e+09 | AA37: =AA36 -> 11812.5 | AB37: =AB36 -> 1.7030127e+08 | AC37: =AC36 -> 22345782 | AD37: =AD36 -> 37981871 | AE37: =AE36 -> 8357006.9 | AF37: =AF36 -> 1.3441797e+08 | AG37: =SUM(AA37:AF37) -> 3.7341572e+08 | AH37: =Y37+Z37+AG37 -> 2.2096124e+09 | AI37: =AH37=V37 -> TRUE | AK37: =AK36 -> 5.885438e+08 | AL37: =AL36 -> 1.2476529e+09 | AM37: =AM36 -> 11812.5 | AN37: =AN36 -> 1.7030127e+08 | AO37: =AO36 -> 22345782 | AP37: =AP36 -> 37981871 | AQ37: =AQ36 -> 8357006.9 | AR37: =AR36 -> 1.3441797e+08 | AS37: =SUM(AM37:AR37) -> 3.7341572e+08 | AT37: =AK37+AL37+AS37 -> 2.2096124e+09 | AU37: =AT37=AH37 -> TRUE | AW37: =AW36 -> 5.885438e+08 | AX37: =AX36 -> 1.2476529e+09 | AY37: =AY36 -> 11812.5 | AZ37: =AZ36 -> 1.7030127e+08 | BA37: =BA36 -> 22345782 | BB37: =BB36 -> 37981871 | BC37: =BC36 -> 8357006.9 | BD37: =BD36 -> 1.3441797e+08 | BE37: =SUM(AY37:BD37) -> 3.7341572e+08 | BF37: =AW37+AX37+BE37 -> 2.2096124e+09 | BG37: =BF37=AT37 -> TRUE | BI37: =BI36 -> 5.885438e+08 | BJ37: =BJ36 -> 1.2476529e+09 | BK37: =BK36 -> 11812.5 | BL37: =BL36 -> 1.7030127e+08 | BM37: =BM36 -> 22345782 | BN37: =BN36 -> 37981871 | BO37: =BO36 -> 8357006.9 | BP37: =BP36 -> 1.3441797e+08 | BQ37: =SUM(BK37:BP37) -> 3.7341572e+08 | BR37: =BI37+BJ37+BQ37 -> 2.2096124e+09 | BU37: =BU36 -> 5.885438e+08 | BV37: =BV36 -> 1.2476529e+09 | BW37: =BW36 -> 11812.5 | BX37: =BX36 -> 1.7030127e+08 | BY37: =BY36 -> 22345782 | BZ37: =BZ36 -> 37981871 | CA37: =CA36 -> 8357006.9 | CB37: =CB36 -> 1.3441797e+08 | CC37: =SUM(BW37:CB37) -> 3.7341572e+08 | CD37: =BU37+BV37+CC37 -> 2.2096124e+09 | CE37: =CD37=BR37 -> TRUE | CG37: =CG36 -> 5.885438e+08 | CH37: =CH36 -> 1.2476529e+09 | CI37: =CI36 -> 11812.5 | CJ37: =CJ36 -> 1.7030127e+08 | CK37: =CK36 -> 22345782 | CL37: =CL36 -> 37981871 | CM37: =CM36 -> 8357006.9 | CN37: =CN36 -> 1.3441797e+08 | CO37: =SUM(CI37:CN37) -> 3.7341572e+08 | CP37: =CG37+CH37+CO37 -> 2.2096124e+09 | CS37: =CS36 -> 5.885438e+08 | CT37: =CT36 -> 1.2476529e+09 | CU37: =CU36 -> 11812.5 | CV37: =CV36 -> 1.7030127e+08 | CW37: =CW36 -> 22345782 | CX37: =CX36 -> 37981871 | CY37: =CY36 -> 8357006.9 | CZ37: =CZ36 -> 1.3441797e+08 | DA37: =SUM(CU37:CZ37) -> 3.7341572e+08 | DB37: =CS37+CT37+DA37 -> 2.2096124e+09 | DE37: =DE36 -> 5.885438e+08 | DF37: =DF36 -> 1.2476529e+09 | DG37: =DG36 -> 11812.5 | DH37: =DH36 -> 1.7030127e+08 | DI37: =DI36 -> 22345782 | DJ37: =DJ36 -> 37981871 | DK37: =DK36 -> 8357006.9 | DL37: =DL36 -> 1.3441797e+08 | DM37: =SUM(DG37:DL37) -> 3.7341572e+08 | DN37: =DE37+DF37+DM37 -> 2.2096124e+09 | DQ37: =DQ36 -> 5.885438e+08 | DR37: =DR36 -> 1.2476529e+09 | DS37: =DS36 -> 11812.5 | DT37: =DT36 -> 1.7030127e+08 | DU37: =DU36 -> 22345782 | DV37: =DV36 -> 37981871 | DW37: =DW36 -> 8357006.9 | DX37: =DX36 -> 1.3441797e+08 | DY37: =SUM(DS37:DX37) -> 3.7341572e+08 | DZ37: =DQ37+DR37+DY37 -> 2.2096124e+09 | EC37: =EC36 -> 5.885438e+08 | ED37: =ED36 -> 1.2476529e+09 | EE37: =EE36 -> 11812.5 | EF37: =EF36 -> 1.7030127e+08 | EG37: =EG36 -> 22345782 | EH37: =EH36 -> 37981871 | EI37: =EI36 -> 8357006.9 | EJ37: =EJ36 -> 1.3441797e+08 | EK37: =SUM(EE37:EJ37) -> 3.7341572e+08 | EL37: =EC37+ED37+EK37 -> 2.2096124e+09
A38: Variation de IBNR CIMA | B38: =B37-B36 -> 0 | C38: =C37-C36 -> 0 | D38: =D37-D36 -> 0 | E38: =E37-E36 -> 0 | F38: =F37-F36 -> 0 | G38: =G37-G36 -> 0 | H38: =H37-H36 -> 0 | I38: =I37-I36 -> 0 | ... K38: =K37-K36 -> 0 | M38: =M37-M36 -> 0 | N38: =N37-N36 -> 0 | O38: =O37-O36 -> 0 | P38: =P37-P36 -> 0 | Q38: =Q37-Q36 -> 0 | R38: =R37-R36 -> 0 | S38: =S37-S36 -> 0 | T38: =T37-T36 -> 0 | ... V38: =V37-V36 -> 0 | Y38: =Y37-Y36 -> 0 | Z38: =Z37-Z36 -> 0 | AA38: =AA37-AA36 -> 0 | AB38: =AB37-AB36 -> 0 | AC38: =AC37-AC36 -> 0 | AD38: =AD37-AD36 -> 0 | AE38: =AE37-AE36 -> 0 | AF38: =AF37-AF36 -> 0 | ... AH38: =AH37-AH36 -> 0 | AK38: =AK37-AK36 -> 0 | AL38: =AL37-AL36 -> 0 | AM38: =AM37-AM36 -> 0 | AN38: =AN37-AN36 -> 0 | AO38: =AO37-AO36 -> 0 | AP38: =AP37-AP36 -> 0 | AQ38: =AQ37-AQ36 -> 0 | AR38: =AR37-AR36 -> 0 | ... AT38: =AT37-AT36 -> 0 | AW38: =AW37-AW36 -> 0 | AX38: =AX37-AX36 -> 0 | AY38: =AY37-AY36 -> 0 | AZ38: =AZ37-AZ36 -> 0 | BA38: =BA37-BA36 -> 0 | BB38: =BB37-BB36 -> 0 | BC38: =BC37-BC36 -> 0 | BD38: =BD37-BD36 -> 0 | ... BF38: =BF37-BF36 -> 0 | BI38: =BI37-BI36 -> 0 | BJ38: =BJ37-BJ36 -> 0 | BK38: =BK37-BK36 -> 0 | BL38: =BL37-BL36 -> 0 | BM38: =BM37-BM36 -> 0 | BN38: =BN37-BN36 -> 0 | BO38: =BO37-BO36 -> 0 | BP38: =BP37-BP36 -> 0 | ... BR38: =BR37-BR36 -> 0 | BU38: =BU37-BU36 -> 0 | BV38: =BV37-BV36 -> 0 | BW38: =BW37-BW36 -> 0 | BX38: =BX37-BX36 -> 0 | BY38: =BY37-BY36 -> 0 | BZ38: =BZ37-BZ36 -> 0 | CA38: =CA37-CA36 -> 0 | CB38: =CB37-CB36 -> 0 | ... CD38: =CD37-CD36 -> 0 | CG38: =CG37-CG36 -> 0 | CH38: =CH37-CH36 -> 0 | CI38: =CI37-CI36 -> 0 | CJ38: =CJ37-CJ36 -> 0 | CK38: =CK37-CK36 -> 0 | CL38: =CL37-CL36 -> 0 | CM38: =CM37-CM36 -> 0 | CN38: =CN37-CN36 -> 0 | ... CP38: =CP37-CP36 -> 0 | CS38: =CS37-CS36 -> 0 | CT38: =CT37-CT36 -> 0 | CU38: =CU37-CU36 -> 0 | CV38: =CV37-CV36 -> 0 | CW38: =CW37-CW36 -> 0 | CX38: =CX37-CX36 -> 0 | CY38: =CY37-CY36 -> 0 | CZ38: =CZ37-CZ36 -> 0 | ... DB38: =DB37-DB36 -> 0 | DE38: =DE37-DE36 -> 0 | DF38: =DF37-DF36 -> 0 | DG38: =DG37-DG36 -> 0 | DH38: =DH37-DH36 -> 0 | DI38: =DI37-DI36 -> 0 | DJ38: =DJ37-DJ36 -> 0 | DK38: =DK37-DK36 -> 0 | DL38: =DL37-DL36 -> 0 | ... DN38: =DN37-DN36 -> 0 | DQ38: =DQ37-DQ36 -> 0 | DR38: =DR37-DR36 -> 0 | DS38: =DS37-DS36 -> 0 | DT38: =DT37-DT36 -> 0 | DU38: =DU37-DU36 -> 0 | DV38: =DV37-DV36 -> 0 | DW38: =DW37-DW36 -> 0 | DX38: =DX37-DX36 -> 0 | ... DZ38: =DZ37-DZ36 -> 0 | EC38: =EC37-EC36 -> 0 | ED38: =ED37-ED36 -> 0 | EE38: =EE37-EE36 -> 0 | EF38: =EF37-EF36 -> 0 | EG38: =EG37-EG36 -> 0 | EH38: =EH37-EH36 -> 0 | EI38: =EI37-EI36 -> 0 | EJ38: =EJ37-EJ36 -> 0 | ... EL38: =EL37-EL36 -> 0
A41: IBNR BE Per. | J41: =SUM(D41:I41) -> 0 | K41: =B41+C41+J41 -> 0 | U41: =SUM(O41:T41) -> 0 | V41: =M41+N41+U41 -> 0 | AG41: =SUM(AA41:AF41) -> 0 | AH41: =Y41+Z41+AG41 -> 0 | AS41: =SUM(AM41:AR41) -> 0 | AT41: =AK41+AL41+AS41 -> 0 | BE41: =SUM(AY41:BD41) -> 0 | BF41: =AW41+AX41+BE41 -> 0 | BQ41: =SUM(BK41:BP41) -> 0 | BR41: =BI41+BJ41+BQ41 -> 0 | CC41: =SUM(BW41:CB41) -> 0 | CD41: =BU41+BV41+CC41 -> 0 | CO41: =SUM(CI41:CN41) -> 0 | CP41: =CG41+CH41+CO41 -> 0 | DA41: =SUM(CU41:CZ41) -> 0 | DB41: =CS41+CT41+DA41 -> 0 | DM41: =SUM(DG41:DL41) -> 0 | DN41: =DE41+DF41+DM41 -> 0 | DY41: =SUM(DS41:DX41) -> 0 | DZ41: =DQ41+DR41+DY41 -> 0 | EK41: =SUM(EE41:EJ41) -> 0 | EL41: =EC41+ED41+EK41 -> 0
A42: IBNR BE Ant. | J42: =SUM(D42:I42) -> 0 | K42: =B42+C42+J42 -> 0 | U42: =SUM(O42:T42) -> 0 | V42: =M42+N42+U42 -> 0 | AG42: =SUM(AA42:AF42) -> 0 | AH42: =Y42+Z42+AG42 -> 0 | AS42: =SUM(AM42:AR42) -> 0 | AT42: =AK42+AL42+AS42 -> 0 | BE42: =SUM(AY42:BD42) -> 0 | BF42: =AW42+AX42+BE42 -> 0 | BQ42: =SUM(BK42:BP42) -> 0 | BR42: =BI42+BJ42+BQ42 -> 0 | CC42: =SUM(BW42:CB42) -> 0 | CD42: =BU42+BV42+CC42 -> 0 | CO42: =SUM(CI42:CN42) -> 0 | CP42: =CG42+CH42+CO42 -> 0 | DA42: =SUM(CU42:CZ42) -> 0 | DB42: =CS42+CT42+DA42 -> 0 | DM42: =SUM(DG42:DL42) -> 0 | DN42: =DE42+DF42+DM42 -> 0 | DY42: =SUM(DS42:DX42) -> 0 | DZ42: =DQ42+DR42+DY42 -> 0 | EK42: =SUM(EE42:EJ42) -> 0 | EL42: =EC42+ED42+EK42 -> 0
A43: Variation de IBNR BE | B43: =B42-B41 -> 0 | C43: =C42-C41 -> 0 | D43: =D42-D41 -> 0 | E43: =E42-E41 -> 0 | F43: =F42-F41 -> 0 | G43: =G42-G41 -> 0 | H43: =H42-H41 -> 0 | I43: =I42-I41 -> 0 | ... K43: =K42-K41 -> 0 | M43: =M42-M41 -> 0 | N43: =N42-N41 -> 0 | O43: =O42-O41 -> 0 | P43: =P42-P41 -> 0 | Q43: =Q42-Q41 -> 0 | R43: =R42-R41 -> 0 | S43: =S42-S41 -> 0 | T43: =T42-T41 -> 0 | ... V43: =V42-V41 -> 0 | Y43: =Y42-Y41 -> 0 | Z43: =Z42-Z41 -> 0 | AA43: =AA42-AA41 -> 0 | AB43: =AB42-AB41 -> 0 | AC43: =AC42-AC41 -> 0 | AD43: =AD42-AD41 -> 0 | AE43: =AE42-AE41 -> 0 | AF43: =AF42-AF41 -> 0 | ... AH43: =AH42-AH41 -> 0 | AK43: =AK42-AK41 -> 0 | AL43: =AL42-AL41 -> 0 | AM43: =AM42-AM41 -> 0 | AN43: =AN42-AN41 -> 0 | AO43: =AO42-AO41 -> 0 | AP43: =AP42-AP41 -> 0 | AQ43: =AQ42-AQ41 -> 0 | AR43: =AR42-AR41 -> 0 | ... AT43: =AT42-AT41 -> 0 | AW43: =AW42-AW41 -> 0 | AX43: =AX42-AX41 -> 0 | AY43: =AY42-AY41 -> 0 | AZ43: =AZ42-AZ41 -> 0 | BA43: =BA42-BA41 -> 0 | BB43: =BB42-BB41 -> 0 | BC43: =BC42-BC41 -> 0 | BD43: =BD42-BD41 -> 0 | ... BF43: =BF42-BF41 -> 0 | BI43: =BI42-BI41 -> 0 | BJ43: =BJ42-BJ41 -> 0 | BK43: =BK42-BK41 -> 0 | BL43: =BL42-BL41 -> 0 | BM43: =BM42-BM41 -> 0 | BN43: =BN42-BN41 -> 0 | BO43: =BO42-BO41 -> 0 | BP43: =BP42-BP41 -> 0 | ... BR43: =BR42-BR41 -> 0 | BU43: =BU42-BU41 -> 0 | BV43: =BV42-BV41 -> 0 | BW43: =BW42-BW41 -> 0 | BX43: =BX42-BX41 -> 0 | BY43: =BY42-BY41 -> 0 | BZ43: =BZ42-BZ41 -> 0 | CA43: =CA42-CA41 -> 0 | CB43: =CB42-CB41 -> 0 | ... CD43: =CD42-CD41 -> 0 | CG43: =CG42-CG41 -> 0 | CH43: =CH42-CH41 -> 0 | CI43: =CI42-CI41 -> 0 | CJ43: =CJ42-CJ41 -> 0 | CK43: =CK42-CK41 -> 0 | CL43: =CL42-CL41 -> 0 | CM43: =CM42-CM41 -> 0 | CN43: =CN42-CN41 -> 0 | ... CP43: =CP42-CP41 -> 0 | CS43: =CS42-CS41 -> 0 | CT43: =CT42-CT41 -> 0 | CU43: =CU42-CU41 -> 0 | CV43: =CV42-CV41 -> 0 | CW43: =CW42-CW41 -> 0 | CX43: =CX42-CX41 -> 0 | CY43: =CY42-CY41 -> 0 | CZ43: =CZ42-CZ41 -> 0 | ... DB43: =DB42-DB41 -> 0 | DE43: =DE42-DE41 -> 0 | DF43: =DF42-DF41 -> 0 | DG43: =DG42-DG41 -> 0 | DH43: =DH42-DH41 -> 0 | DI43: =DI42-DI41 -> 0 | DJ43: =DJ42-DJ41 -> 0 | DK43: =DK42-DK41 -> 0 | DL43: =DL42-DL41 -> 0 | ... DN43: =DN42-DN41 -> 0 | DQ43: =DQ42-DQ41 -> 0 | DR43: =DR42-DR41 -> 0 | DS43: =DS42-DS41 -> 0 | DT43: =DT42-DT41 -> 0 | DU43: =DU42-DU41 -> 0 | DV43: =DV42-DV41 -> 0 | DW43: =DW42-DW41 -> 0 | DX43: =DX42-DX41 -> 0 | ... DZ43: =DZ42-DZ41 -> 0 | EC43: =EC42-EC41 -> 0 | ED43: =ED42-ED41 -> 0 | EE43: =EE42-EE41 -> 0 | EF43: =EF42-EF41 -> 0 | EG43: =EG42-EG41 -> 0 | EH43: =EH42-EH41 -> 0 | EI43: =EI42-EI41 -> 0 | EJ43: =EJ42-EJ41 -> 0 | ... EL43: =EL42-EL41 -> 0
A45: SAP hors chargement Per. | C45: 0 | D45: 0 | J45: =SUM(D45:I45) -> 0 | K45: =B45+C45+J45 -> 0 | L45: ok | M45: =B45 -> 0 | N45: =C45 -> 0 | O45: =D45 -> 0 | P45: =E45 -> 0 | Q45: =F45 -> 0 | R45: =G45 -> 0 | S45: =H45 -> 0 | T45: =I45 -> 0 | U45: =SUM(O45:T45) -> 0 | V45: =M45+N45+U45 -> 0 | Y45: =M45*Y144 -> 0 | Z45: =N45*Z144 -> 0 | AA45: =O45*AA144 -> 0 | AB45: =P45*AB144 -> 0 | AC45: =Q45*AC144 -> 0 | AD45: =R45*AD144 -> 0 | AE45: =S45*AE144 -> 0 | AF45: =T45*AF144 -> 0 | AG45: =SUM(AA45:AF45) -> 0 | AH45: =Y45+Z45+AG45 -> 0 | AK45: =Y45*AK144 -> 0 | AL45: =Z45*AL144 -> 0 | AM45: =AA45*AM144 -> 0 | AN45: =AB45*AN144 -> 0 | AO45: =AC45*AO144 -> 0 | AP45: =AD45*AP144 -> 0 | AQ45: =AE45*AQ144 -> 0 | AR45: =AF45*AR144 -> 0 | AS45: =SUM(AM45:AR45) -> 0 | AT45: =AK45+AL45+AS45 -> 0 | AW45: =AK45*AW144 -> 0 | AX45: =AL45*AX144 -> 0 | AY45: =AM45*AY144 -> 0 | AZ45: =AN45*AZ144 -> 0 | BA45: =AO45*BA144 -> 0 | BB45: =AP45*BB144 -> 0 | BC45: =AQ45*BC144 -> 0 | BD45: =AR45*BD144 -> 0 | BE45: =SUM(AY45:BD45) -> 0 | BF45: =AW45+AX45+BE45 -> 0 | BI45: =AW45*BI144 -> 0 | BJ45: =AX45*BJ144 -> 0 | BK45: =AY45*BK144 -> 0 | BL45: =AZ45*BL144 -> 0 | BM45: =BA45*BM144 -> 0 | BN45: =BB45*BN144 -> 0 | BO45: =BC45*BO144 -> 0 | BP45: =BD45*BP144 -> 0 | BQ45: =SUM(BK45:BP45) -> 0 | BR45: =BI45+BJ45+BQ45 -> 0 | BU45: =BI45*BU144 -> 0 | BV45: =BJ45*BV144 -> 0 | BW45: =BK45*BW144 -> 0 | BX45: =BL45*BX144 -> 0 | BY45: =BM45*BY144 -> 0 | BZ45: =BN45*BZ144 -> 0 | CA45: =BO45*CA144 -> 0 | CB45: =BP45*CB144 -> 0 | CC45: =SUM(BW45:CB45) -> 0 | CD45: =BU45+BV45+CC45 -> 0 | CG45: =BU45*CG144 -> 0 | CH45: =BV45*CH144 -> 0 | CI45: =BW45*CI144 -> 0 | CJ45: =BX45*CJ144 -> 0 | CK45: =BY45*CK144 -> 0 | CL45: =BZ45*CL144 -> 0 | CM45: =CA45*CM144 -> 0 | CN45: =CB45*CN144 -> 0 | CO45: =SUM(CI45:CN45) -> 0 | CP45: =CG45+CH45+CO45 -> 0 | CS45: =CG45*CS144 -> 0 | CT45: =CH45*CT144 -> 0 | CU45: =CI45*CU144 -> 0 | CV45: =CJ45*CV144 -> 0 | CW45: =CK45*CW144 -> 0 | CX45: =CL45*CX144 -> 0 | CY45: =CM45*CY144 -> 0 | CZ45: =CN45*CZ144 -> 0 | DA45: =SUM(CU45:CZ45) -> 0 | DB45: =CS45+CT45+DA45 -> 0 | DE45: =CS45*DE144 -> 0 | DF45: =CT45*DF144 -> 0 | DG45: =CU45*DG144 -> 0 | DH45: =CV45*DH144 -> 0 | DI45: =CW45*DI144 -> 0 | DJ45: =CX45*DJ144 -> 0 | DK45: =CY45*DK144 -> 0 | DL45: =CZ45*DL144 -> 0 | DM45: =SUM(DG45:DL45) -> 0 | DN45: =DE45+DF45+DM45 -> 0 | DQ45: =DE45*DQ144 -> 0 | DR45: =DF45*DR144 -> 0 | DS45: =DG45*DS144 -> 0 | DT45: =DH45*DT144 -> 0 | DU45: =DI45*DU144 -> 0 | DV45: =DJ45*DV144 -> 0 | DW45: =DK45*DW144 -> 0 | DX45: =DL45*DX144 -> 0 | DY45: =SUM(DS45:DX45) -> 0 | DZ45: =DQ45+DR45+DY45 -> 0 | EC45: =DQ45*EC144 -> 0 | ED45: =DR45*ED144 -> 0 | EE45: =DS45*EE144 -> 0 | EF45: =DT45*EF144 -> 0 | EG45: =DU45*EG144 -> 0 | EH45: =DV45*EH144 -> 0 | EI45: =DW45*EI144 -> 0 | EJ45: =DX45*EJ144 -> 0 | EK45: =SUM(EE45:EJ45) -> 0 | EL45: =EC45+ED45+EK45 -> 0
A46: SAP hors chargement Ant. | B46: =7522931981.67789+2357994271.90149 -> 9.8809263e+09 | C46: 0 | D46: 34843226 | E46: =1215581386.72406+1047231305.4507 -> 2.2628127e+09 | F46: =173715481.305106+186672000.406715 -> 3.6038748e+08 | G46: =842520837.956772+161400138.002678 -> 1.003921e+09 | H46: =741192559.1+445374226.305127 -> 1.1865668e+09 | I46: =601858505.571231+252853251.075699 -> 8.5471176e+08 | J46: =SUM(D46:I46) -> 5.7032429e+09 | K46: =B46+C46+J46 -> 1.5584169e+10 | L46: ok | M46: =B46 -> 9.8809263e+09 | N46: =C46 -> 0 | O46: =D46 -> 34843226 | P46: =E46 -> 2.2628127e+09 | Q46: =F46 -> 3.6038748e+08 | R46: =G46 -> 1.003921e+09 | S46: =H46 -> 1.1865668e+09 | T46: =I46 -> 8.5471176e+08 | U46: =SUM(O46:T46) -> 5.7032429e+09 | V46: =M46+N46+U46 -> 1.5584169e+10 | Y46: =M46 -> 9.8809263e+09 | Z46: =N46 -> 0 | AA46: =O46 -> 34843226 | AB46: =P46 -> 2.2628127e+09 | AC46: =Q46 -> 3.6038748e+08 | AD46: =R46 -> 1.003921e+09 | AE46: =S46 -> 1.1865668e+09 | AF46: =T46 -> 8.5471176e+08 | AG46: =U46 -> 5.7032429e+09 | AH46: =Y46+Z46+AG46 -> 1.5584169e+10 | AK46: =Y46*AK145 -> 9.8809263e+09 | AL46: =Z46*AL145 -> 0 | AM46: =AA46*AM145 -> 34843226 | AN46: =AB46*AN145 -> 2.2628127e+09 | AO46: =AC46*AO145 -> 3.6038748e+08 | AP46: =AD46*AP145 -> 1.003921e+09 | AQ46: =AE46*AQ145 -> 1.1865668e+09 | AR46: =AF46*AR145 -> 8.5471176e+08 | AS46: =SUM(AM46:AR46) -> 5.7032429e+09 | AT46: =AK46+AL46+AS46 -> 1.5584169e+10 | AW46: =AK46*AW145 -> 9.8809263e+09 | AX46: =AL46*AX145 -> 0 | AY46: =AM46*AY145 -> 34843226 | AZ46: =AN46*AZ145 -> 2.2628127e+09 | BA46: =AO46*BA145 -> 3.6038748e+08 | BB46: =AP46*BB145 -> 1.003921e+09 | BC46: =AQ46*BC145 -> 1.1865668e+09 | BD46: =AR46*BD145 -> 8.5471176e+08 | BE46: =SUM(AY46:BD46) -> 5.7032429e+09 | BF46: =AW46+AX46+BE46 -> 1.5584169e+10 | BI46: =AW46*BI145 -> 9.8809263e+09 | BJ46: =AX46*BJ145 -> 0 | BK46: =AY46*BK145 -> 34843226 | BL46: =AZ46*BL145 -> 2.2628127e+09 | BM46: =BA46*BM145 -> 3.6038748e+08 | BN46: =BB46*BN145 -> 1.003921e+09 | BO46: =BC46*BO145 -> 1.1865668e+09 | BP46: =BD46*BP145 -> 8.5471176e+08 | BQ46: =SUM(BK46:BP46) -> 5.7032429e+09 | BR46: =BI46+BJ46+BQ46 -> 1.5584169e+10 | BU46: =BI46*BU145 -> 9.8809263e+09 | BV46: =BJ46*BV145 -> 0 | BW46: =BK46*BW145 -> 34843226 | BX46: =BL46*BX145 -> 2.2628127e+09 | BY46: =BM46*BY145 -> 3.6038748e+08 | BZ46: =BN46*BZ145 -> 1.003921e+09 | CA46: =BO46*CA145 -> 1.1865668e+09 | CB46: =BP46*CB145 -> 8.5471176e+08 | CC46: =SUM(BW46:CB46) -> 5.7032429e+09 | CD46: =BU46+BV46+CC46 -> 1.5584169e+10 | CG46: =BU46*CG145 -> 9.8809263e+09 | CH46: =BV46*CH145 -> 0 | CI46: =BW46*CI145 -> 34843226 | CJ46: =BX46*CJ145 -> 2.2628127e+09 | CK46: =BY46*CK145 -> 3.6038748e+08 | CL46: =BZ46*CL145 -> 1.003921e+09 | CM46: =CA46*CM145 -> 1.1865668e+09 | CN46: =CB46*CN145 -> 8.5471176e+08 | CO46: =SUM(CI46:CN46) -> 5.7032429e+09 | CP46: =CG46+CH46+CO46 -> 1.5584169e+10 | CS46: =CG46*CS145 -> 9.8809263e+09 | CT46: =CH46*CT145 -> 0 | CU46: =CI46*CU145 -> 34843226 | CV46: =CJ46*CV145 -> 2.2628127e+09 | CW46: =CK46*CW145 -> 3.6038748e+08 | CX46: =CL46*CX145 -> 1.003921e+09 | CY46: =CM46*CY145 -> 1.1865668e+09 | CZ46: =CN46*CZ145 -> 8.5471176e+08 | DA46: =SUM(CU46:CZ46) -> 5.7032429e+09 | DB46: =CS46+CT46+DA46 -> 1.5584169e+10 | DE46: =CS46*DE145 -> 9.8809263e+09 | DF46: =CT46*DF145 -> 0 | DG46: =CU46*DG145 -> 34843226 | DH46: =CV46*DH145 -> 2.2628127e+09 | DI46: =CW46*DI145 -> 3.6038748e+08 | DJ46: =CX46*DJ145 -> 1.003921e+09 | DK46: =CY46*DK145 -> 1.1865668e+09 | DL46: =CZ46*DL145 -> 8.5471176e+08 | DM46: =SUM(DG46:DL46) -> 5.7032429e+09 | DN46: =DE46+DF46+DM46 -> 1.5584169e+10 | DQ46: =DE46*DQ145 -> 9.8809263e+09 | DR46: =DF46*DR145 -> 0 | DS46: =DG46*DS145 -> 34843226 | DT46: =DH46*DT145 -> 2.2628127e+09 | DU46: =DI46*DU145 -> 3.6038748e+08 | DV46: =DJ46*DV145 -> 1.003921e+09 | DW46: =DK46*DW145 -> 1.1865668e+09 | DX46: =DL46*DX145 -> 8.5471176e+08 | DY46: =SUM(DS46:DX46) -> 5.7032429e+09 | DZ46: =DQ46+DR46+DY46 -> 1.5584169e+10 | EC46: =DQ46*EC145 -> 9.8809263e+09 | ED46: =DR46*ED145 -> 0 | EE46: =DS46*EE145 -> 34843226 | EF46: =DT46*EF145 -> 2.2628127e+09 | EG46: =DU46*EG145 -> 3.6038748e+08 | EH46: =DV46*EH145 -> 1.003921e+09 | EI46: =DW46*EI145 -> 1.1865668e+09 | EJ46: =DX46*EJ145 -> 8.5471176e+08 | EK46: =SUM(EE46:EJ46) -> 5.7032429e+09 | EL46: =EC46+ED46+EK46 -> 1.5584169e+10
A47: Recours Per. | B47: 1403750 | C47: 0 | D47: 0 | E47: 0 | F47: 0 | G47: 0 | H47: 0 | I47: 0 | J47: =SUM(D47:I47) -> 0 | K47: =B47+C47+J47 -> 1403750 | L47: ok | M47: =B47 -> 1403750 | N47: =C47 -> 0 | O47: =D47 -> 0 | P47: =E47 -> 0 | Q47: =F47 -> 0 | R47: =G47 -> 0 | S47: =H47 -> 0 | T47: =I47 -> 0 | U47: =SUM(O47:T47) -> 0 | V47: =M47+N47+U47 -> 1403750 | W47: =V47=K47 -> TRUE | Y47: =M47 -> 1403750 | Z47: =N47 -> 0 | AA47: =O47 -> 0 | AB47: =P47 -> 0 | AC47: =Q47 -> 0 | AD47: =R47 -> 0 | AE47: =S47 -> 0 | AF47: =T47 -> 0 | AG47: =SUM(AA47:AF47) -> 0 | AH47: =Y47+Z47+AG47 -> 1403750 | AI47: =AH47=V47 -> TRUE | AK47: =Y47*AK146 -> 1403750 | AL47: =Z47*AL146 -> 0 | AM47: =AA47*AM146 -> 0 | AN47: =AB47*AN146 -> 0 | AO47: =AC47*AO146 -> 0 | AP47: =AD47*AP146 -> 0 | AQ47: =AE47*AQ146 -> 0 | AR47: =AF47*AR146 -> 0 | AS47: =SUM(AM47:AR47) -> 0 | AT47: =AK47+AL47+AS47 -> 1403750 | AU47: =AT47=AH47 -> TRUE | AW47: =AK47*AW146 -> 1403750 | AX47: =AL47*AX146 -> 0 | AY47: =AM47*AY146 -> 0 | AZ47: =AN47*AZ146 -> 0 | BA47: =AO47*BA146 -> 0 | BB47: =AP47*BB146 -> 0 | BC47: =AQ47*BC146 -> 0 | BD47: =AR47*BD146 -> 0 | BE47: =SUM(AY47:BD47) -> 0 | BF47: =AW47+AX47+BE47 -> 1403750 | BG47: =BF47=AT47 -> TRUE | BI47: =AW47*BI146 -> 1403750 | BJ47: =AX47*BJ146 -> 0 | BK47: =AY47*BK146 -> 0 | BL47: =AZ47*BL146 -> 0 | BM47: =BA47*BM146 -> 0 | BN47: =BB47*BN146 -> 0 | BO47: =BC47*BO146 -> 0 | BP47: =BD47*BP146 -> 0 | BQ47: =SUM(BK47:BP47) -> 0 | BR47: =BI47+BJ47+BQ47 -> 1403750 | BU47: =BI47*BU146 -> 1403750 | BV47: =BJ47*BV146 -> 0 | BW47: =BK47*BW146 -> 0 | BX47: =BL47*BX146 -> 0 | BY47: =BM47*BY146 -> 0 | BZ47: =BN47*BZ146 -> 0 | CA47: =BO47*CA146 -> 0 | CB47: =BP47*CB146 -> 0 | CC47: =SUM(BW47:CB47) -> 0 | CD47: =BU47+BV47+CC47 -> 1403750 | CE47: =CD47=BR47 -> TRUE | CG47: =BU47*CG146 -> 1403750 | CH47: =BV47*CH146 -> 0 | CI47: =BW47*CI146 -> 0 | CJ47: =BX47*CJ146 -> 0 | CK47: =BY47*CK146 -> 0 | CL47: =BZ47*CL146 -> 0 | CM47: =CA47*CM146 -> 0 | CN47: =CB47*CN146 -> 0 | CO47: =SUM(CI47:CN47) -> 0 | CP47: =CG47+CH47+CO47 -> 1403750 | CS47: =CG47*CS146 -> 1403750 | CT47: =CH47*CT146 -> 0 | CU47: =CI47*CU146 -> 0 | CV47: =CJ47*CV146 -> 0 | CW47: =CK47*CW146 -> 0 | CX47: =CL47*CX146 -> 0 | CY47: =CM47*CY146 -> 0 | CZ47: =CN47*CZ146 -> 0 | DA47: =SUM(CU47:CZ47) -> 0 | DB47: =CS47+CT47+DA47 -> 1403750 | DE47: =CS47*DE146 -> 1403750 | DF47: =CT47*DF146 -> 0 | DG47: =CU47*DG146 -> 0 | DH47: =CV47*DH146 -> 0 | DI47: =CW47*DI146 -> 0 | DJ47: =CX47*DJ146 -> 0 | DK47: =CY47*DK146 -> 0 | DL47: =CZ47*DL146 -> 0 | DM47: =SUM(DG47:DL47) -> 0 | DN47: =DE47+DF47+DM47 -> 1403750 | DQ47: =DE47*DQ146 -> 1403750 | DR47: =DF47*DR146 -> 0 | DS47: =DG47*DS146 -> 0 | DT47: =DH47*DT146 -> 0 | DU47: =DI47*DU146 -> 0 | DV47: =DJ47*DV146 -> 0 | DW47: =DK47*DW146 -> 0 | DX47: =DL47*DX146 -> 0 | DY47: =SUM(DS47:DX47) -> 0 | DZ47: =DQ47+DR47+DY47 -> 1403750 | EC47: =DQ47*EC146 -> 1403750 | ED47: =DR47*ED146 -> 0 | EE47: =DS47*EE146 -> 0 | EF47: =DT47*EF146 -> 0 | EG47: =DU47*EG146 -> 0 | EH47: =DV47*EH146 -> 0 | EI47: =DW47*EI146 -> 0 | EJ47: =DX47*EJ146 -> 0 | EK47: =SUM(EE47:EJ47) -> 0 | EL47: =EC47+ED47+EK47 -> 1403750
A48: Recours Per.Anté | B48: 52319871 | C48: 5602656 | D48: 2580944 | E48: 697269394 | F48: 124699446 | G48: 13662804 | H48: 0 | I48: 1.9198743e+08 | J48: =SUM(D48:I48) -> 1.0302e+09 | K48: =B48+C48+J48 -> 1.0881225e+09 | L48: ok | M48: =B48 -> 52319871 | N48: =C48 -> 5602656 | O48: =D48 -> 2580944 | P48: =E48 -> 697269394 | Q48: =F48 -> 124699446 | R48: =G48 -> 13662804 | S48: =H48 -> 0 | T48: =I48 -> 1.9198743e+08 | U48: =SUM(O48:T48) -> 1.0302e+09 | V48: =M48+N48+U48 -> 1.0881225e+09 | W48: =V48=K48 -> TRUE | Y48: =M48 -> 52319871 | Z48: =N48 -> 5602656 | AA48: =O48 -> 2580944 | AB48: =P48 -> 697269394 | AC48: =Q48 -> 124699446 | AD48: =R48 -> 13662804 | AE48: =S48 -> 0 | AF48: =T48 -> 1.9198743e+08 | AG48: =SUM(AA48:AF48) -> 1.0302e+09 | AH48: =Y48+Z48+AG48 -> 1.0881225e+09 | AI48: =AH48=V48 -> TRUE | AK48: =Y48*AK147 -> 52319871 | AL48: =Z48*AL147 -> 5602656 | AM48: =AA48*AM147 -> 2580944 | AN48: =AB48*AN147 -> 697269394 | AO48: =AC48*AO147 -> 124699446 | AP48: =AD48*AP147 -> 13662804 | AQ48: =AE48*AQ147 -> 0 | AR48: =AF48*AR147 -> 1.9198743e+08 | AS48: =SUM(AM48:AR48) -> 1.0302e+09 | AT48: =AK48+AL48+AS48 -> 1.0881225e+09 | AU48: =AT48=AH48 -> TRUE | AW48: =AK48*AW147 -> 52319871 | AX48: =AL48*AX147 -> 5602656 | AY48: =AM48*AY147 -> 2580944 | AZ48: =AN48*AZ147 -> 697269394 | BA48: =AO48*BA147 -> 124699446 | BB48: =AP48*BB147 -> 13662804 | BC48: =AQ48*BC147 -> 0 | BD48: =AR48*BD147 -> 1.9198743e+08 | BE48: =SUM(AY48:BD48) -> 1.0302e+09 | BF48: =AW48+AX48+BE48 -> 1.0881225e+09 | BG48: =BF48=AT48 -> TRUE | BI48: =AW48*BI147 -> 52319871 | BJ48: =AX48*BJ147 -> 5602656 | BK48: =AY48*BK147 -> 2580944 | BL48: =AZ48*BL147 -> 697269394 | BM48: =BA48*BM147 -> 124699446 | BN48: =BB48*BN147 -> 13662804 | BO48: =BC48*BO147 -> 0 | BP48: =BD48*BP147 -> 1.9198743e+08 | BQ48: =SUM(BK48:BP48) -> 1.0302e+09 | BR48: =BI48+BJ48+BQ48 -> 1.0881225e+09 | BU48: =BI48*BU147 -> 52319871 | BV48: =BJ48*BV147 -> 5602656 | BW48: =BK48*BW147 -> 2580944 | BX48: =BL48*BX147 -> 697269394 | BY48: =BM48*BY147 -> 124699446 | BZ48: =BN48*BZ147 -> 13662804 | CA48: =BO48*CA147 -> 0 | CB48: =BP48*CB147 -> 1.9198743e+08 | CC48: =SUM(BW48:CB48) -> 1.0302e+09 | CD48: =BU48+BV48+CC48 -> 1.0881225e+09 | CE48: =CD48=BR48 -> TRUE | CG48: =BU48*CG147 -> 52319871 | CH48: =BV48*CH147 -> 5602656 | CI48: =BW48*CI147 -> 2580944 | CJ48: =BX48*CJ147 -> 697269394 | CK48: =BY48*CK147 -> 124699446 | CL48: =BZ48*CL147 -> 13662804 | CM48: =CA48*CM147 -> 0 | CN48: =CB48*CN147 -> 1.9198743e+08 | CO48: =SUM(CI48:CN48) -> 1.0302e+09 | CP48: =CG48+CH48+CO48 -> 1.0881225e+09 | CS48: =CG48*CS147 -> 52319871 | CT48: =CH48*CT147 -> 5602656 | CU48: =CI48*CU147 -> 2580944 | CV48: =CJ48*CV147 -> 697269394 | CW48: =CK48*CW147 -> 124699446 | CX48: =CL48*CX147 -> 13662804 | CY48: =CM48*CY147 -> 0 | CZ48: =CN48*CZ147 -> 1.9198743e+08 | DA48: =SUM(CU48:CZ48) -> 1.0302e+09 | DB48: =CS48+CT48+DA48 -> 1.0881225e+09 | DE48: =CS48*DE147 -> 52319871 | DF48: =CT48*DF147 -> 5602656 | DG48: =CU48*DG147 -> 2580944 | DH48: =CV48*DH147 -> 697269394 | DI48: =CW48*DI147 -> 124699446 | DJ48: =CX48*DJ147 -> 13662804 | DK48: =CY48*DK147 -> 0 | DL48: =CZ48*DL147 -> 1.9198743e+08 | DM48: =SUM(DG48:DL48) -> 1.0302e+09 | DN48: =DE48+DF48+DM48 -> 1.0881225e+09 | DQ48: =DE48*DQ147 -> 52319871 | DR48: =DF48*DR147 -> 5602656 | DS48: =DG48*DS147 -> 2580944 | DT48: =DH48*DT147 -> 697269394 | DU48: =DI48*DU147 -> 124699446 | DV48: =DJ48*DV147 -> 13662804 | DW48: =DK48*DW147 -> 0 | DX48: =DL48*DX147 -> 1.9198743e+08 | DY48: =SUM(DS48:DX48) -> 1.0302e+09 | DZ48: =DQ48+DR48+DY48 -> 1.0881225e+09 | EC48: =DQ48*EC147 -> 52319871 | ED48: =DR48*ED147 -> 5602656 | EE48: =DS48*EE147 -> 2580944 | EF48: =DT48*EF147 -> 697269394 | EG48: =DU48*EG147 -> 124699446 | EH48: =DV48*EH147 -> 13662804 | EI48: =DW48*EI147 -> 0 | EJ48: =DX48*EJ147 -> 1.9198743e+08 | EK48: =SUM(EE48:EJ48) -> 1.0302e+09 | EL48: =EC48+ED48+EK48 -> 1.0881225e+09
A49: SAP net de recours hors chargement | B49: =(B46-B47*0)+(B45-B48*0) -> 9.8809263e+09 | C49: =(C46-C47*0)+(C45-C48*0) -> 0 | D49: =(D46-D47*0)+(D45-D48*0) -> 34843226 | E49: =(E46-E47*0)+(E45-E48*0) -> 2.2628127e+09 | F49: =(F46-F47*0)+(F45-F48*0) -> 3.6038748e+08 | G49: =(G46-G47*0)+(G45-G48*0) -> 1.003921e+09 | H49: =(H46-H47*0)+(H45-H48*0) -> 1.1865668e+09 | I49: =(I46-I47*0)+(I45-I48*0) -> 8.5471176e+08 | J49: =SUM(D49:I49) -> 5.7032429e+09 | K49: =B49+C49+J49 -> 1.5584169e+10 | M49: =(M46-M47*0)+(M45-M48*0) -> 9.8809263e+09 | N49: =(N46-N47*0)+(N45-N48*0) -> 0 | O49: =(O46-O47*0)+(O45-O48*0) -> 34843226 | P49: =(P46-P47*0)+(P45-P48*0) -> 2.2628127e+09 | Q49: =(Q46-Q47*0)+(Q45-Q48*0) -> 3.6038748e+08 | R49: =(R46-R47*0)+(R45-R48*0) -> 1.003921e+09 | S49: =(S46-S47*0)+(S45-S48*0) -> 1.1865668e+09 | T49: =(T46-T47*0)+(T45-T48*0) -> 8.5471176e+08 | U49: =SUM(O49:T49) -> 5.7032429e+09 | V49: =M49+N49+U49 -> 1.5584169e+10 | Y49: =(Y46-Y47*0)+(Y45-Y48*0) -> 9.8809263e+09 | Z49: =(Z46-Z47*0)+(Z45-Z48*0) -> 0 | AA49: =(AA46-AA47*0)+(AA45-AA48*0) -> 34843226 | AB49: =(AB46-AB47*0)+(AB45-AB48*0) -> 2.2628127e+09 | AC49: =(AC46-AC47*0)+(AC45-AC48*0) -> 3.6038748e+08 | AD49: =(AD46-AD47*0)+(AD45-AD48*0) -> 1.003921e+09 | AE49: =(AE46-AE47*0)+(AE45-AE48*0) -> 1.1865668e+09 | AF49: =(AF46-AF47*0)+(AF45-AF48*0) -> 8.5471176e+08 | AG49: =SUM(AA49:AF49) -> 5.7032429e+09 | AH49: =Y49+Z49+AG49 -> 1.5584169e+10 | AK49: =(AK46-AK47*0)+(AK45-AK48*0) -> 9.8809263e+09 | AL49: =(AL46-AL47*0)+(AL45-AL48*0) -> 0 | AM49: =(AM46-AM47*0)+(AM45-AM48*0) -> 34843226 | AN49: =(AN46-AN47*0)+(AN45-AN48*0) -> 2.2628127e+09 | AO49: =(AO46-AO47*0)+(AO45-AO48*0) -> 3.6038748e+08 | AP49: =(AP46-AP47*0)+(AP45-AP48*0) -> 1.003921e+09 | AQ49: =(AQ46-AQ47*0)+(AQ45-AQ48*0) -> 1.1865668e+09 | AR49: =(AR46-AR47*0)+(AR45-AR48*0) -> 8.5471176e+08 | AS49: =SUM(AM49:AR49) -> 5.7032429e+09 | AT49: =AK49+AL49+AS49 -> 1.5584169e+10 | AW49: =(AW46-AW47*0)+(AW45-AW48*0) -> 9.8809263e+09 | AX49: =(AX46-AX47*0)+(AX45-AX48*0) -> 0 | AY49: =(AY46-AY47*0)+(AY45-AY48*0) -> 34843226 | AZ49: =(AZ46-AZ47*0)+(AZ45-AZ48*0) -> 2.2628127e+09 | BA49: =(BA46-BA47*0)+(BA45-BA48*0) -> 3.6038748e+08 | BB49: =(BB46-BB47*0)+(BB45-BB48*0) -> 1.003921e+09 | BC49: =(BC46-BC47*0)+(BC45-BC48*0) -> 1.1865668e+09 | BD49: =(BD46-BD47*0)+(BD45-BD48*0) -> 8.5471176e+08 | BE49: =SUM(AY49:BD49) -> 5.7032429e+09 | BF49: =AW49+AX49+BE49 -> 1.5584169e+10 | BI49: =(BI46-BI47*0)+(BI45-BI48*0) -> 9.8809263e+09 | BJ49: =(BJ46-BJ47*0)+(BJ45-BJ48*0) -> 0 | BK49: =(BK46-BK47*0)+(BK45-BK48*0) -> 34843226 | BL49: =(BL46-BL47*0)+(BL45-BL48*0) -> 2.2628127e+09 | BM49: =(BM46-BM47*0)+(BM45-BM48*0) -> 3.6038748e+08 | BN49: =(BN46-BN47*0)+(BN45-BN48*0) -> 1.003921e+09 | BO49: =(BO46-BO47*0)+(BO45-BO48*0) -> 1.1865668e+09 | BP49: =(BP46-BP47*0)+(BP45-BP48*0) -> 8.5471176e+08 | BQ49: =SUM(BK49:BP49) -> 5.7032429e+09 | BR49: =BI49+BJ49+BQ49 -> 1.5584169e+10 | BU49: =(BU46-BU47*0)+(BU45-BU48*0) -> 9.8809263e+09 | BV49: =(BV46-BV47*0)+(BV45-BV48*0) -> 0 | BW49: =(BW46-BW47*0)+(BW45-BW48*0) -> 34843226 | BX49: =(BX46-BX47*0)+(BX45-BX48*0) -> 2.2628127e+09 | BY49: =(BY46-BY47*0)+(BY45-BY48*0) -> 3.6038748e+08 | BZ49: =(BZ46-BZ47*0)+(BZ45-BZ48*0) -> 1.003921e+09 | CA49: =(CA46-CA47*0)+(CA45-CA48*0) -> 1.1865668e+09 | CB49: =(CB46-CB47*0)+(CB45-CB48*0) -> 8.5471176e+08 | CC49: =SUM(BW49:CB49) -> 5.7032429e+09 | CD49: =BU49+BV49+CC49 -> 1.5584169e+10 | CG49: =(CG46-CG47*0)+(CG45-CG48*0) -> 9.8809263e+09 | CH49: =(CH46-CH47*0)+(CH45-CH48*0) -> 0 | CI49: =(CI46-CI47*0)+(CI45-CI48*0) -> 34843226 | CJ49: =(CJ46-CJ47*0)+(CJ45-CJ48*0) -> 2.2628127e+09 | CK49: =(CK46-CK47*0)+(CK45-CK48*0) -> 3.6038748e+08 | CL49: =(CL46-CL47*0)+(CL45-CL48*0) -> 1.003921e+09 | CM49: =(CM46-CM47*0)+(CM45-CM48*0) -> 1.1865668e+09 | CN49: =(CN46-CN47*0)+(CN45-CN48*0) -> 8.5471176e+08 | CO49: =SUM(CI49:CN49) -> 5.7032429e+09 | CP49: =CG49+CH49+CO49 -> 1.5584169e+10 | CS49: =(CS46-CS47*0)+(CS45-CS48*0) -> 9.8809263e+09 | CT49: =(CT46-CT47*0)+(CT45-CT48*0) -> 0 | CU49: =(CU46-CU47*0)+(CU45-CU48*0) -> 34843226 | CV49: =(CV46-CV47*0)+(CV45-CV48*0) -> 2.2628127e+09 | CW49: =(CW46-CW47*0)+(CW45-CW48*0) -> 3.6038748e+08 | CX49: =(CX46-CX47*0)+(CX45-CX48*0) -> 1.003921e+09 | CY49: =(CY46-CY47*0)+(CY45-CY48*0) -> 1.1865668e+09 | CZ49: =(CZ46-CZ47*0)+(CZ45-CZ48*0) -> 8.5471176e+08 | DA49: =SUM(CU49:CZ49) -> 5.7032429e+09 | DB49: =CS49+CT49+DA49 -> 1.5584169e+10 | DE49: =(DE46-DE47*0)+(DE45-DE48*0) -> 9.8809263e+09 | DF49: =(DF46-DF47*0)+(DF45-DF48*0) -> 0 | DG49: =(DG46-DG47*0)+(DG45-DG48*0) -> 34843226 | DH49: =(DH46-DH47*0)+(DH45-DH48*0) -> 2.2628127e+09 | DI49: =(DI46-DI47*0)+(DI45-DI48*0) -> 3.6038748e+08 | DJ49: =(DJ46-DJ47*0)+(DJ45-DJ48*0) -> 1.003921e+09 | DK49: =(DK46-DK47*0)+(DK45-DK48*0) -> 1.1865668e+09 | DL49: =(DL46-DL47*0)+(DL45-DL48*0) -> 8.5471176e+08 | DM49: =SUM(DG49:DL49) -> 5.7032429e+09 | DN49: =DE49+DF49+DM49 -> 1.5584169e+10 | DQ49: =(DQ46-DQ47*0)+(DQ45-DQ48*0) -> 9.8809263e+09 | DR49: =(DR46-DR47*0)+(DR45-DR48*0) -> 0 | DS49: =(DS46-DS47*0)+(DS45-DS48*0) -> 34843226 | DT49: =(DT46-DT47*0)+(DT45-DT48*0) -> 2.2628127e+09 | DU49: =(DU46-DU47*0)+(DU45-DU48*0) -> 3.6038748e+08 | DV49: =(DV46-DV47*0)+(DV45-DV48*0) -> 1.003921e+09 | DW49: =(DW46-DW47*0)+(DW45-DW48*0) -> 1.1865668e+09 | DX49: =(DX46-DX47*0)+(DX45-DX48*0) -> 8.5471176e+08 | DY49: =SUM(DS49:DX49) -> 5.7032429e+09 | DZ49: =DQ49+DR49+DY49 -> 1.5584169e+10 | EC49: =(EC46-EC47*0)+(EC45-EC48*0) -> 9.8809263e+09 | ED49: =(ED46-ED47*0)+(ED45-ED48*0) -> 0 | EE49: =(EE46-EE47*0)+(EE45-EE48*0) -> 34843226 | EF49: =(EF46-EF47*0)+(EF45-EF48*0) -> 2.2628127e+09 | EG49: =(EG46-EG47*0)+(EG45-EG48*0) -> 3.6038748e+08 | EH49: =(EH46-EH47*0)+(EH45-EH48*0) -> 1.003921e+09 | EI49: =(EI46-EI47*0)+(EI45-EI48*0) -> 1.1865668e+09 | EJ49: =(EJ46-EJ47*0)+(EJ45-EJ48*0) -> 8.5471176e+08 | EK49: =SUM(EE49:EJ49) -> 5.7032429e+09 | EL49: =EC49+ED49+EK49 -> 1.5584169e+10
A51: Chargement de Gestion IBNR et SAP
A52: IBNR ouverture | B52: =B36*1.05-B36 -> 29427190 | C52: =C36*1.05-C36 -> 62382644 | D52: =D36*1.05-D36 -> 590.625 | E52: =E36*1.05-E36 -> 8515063.7 | F52: =F36*1.05-F36 -> 1117289.1 | G52: =G36*1.05-G36 -> 1899093.6 | H52: =H36*1.05-H36 -> 417850.34 | I52: =I36*1.05-I36 -> 6720898.5 | J52: =SUM(D52:I52) -> 18670786 | K52: =B52+C52+J52 -> 1.1048062e+08 | M52: =B52 -> 29427190 | N52: =C52 -> 62382644 | O52: =D52 -> 590.625 | P52: =E52 -> 8515063.7 | Q52: =F52 -> 1117289.1 | R52: =G52 -> 1899093.6 | S52: =H52 -> 417850.34 | T52: =I52 -> 6720898.5 | U52: =SUM(O52:T52) -> 18670786 | V52: =M52+N52+U52 -> 1.1048062e+08 | W52: =V52=K52 -> TRUE | Y52: =M52 -> 29427190 | Z52: =Z36*1.05-Z36 -> 62382644 | AA52: =AA36*1.05-AA36 -> 590.625 | AB52: =AB36*1.05-AB36 -> 8515063.7 | AC52: =AC36*1.05-AC36 -> 1117289.1 | AD52: =AD36*1.05-AD36 -> 1899093.6 | AE52: =AE36*1.05-AE36 -> 417850.34 | AF52: =AF36*1.05-AF36 -> 6720898.5 | AG52: =SUM(AA52:AF52) -> 18670786 | AH52: =Y52+Z52+AG52 -> 1.1048062e+08 | AI52: =AH52=V52 -> TRUE | AK52: =AK36*1.05-AK36 -> 29427190 | AL52: =AL36*1.05-AL36 -> 62382644 | AM52: =AM36*1.05-AM36 -> 590.625 | AN52: =AN36*1.05-AN36 -> 8515063.7 | AO52: =AO36*1.05-AO36 -> 1117289.1 | AP52: =AP36*1.05-AP36 -> 1899093.6 | AQ52: =AQ36*1.05-AQ36 -> 417850.34 | AR52: =AR36*1.05-AR36 -> 6720898.5 | AS52: =SUM(AM52:AR52) -> 18670786 | AT52: =AK52+AL52+AS52 -> 1.1048062e+08 | AU52: =AT52=AH52 -> TRUE | AW52: =AW36*1.05-AW36 -> 29427190 | AX52: =AX36*1.05-AX36 -> 62382644 | AY52: =AY36*1.05-AY36 -> 590.625 | AZ52: =AZ36*1.05-AZ36 -> 8515063.7 | BA52: =BA36*1.05-BA36 -> 1117289.1 | BB52: =BB36*1.05-BB36 -> 1899093.6 | BC52: =BC36*1.05-BC36 -> 417850.34 | BD52: =BD36*1.05-BD36 -> 6720898.5 | BE52: =SUM(AY52:BD52) -> 18670786 | BF52: =AW52+AX52+BE52 -> 1.1048062e+08 | BG52: =BF52=AT52 -> TRUE | BI52: =BI36*1.05-BI36 -> 29427190 | BJ52: =BJ36*1.05-BJ36 -> 62382644 | BK52: =BK36*1.05-BK36 -> 590.625 | BL52: =BL36*1.05-BL36 -> 8515063.7 | BM52: =BM36*1.05-BM36 -> 1117289.1 | BN52: =BN36*1.05-BN36 -> 1899093.6 | BO52: =BO36*1.05-BO36 -> 417850.34 | BP52: =BP36*1.05-BP36 -> 6720898.5 | BQ52: =SUM(BK52:BP52) -> 18670786 | BR52: =BI52+BJ52+BQ52 -> 1.1048062e+08 | BU52: =BU36*1.05-BU36 -> 29427190 | BV52: =BV36*1.05-BV36 -> 62382644 | BW52: =BW36*1.05-BW36 -> 590.625 | BX52: =BX36*1.05-BX36 -> 8515063.7 | BY52: =BY36*1.05-BY36 -> 1117289.1 | BZ52: =BZ36*1.05-BZ36 -> 1899093.6 | CA52: =CA36*1.05-CA36 -> 417850.34 | CB52: =CB36*1.05-CB36 -> 6720898.5 | CC52: =SUM(BW52:CB52) -> 18670786 | CD52: =BU52+BV52+CC52 -> 1.1048062e+08 | CE52: =CD52=BR52 -> TRUE | CG52: =CG36*1.05-CG36 -> 29427190 | CH52: =CH36*1.05-CH36 -> 62382644 | CI52: =CI36*1.05-CI36 -> 590.625 | CJ52: =CJ36*1.05-CJ36 -> 8515063.7 | CK52: =CK36*1.05-CK36 -> 1117289.1 | CL52: =CL36*1.05-CL36 -> 1899093.6 | CM52: =CM36*1.05-CM36 -> 417850.34 | CN52: =CN36*1.05-CN36 -> 6720898.5 | CO52: =SUM(CI52:CN52) -> 18670786 | CP52: =CG52+CH52+CO52 -> 1.1048062e+08 | CS52: =CS36*1.05-CS36 -> 29427190 | CT52: =CT36*1.05-CT36 -> 62382644 | CU52: =CU36*1.05-CU36 -> 590.625 | CV52: =CV36*1.05-CV36 -> 8515063.7 | CW52: =CW36*1.05-CW36 -> 1117289.1 | CX52: =CX36*1.05-CX36 -> 1899093.6 | CY52: =CY36*1.05-CY36 -> 417850.34 | CZ52: =CZ36*1.05-CZ36 -> 6720898.5 | DA52: =SUM(CU52:CZ52) -> 18670786 | DB52: =CS52+CT52+DA52 -> 1.1048062e+08 | DE52: =DE36*1.05-DE36 -> 29427190 | DF52: =DF36*1.05-DF36 -> 62382644 | DG52: =DG36*1.05-DG36 -> 590.625 | DH52: =DH36*1.05-DH36 -> 8515063.7 | DI52: =DI36*1.05-DI36 -> 1117289.1 | DJ52: =DJ36*1.05-DJ36 -> 1899093.6 | DK52: =DK36*1.05-DK36 -> 417850.34 | DL52: =DL36*1.05-DL36 -> 6720898.5 | DM52: =SUM(DG52:DL52) -> 18670786 | DN52: =DE52+DF52+DM52 -> 1.1048062e+08 | DQ52: =DQ36*1.05-DQ36 -> 29427190 | DR52: =DR36*1.05-DR36 -> 62382644 | DS52: =DS36*1.05-DS36 -> 590.625 | DT52: =DT36*1.05-DT36 -> 8515063.7 | DU52: =DU36*1.05-DU36 -> 1117289.1 | DV52: =DV36*1.05-DV36 -> 1899093.6 | DW52: =DW36*1.05-DW36 -> 417850.34 | DX52: =DX36*1.05-DX36 -> 6720898.5 | DY52: =SUM(DS52:DX52) -> 18670786 | DZ52: =DQ52+DR52+DY52 -> 1.1048062e+08 | EC52: =EC36*1.05-EC36 -> 29427190 | ED52: =ED36*1.05-ED36 -> 62382644 | EE52: =EE36*1.05-EE36 -> 590.625 | EF52: =EF36*1.05-EF36 -> 8515063.7 | EG52: =EG36*1.05-EG36 -> 1117289.1 | EH52: =EH36*1.05-EH36 -> 1899093.6 | EI52: =EI36*1.05-EI36 -> 417850.34 | EJ52: =EJ36*1.05-EJ36 -> 6720898.5 | EK52: =SUM(EE52:EJ52) -> 18670786 | EL52: =EC52+ED52+EK52 -> 1.1048062e+08
A53: IBNR cloture | B53: =B37*1.05-B37 -> 29427190 | C53: =C37*1.05-C37 -> 62382644 | D53: =D37*1.05-D37 -> 590.625 | E53: =E37*1.05-E37 -> 8515063.7 | F53: =F37*1.05-F37 -> 1117289.1 | G53: =G37*1.05-G37 -> 1899093.6 | H53: =H37*1.05-H37 -> 417850.34 | I53: =I37*1.05-I37 -> 6720898.5 | J53: =SUM(D53:I53) -> 18670786 | K53: =B53+C53+J53 -> 1.1048062e+08 | M53: =B53 -> 29427190 | N53: =C53 -> 62382644 | O53: =D53 -> 590.625 | P53: =E53 -> 8515063.7 | Q53: =F53 -> 1117289.1 | R53: =G53 -> 1899093.6 | S53: =H53 -> 417850.34 | T53: =I53 -> 6720898.5 | U53: =SUM(O53:T53) -> 18670786 | V53: =M53+N53+U53 -> 1.1048062e+08 | W53: =V53=K53 -> TRUE | Y53: =M53 -> 29427190 | Z53: =N53 -> 62382644 | AA53: =O53 -> 590.625 | AB53: =P53 -> 8515063.7 | AC53: =Q53 -> 1117289.1 | AD53: =R53 -> 1899093.6 | AE53: =S53 -> 417850.34 | AF53: =T53 -> 6720898.5 | AG53: =SUM(AA53:AF53) -> 18670786 | AH53: =Y53+Z53+AG53 -> 1.1048062e+08 | AI53: =AH53=V53 -> TRUE | AK53: =AK37*1.05-AK37 -> 29427190 | AL53: =AL37*1.05-AL37 -> 62382644 | AM53: =AM37*1.05-AM37 -> 590.625 | AN53: =AN37*1.05-AN37 -> 8515063.7 | AO53: =AO37*1.05-AO37 -> 1117289.1 | AP53: =AP37*1.05-AP37 -> 1899093.6 | AQ53: =AQ37*1.05-AQ37 -> 417850.34 | AR53: =AR37*1.05-AR37 -> 6720898.5 | AS53: =SUM(AM53:AR53) -> 18670786 | AT53: =AK53+AL53+AS53 -> 1.1048062e+08 | AU53: =AT53=AH53 -> TRUE | AW53: =AW37*1.05-AW37 -> 29427190 | AX53: =AX37*1.05-AX37 -> 62382644 | AY53: =AY37*1.05-AY37 -> 590.625 | AZ53: =AZ37*1.05-AZ37 -> 8515063.7 | BA53: =BA37*1.05-BA37 -> 1117289.1 | BB53: =BB37*1.05-BB37 -> 1899093.6 | BC53: =BC37*1.05-BC37 -> 417850.34 | BD53: =BD37*1.05-BD37 -> 6720898.5 | BE53: =SUM(AY53:BD53) -> 18670786 | BF53: =AW53+AX53+BE53 -> 1.1048062e+08 | BG53: =BF53=AT53 -> TRUE | BI53: =BI37*1.05-BI37 -> 29427190 | BJ53: =BJ37*1.05-BJ37 -> 62382644 | BK53: =BK37*1.05-BK37 -> 590.625 | BL53: =BL37*1.05-BL37 -> 8515063.7 | BM53: =BM37*1.05-BM37 -> 1117289.1 | BN53: =BN37*1.05-BN37 -> 1899093.6 | BO53: =BO37*1.05-BO37 -> 417850.34 | BP53: =BP37*1.05-BP37 -> 6720898.5 | BQ53: =SUM(BK53:BP53) -> 18670786 | BR53: =BI53+BJ53+BQ53 -> 1.1048062e+08 | BU53: =BU37*1.05-BU37 -> 29427190 | BV53: =BV37*1.05-BV37 -> 62382644 | BW53: =BW37*1.05-BW37 -> 590.625 | BX53: =BX37*1.05-BX37 -> 8515063.7 | BY53: =BY37*1.05-BY37 -> 1117289.1 | BZ53: =BZ37*1.05-BZ37 -> 1899093.6 | CA53: =CA37*1.05-CA37 -> 417850.34 | CB53: =CB37*1.05-CB37 -> 6720898.5 | CC53: =SUM(BW53:CB53) -> 18670786 | CD53: =BU53+BV53+CC53 -> 1.1048062e+08 | CE53: =CD53=BR53 -> TRUE | CG53: =CG37*1.05-CG37 -> 29427190 | CH53: =CH37*1.05-CH37 -> 62382644 | CI53: =CI37*1.05-CI37 -> 590.625 | CJ53: =CJ37*1.05-CJ37 -> 8515063.7 | CK53: =CK37*1.05-CK37 -> 1117289.1 | CL53: =CL37*1.05-CL37 -> 1899093.6 | CM53: =CM37*1.05-CM37 -> 417850.34 | CN53: =CN37*1.05-CN37 -> 6720898.5 | CO53: =SUM(CI53:CN53) -> 18670786 | CP53: =CG53+CH53+CO53 -> 1.1048062e+08 | CS53: =CS37*1.05-CS37 -> 29427190 | CT53: =CT37*1.05-CT37 -> 62382644 | CU53: =CU37*1.05-CU37 -> 590.625 | CV53: =CV37*1.05-CV37 -> 8515063.7 | CW53: =CW37*1.05-CW37 -> 1117289.1 | CX53: =CX37*1.05-CX37 -> 1899093.6 | CY53: =CY37*1.05-CY37 -> 417850.34 | CZ53: =CZ37*1.05-CZ37 -> 6720898.5 | DA53: =SUM(CU53:CZ53) -> 18670786 | DB53: =CS53+CT53+DA53 -> 1.1048062e+08 | DE53: =DE37*1.05-DE37 -> 29427190 | DF53: =DF37*1.05-DF37 -> 62382644 | DG53: =DG37*1.05-DG37 -> 590.625 | DH53: =DH37*1.05-DH37 -> 8515063.7 | DI53: =DI37*1.05-DI37 -> 1117289.1 | DJ53: =DJ37*1.05-DJ37 -> 1899093.6 | DK53: =DK37*1.05-DK37 -> 417850.34 | DL53: =DL37*1.05-DL37 -> 6720898.5 | DM53: =SUM(DG53:DL53) -> 18670786 | DN53: =DE53+DF53+DM53 -> 1.1048062e+08 | DQ53: =DQ37*1.05-DQ37 -> 29427190 | DR53: =DR37*1.05-DR37 -> 62382644 | DS53: =DS37*1.05-DS37 -> 590.625 | DT53: =DT37*1.05-DT37 -> 8515063.7 | DU53: =DU37*1.05-DU37 -> 1117289.1 | DV53: =DV37*1.05-DV37 -> 1899093.6 | DW53: =DW37*1.05-DW37 -> 417850.34 | DX53: =DX37*1.05-DX37 -> 6720898.5 | DY53: =SUM(DS53:DX53) -> 18670786 | DZ53: =DQ53+DR53+DY53 -> 1.1048062e+08 | EC53: =EC37*1.05-EC37 -> 29427190 | ED53: =ED37*1.05-ED37 -> 62382644 | EE53: =EE37*1.05-EE37 -> 590.625 | EF53: =EF37*1.05-EF37 -> 8515063.7 | EG53: =EG37*1.05-EG37 -> 1117289.1 | EH53: =EH37*1.05-EH37 -> 1899093.6 | EI53: =EI37*1.05-EI37 -> 417850.34 | EJ53: =EJ37*1.05-EJ37 -> 6720898.5 | EK53: =SUM(EE53:EJ53) -> 18670786 | EL53: =EC53+ED53+EK53 -> 1.1048062e+08
A54: SAP exercice courant | B54: =B45*0.05 -> 0 | C54: =C45*0.05 -> 0 | D54: =D45*0.05 -> 0 | E54: =E45*0.05 -> 0 | F54: =F45*0.05 -> 0 | G54: =G45*0.05 -> 0 | H54: =H45*0.05 -> 0 | I54: =I45*0.05 -> 0 | J54: =SUM(D54:I54) -> 0 | K54: =B54+C54+J54 -> 0 | M54: =B54 -> 0 | N54: =C54 -> 0 | O54: =D54 -> 0 | P54: =E54 -> 0 | Q54: =F54 -> 0 | R54: =G54 -> 0 | S54: =H54 -> 0 | T54: =I54 -> 0 | U54: =SUM(O54:T54) -> 0 | V54: =M54+N54+U54 -> 0 | W54: =V54=K54 -> TRUE | Y54: =M54 -> 0 | Z54: =N54 -> 0 | AA54: =O54 -> 0 | AB54: =P54 -> 0 | AC54: =Q54 -> 0 | AD54: =R54 -> 0 | AE54: =S54 -> 0 | AF54: =T54 -> 0 | AG54: =SUM(AA54:AF54) -> 0 | AH54: =Y54+Z54+AG54 -> 0 | AI54: =AH54=V54 -> TRUE | AK54: =AK45*0.05 -> 0 | AL54: =AL45*0.05 -> 0 | AM54: =AM45*0.05 -> 0 | AN54: =AN45*0.05 -> 0 | AO54: =AO45*0.05 -> 0 | AP54: =AP45*0.05 -> 0 | AQ54: =AQ45*0.05 -> 0 | AR54: =AR45*0.05 -> 0 | AS54: =SUM(AM54:AR54) -> 0 | AT54: =AK54+AL54+AS54 -> 0 | AU54: =AT54=AH54 -> TRUE | AW54: =AW45*0.05 -> 0 | AX54: =AX45*0.05 -> 0 | AY54: =AY45*0.05 -> 0 | AZ54: =AZ45*0.05 -> 0 | BA54: =BA45*0.05 -> 0 | BB54: =BB45*0.05 -> 0 | BC54: =BC45*0.05 -> 0 | BD54: =BD45*0.05 -> 0 | BE54: =SUM(AY54:BD54) -> 0 | BF54: =AW54+AX54+BE54 -> 0 | BG54: =BF54=AT54 -> TRUE | BI54: =BI45*0.05 -> 0 | BJ54: =BJ45*0.05 -> 0 | BK54: =BK45*0.05 -> 0 | BL54: =BL45*0.05 -> 0 | BM54: =BM45*0.05 -> 0 | BN54: =BN45*0.05 -> 0 | BO54: =BO45*0.05 -> 0 | BP54: =BP45*0.05 -> 0 | BQ54: =SUM(BK54:BP54) -> 0 | BR54: =BI54+BJ54+BQ54 -> 0 | BU54: =BU45*0.05 -> 0 | BV54: =BV45*0.05 -> 0 | BW54: =BW45*0.05 -> 0 | BX54: =BX45*0.05 -> 0 | BY54: =BY45*0.05 -> 0 | BZ54: =BZ45*0.05 -> 0 | CA54: =CA45*0.05 -> 0 | CB54: =CB45*0.05 -> 0 | CC54: =SUM(BW54:CB54) -> 0 | CD54: =BU54+BV54+CC54 -> 0 | CE54: =CD54=BR54 -> TRUE | CG54: =CG45*0.05 -> 0 | CH54: =CH45*0.05 -> 0 | CI54: =CI45*0.05 -> 0 | CJ54: =CJ45*0.05 -> 0 | CK54: =CK45*0.05 -> 0 | CL54: =CL45*0.05 -> 0 | CM54: =CM45*0.05 -> 0 | CN54: =CN45*0.05 -> 0 | CO54: =SUM(CI54:CN54) -> 0 | CP54: =CG54+CH54+CO54 -> 0 | CS54: =CS45*0.05 -> 0 | CT54: =CT45*0.05 -> 0 | CU54: =CU45*0.05 -> 0 | CV54: =CV45*0.05 -> 0 | CW54: =CW45*0.05 -> 0 | CX54: =CX45*0.05 -> 0 | CY54: =CY45*0.05 -> 0 | CZ54: =CZ45*0.05 -> 0 | DA54: =SUM(CU54:CZ54) -> 0 | DB54: =CS54+CT54+DA54 -> 0 | DE54: =DE45*0.05 -> 0 | DF54: =DF45*0.05 -> 0 | DG54: =DG45*0.05 -> 0 | DH54: =DH45*0.05 -> 0 | DI54: =DI45*0.05 -> 0 | DJ54: =DJ45*0.05 -> 0 | DK54: =DK45*0.05 -> 0 | DL54: =DL45*0.05 -> 0 | DM54: =SUM(DG54:DL54) -> 0 | DN54: =DE54+DF54+DM54 -> 0 | DQ54: =DQ45*0.05 -> 0 | DR54: =DR45*0.05 -> 0 | DS54: =DS45*0.05 -> 0 | DT54: =DT45*0.05 -> 0 | DU54: =DU45*0.05 -> 0 | DV54: =DV45*0.05 -> 0 | DW54: =DW45*0.05 -> 0 | DX54: =DX45*0.05 -> 0 | DY54: =SUM(DS54:DX54) -> 0 | DZ54: =DQ54+DR54+DY54 -> 0 | EC54: =EC45*0.05 -> 0 | ED54: =ED45*0.05 -> 0 | EE54: =EE45*0.05 -> 0 | EF54: =EF45*0.05 -> 0 | EG54: =EG45*0.05 -> 0 | EH54: =EH45*0.05 -> 0 | EI54: =EI45*0.05 -> 0 | EJ54: =EJ45*0.05 -> 0 | EK54: =SUM(EE54:EJ54) -> 0 | EL54: =EC54+ED54+EK54 -> 0
A55: SAP exercices antérieurs | B55: =B46*0.05 -> 4.9404631e+08 | C55: =C46*0.05 -> 0 | D55: =D46*0.05 -> 1742161.3 | E55: =E46*0.05 -> 1.1314063e+08 | F55: =F46*0.05 -> 18019374 | G55: =G46*0.05 -> 50196049 | H55: =H46*0.05 -> 59328339 | I55: =I46*0.05 -> 42735588 | J55: =SUM(D55:I55) -> 2.8516215e+08 | K55: =B55+C55+J55 -> 7.7920846e+08 | M55: =B55 -> 4.9404631e+08 | N55: =C55 -> 0 | O55: =D55 -> 1742161.3 | P55: =E55 -> 1.1314063e+08 | Q55: =F55 -> 18019374 | R55: =G55 -> 50196049 | S55: =H55 -> 59328339 | T55: =I55 -> 42735588 | U55: =SUM(O55:T55) -> 2.8516215e+08 | V55: =M55+N55+U55 -> 7.7920846e+08 | W55: =V55=K55 -> TRUE | Y55: =M55 -> 4.9404631e+08 | Z55: =N55 -> 0 | AA55: =O55 -> 1742161.3 | AB55: =P55 -> 1.1314063e+08 | AC55: =Q55 -> 18019374 | AD55: =R55 -> 50196049 | AE55: =S55 -> 59328339 | AF55: =T55 -> 42735588 | AG55: =SUM(AA55:AF55) -> 2.8516215e+08 | AH55: =Y55+Z55+AG55 -> 7.7920846e+08 | AI55: =AH55=V55 -> TRUE | AK55: =AK46*0.05 -> 4.9404631e+08 | AL55: =AL46*0.05 -> 0 | AM55: =AM46*0.05 -> 1742161.3 | AN55: =AN46*0.05 -> 1.1314063e+08 | AO55: =AO46*0.05 -> 18019374 | AP55: =AP46*0.05 -> 50196049 | AQ55: =AQ46*0.05 -> 59328339 | AR55: =AR46*0.05 -> 42735588 | AS55: =SUM(AM55:AR55) -> 2.8516215e+08 | AT55: =AK55+AL55+AS55 -> 7.7920846e+08 | AU55: =AT55=AH55 -> TRUE | AW55: =AW46*0.05 -> 4.9404631e+08 | AX55: =AX46*0.05 -> 0 | AY55: =AY46*0.05 -> 1742161.3 | AZ55: =AZ46*0.05 -> 1.1314063e+08 | BA55: =BA46*0.05 -> 18019374 | BB55: =BB46*0.05 -> 50196049 | BC55: =BC46*0.05 -> 59328339 | BD55: =BD46*0.05 -> 42735588 | BE55: =SUM(AY55:BD55) -> 2.8516215e+08 | BF55: =AW55+AX55+BE55 -> 7.7920846e+08 | BG55: =BF55=AT55 -> TRUE | BI55: =BI46*0.05 -> 4.9404631e+08 | BJ55: =BJ46*0.05 -> 0 | BK55: =BK46*0.05 -> 1742161.3 | BL55: =BL46*0.05 -> 1.1314063e+08 | BM55: =BM46*0.05 -> 18019374 | BN55: =BN46*0.05 -> 50196049 | BO55: =BO46*0.05 -> 59328339 | BP55: =BP46*0.05 -> 42735588 | BQ55: =SUM(BK55:BP55) -> 2.8516215e+08 | BR55: =BI55+BJ55+BQ55 -> 7.7920846e+08 | BU55: =BU46*0.05 -> 4.9404631e+08 | BV55: =BV46*0.05 -> 0 | BW55: =BW46*0.05 -> 1742161.3 | BX55: =BX46*0.05 -> 1.1314063e+08 | BY55: =BY46*0.05 -> 18019374 | BZ55: =BZ46*0.05 -> 50196049 | CA55: =CA46*0.05 -> 59328339 | CB55: =CB46*0.05 -> 42735588 | CC55: =SUM(BW55:CB55) -> 2.8516215e+08 | CD55: =BU55+BV55+CC55 -> 7.7920846e+08 | CE55: =CD55=BR55 -> TRUE | CG55: =CG46*0.05 -> 4.9404631e+08 | CH55: =CH46*0.05 -> 0 | CI55: =CI46*0.05 -> 1742161.3 | CJ55: =CJ46*0.05 -> 1.1314063e+08 | CK55: =CK46*0.05 -> 18019374 | CL55: =CL46*0.05 -> 50196049 | CM55: =CM46*0.05 -> 59328339 | CN55: =CN46*0.05 -> 42735588 | CO55: =SUM(CI55:CN55) -> 2.8516215e+08 | CP55: =CG55+CH55+CO55 -> 7.7920846e+08 | CS55: =CS46*0.05 -> 4.9404631e+08 | CT55: =CT46*0.05 -> 0 | CU55: =CU46*0.05 -> 1742161.3 | CV55: =CV46*0.05 -> 1.1314063e+08 | CW55: =CW46*0.05 -> 18019374 | CX55: =CX46*0.05 -> 50196049 | CY55: =CY46*0.05 -> 59328339 | CZ55: =CZ46*0.05 -> 42735588 | DA55: =SUM(CU55:CZ55) -> 2.8516215e+08 | DB55: =CS55+CT55+DA55 -> 7.7920846e+08 | DE55: =DE46*0.05 -> 4.9404631e+08 | DF55: =DF46*0.05 -> 0 | DG55: =DG46*0.05 -> 1742161.3 | DH55: =DH46*0.05 -> 1.1314063e+08 | DI55: =DI46*0.05 -> 18019374 | DJ55: =DJ46*0.05 -> 50196049 | DK55: =DK46*0.05 -> 59328339 | DL55: =DL46*0.05 -> 42735588 | DM55: =SUM(DG55:DL55) -> 2.8516215e+08 | DN55: =DE55+DF55+DM55 -> 7.7920846e+08 | DQ55: =DQ46*0.05 -> 4.9404631e+08 | DR55: =DR46*0.05 -> 0 | DS55: =DS46*0.05 -> 1742161.3 | DT55: =DT46*0.05 -> 1.1314063e+08 | DU55: =DU46*0.05 -> 18019374 | DV55: =DV46*0.05 -> 50196049 | DW55: =DW46*0.05 -> 59328339 | DX55: =DX46*0.05 -> 42735588 | DY55: =SUM(DS55:DX55) -> 2.8516215e+08 | DZ55: =DQ55+DR55+DY55 -> 7.7920846e+08 | EC55: =EC46*0.05 -> 4.9404631e+08 | ED55: =ED46*0.05 -> 0 | EE55: =EE46*0.05 -> 1742161.3 | EF55: =EF46*0.05 -> 1.1314063e+08 | EG55: =EG46*0.05 -> 18019374 | EH55: =EH46*0.05 -> 50196049 | EI55: =EI46*0.05 -> 59328339 | EJ55: =EJ46*0.05 -> 42735588 | EK55: =SUM(EE55:EJ55) -> 2.8516215e+08 | EL55: =EC55+ED55+EK55 -> 7.7920846e+08
A57: IBNR BE
A58: Ouverture | J58: =SUM(D58:I58) -> 0 | K58: =B58+C58+J58 -> 0 | U58: =SUM(O58:T58) -> 0 | V58: =M58+N58+U58 -> 0 | AG58: =SUM(AA58:AF58) -> 0 | AH58: =Y58+Z58+AG58 -> 0 | AS58: =SUM(AM58:AR58) -> 0 | AT58: =AK58+AL58+AS58 -> 0 | BE58: =SUM(AY58:BD58) -> 0 | BF58: =AW58+AX58+BE58 -> 0 | BQ58: =SUM(BK58:BP58) -> 0 | BR58: =BI58+BJ58+BQ58 -> 0 | CC58: =SUM(BW58:CB58) -> 0 | CD58: =BU58+BV58+CC58 -> 0 | CO58: =SUM(CI58:CN58) -> 0 | CP58: =CG58+CH58+CO58 -> 0 | DA58: =SUM(CU58:CZ58) -> 0 | DB58: =CS58+CT58+DA58 -> 0 | DM58: =SUM(DG58:DL58) -> 0 | DN58: =DE58+DF58+DM58 -> 0 | DY58: =SUM(DS58:DX58) -> 0 | DZ58: =DQ58+DR58+DY58 -> 0 | EK58: =SUM(EE58:EJ58) -> 0 | EL58: =EC58+ED58+EK58 -> 0
A59: Clôture Per. | B59: =B41 -> 0 | C59: =C41 -> 0 | D59: =D41 -> 0 | E59: =E41 -> 0 | F59: =F41 -> 0 | G59: =G41 -> 0 | H59: =H41 -> 0 | I59: =I41 -> 0 | J59: =SUM(D59:I59) -> 0 | K59: =B59+C59+J59 -> 0 | M59: =M41 -> 0 | N59: =N41 -> 0 | O59: =O41 -> 0 | P59: =P41 -> 0 | Q59: =Q41 -> 0 | R59: =R41 -> 0 | S59: =S41 -> 0 | T59: =T41 -> 0 | U59: =SUM(O59:T59) -> 0 | V59: =M59+N59+U59 -> 0 | Y59: =Y41 -> 0 | Z59: =Z41 -> 0 | AA59: =AA41 -> 0 | AB59: =AB41 -> 0 | AC59: =AC41 -> 0 | AD59: =AD41 -> 0 | AE59: =AE41 -> 0 | AF59: =AF41 -> 0 | AG59: =SUM(AA59:AF59) -> 0 | AH59: =Y59+Z59+AG59 -> 0 | AK59: =AK41 -> 0 | AL59: =AL41 -> 0 | AM59: =AM41 -> 0 | AN59: =AN41 -> 0 | AO59: =AO41 -> 0 | AP59: =AP41 -> 0 | AQ59: =AQ41 -> 0 | AR59: =AR41 -> 0 | AS59: =SUM(AM59:AR59) -> 0 | AT59: =AK59+AL59+AS59 -> 0 | AW59: =AW41 -> 0 | AX59: =AX41 -> 0 | AY59: =AY41 -> 0 | AZ59: =AZ41 -> 0 | BA59: =BA41 -> 0 | BB59: =BB41 -> 0 | BC59: =BC41 -> 0 | BD59: =BD41 -> 0 | BE59: =SUM(AY59:BD59) -> 0 | BF59: =AW59+AX59+BE59 -> 0 | BI59: =BI41 -> 0 | BJ59: =BJ41 -> 0 | BK59: =BK41 -> 0 | BL59: =BL41 -> 0 | BM59: =BM41 -> 0 | BN59: =BN41 -> 0 | BO59: =BO41 -> 0 | BP59: =BP41 -> 0 | BQ59: =SUM(BK59:BP59) -> 0 | BR59: =BI59+BJ59+BQ59 -> 0 | BU59: =BU41 -> 0 | BV59: =BV41 -> 0 | BW59: =BW41 -> 0 | BX59: =BX41 -> 0 | BY59: =BY41 -> 0 | BZ59: =BZ41 -> 0 | CA59: =CA41 -> 0 | CB59: =CB41 -> 0 | CC59: =SUM(BW59:CB59) -> 0 | CD59: =BU59+BV59+CC59 -> 0 | CG59: =CG41 -> 0 | CH59: =CH41 -> 0 | CI59: =CI41 -> 0 | CJ59: =CJ41 -> 0 | CK59: =CK41 -> 0 | CL59: =CL41 -> 0 | CM59: =CM41 -> 0 | CN59: =CN41 -> 0 | CO59: =SUM(CI59:CN59) -> 0 | CP59: =CG59+CH59+CO59 -> 0 | CS59: =CS41 -> 0 | CT59: =CT41 -> 0 | CU59: =CU41 -> 0 | CV59: =CV41 -> 0 | CW59: =CW41 -> 0 | CX59: =CX41 -> 0 | CY59: =CY41 -> 0 | CZ59: =CZ41 -> 0 | DA59: =SUM(CU59:CZ59) -> 0 | DB59: =CS59+CT59+DA59 -> 0 | DE59: =DE41 -> 0 | DF59: =DF41 -> 0 | DG59: =DG41 -> 0 | DH59: =DH41 -> 0 | DI59: =DI41 -> 0 | DJ59: =DJ41 -> 0 | DK59: =DK41 -> 0 | DL59: =DL41 -> 0 | DM59: =SUM(DG59:DL59) -> 0 | DN59: =DE59+DF59+DM59 -> 0 | DQ59: =DQ41 -> 0 | DR59: =DR41 -> 0 | DS59: =DS41 -> 0 | DT59: =DT41 -> 0 | DU59: =DU41 -> 0 | DV59: =DV41 -> 0 | DW59: =DW41 -> 0 | DX59: =DX41 -> 0 | DY59: =SUM(DS59:DX59) -> 0 | DZ59: =DQ59+DR59+DY59 -> 0 | EC59: =EC41 -> 0 | ED59: =ED41 -> 0 | EE59: =EE41 -> 0 | EF59: =EF41 -> 0 | EG59: =EG41 -> 0 | EH59: =EH41 -> 0 | EI59: =EI41 -> 0 | EJ59: =EJ41 -> 0 | EK59: =SUM(EE59:EJ59) -> 0 | EL59: =EC59+ED59+EK59 -> 0
A60: Clôture Ant. | B60: =B42 -> 0 | C60: =C42 -> 0 | D60: =D42 -> 0 | E60: =E42 -> 0 | F60: =F42 -> 0 | G60: =G42 -> 0 | H60: =H42 -> 0 | I60: =I42 -> 0 | J60: =SUM(D60:I60) -> 0 | K60: =B60+C60+J60 -> 0 | M60: =M42 -> 0 | N60: =N42 -> 0 | O60: =O42 -> 0 | P60: =P42 -> 0 | Q60: =Q42 -> 0 | R60: =R42 -> 0 | S60: =S42 -> 0 | T60: =T42 -> 0 | U60: =SUM(O60:T60) -> 0 | V60: =M60+N60+U60 -> 0 | Y60: =Y42 -> 0 | Z60: =Z42 -> 0 | AA60: =AA42 -> 0 | AB60: =AB42 -> 0 | AC60: =AC42 -> 0 | AD60: =AD42 -> 0 | AE60: =AE42 -> 0 | AF60: =AF42 -> 0 | AG60: =SUM(AA60:AF60) -> 0 | AH60: =Y60+Z60+AG60 -> 0 | AK60: =AK42 -> 0 | AL60: =AL42 -> 0 | AM60: =AM42 -> 0 | AN60: =AN42 -> 0 | AO60: =AO42 -> 0 | AP60: =AP42 -> 0 | AQ60: =AQ42 -> 0 | AR60: =AR42 -> 0 | AS60: =SUM(AM60:AR60) -> 0 | AT60: =AK60+AL60+AS60 -> 0 | AW60: =AW42 -> 0 | AX60: =AX42 -> 0 | AY60: =AY42 -> 0 | AZ60: =AZ42 -> 0 | BA60: =BA42 -> 0 | BB60: =BB42 -> 0 | BC60: =BC42 -> 0 | BD60: =BD42 -> 0 | BE60: =SUM(AY60:BD60) -> 0 | BF60: =AW60+AX60+BE60 -> 0 | BI60: =BI42 -> 0 | BJ60: =BJ42 -> 0 | BK60: =BK42 -> 0 | BL60: =BL42 -> 0 | BM60: =BM42 -> 0 | BN60: =BN42 -> 0 | BO60: =BO42 -> 0 | BP60: =BP42 -> 0 | BQ60: =SUM(BK60:BP60) -> 0 | BR60: =BI60+BJ60+BQ60 -> 0 | BU60: =BU42 -> 0 | BV60: =BV42 -> 0 | BW60: =BW42 -> 0 | BX60: =BX42 -> 0 | BY60: =BY42 -> 0 | BZ60: =BZ42 -> 0 | CA60: =CA42 -> 0 | CB60: =CB42 -> 0 | CC60: =SUM(BW60:CB60) -> 0 | CD60: =BU60+BV60+CC60 -> 0 | CG60: =CG42 -> 0 | CH60: =CH42 -> 0 | CI60: =CI42 -> 0 | CJ60: =CJ42 -> 0 | CK60: =CK42 -> 0 | CL60: =CL42 -> 0 | CM60: =CM42 -> 0 | CN60: =CN42 -> 0 | CO60: =SUM(CI60:CN60) -> 0 | CP60: =CG60+CH60+CO60 -> 0 | CS60: =CS42 -> 0 | CT60: =CT42 -> 0 | CU60: =CU42 -> 0 | CV60: =CV42 -> 0 | CW60: =CW42 -> 0 | CX60: =CX42 -> 0 | CY60: =CY42 -> 0 | CZ60: =CZ42 -> 0 | DA60: =SUM(CU60:CZ60) -> 0 | DB60: =CS60+CT60+DA60 -> 0 | DE60: =DE42 -> 0 | DF60: =DF42 -> 0 | DG60: =DG42 -> 0 | DH60: =DH42 -> 0 | DI60: =DI42 -> 0 | DJ60: =DJ42 -> 0 | DK60: =DK42 -> 0 | DL60: =DL42 -> 0 | DM60: =SUM(DG60:DL60) -> 0 | DN60: =DE60+DF60+DM60 -> 0 | DQ60: =DQ42 -> 0 | DR60: =DR42 -> 0 | DS60: =DS42 -> 0 | DT60: =DT42 -> 0 | DU60: =DU42 -> 0 | DV60: =DV42 -> 0 | DW60: =DW42 -> 0 | DX60: =DX42 -> 0 | DY60: =SUM(DS60:DX60) -> 0 | DZ60: =DQ60+DR60+DY60 -> 0 | EC60: =EC42 -> 0 | ED60: =ED42 -> 0 | EE60: =EE42 -> 0 | EF60: =EF42 -> 0 | EG60: =EG42 -> 0 | EH60: =EH42 -> 0 | EI60: =EI42 -> 0 | EJ60: =EJ42 -> 0 | EK60: =SUM(EE60:EJ60) -> 0 | EL60: =EC60+ED60+EK60 -> 0
A61: Variation Per. | B61: =B59 -> 0 | C61: =C59 -> 0 | D61: =D59 -> 0 | E61: =E59 -> 0 | F61: =F59 -> 0 | G61: =G59 -> 0 | H61: =H59 -> 0 | I61: =I59 -> 0 | J61: =SUM(D61:I61) -> 0 | K61: =B61+C61+J61 -> 0 | M61: =M59 -> 0 | N61: =N59 -> 0 | O61: =O59 -> 0 | P61: =P59 -> 0 | Q61: =Q59 -> 0 | R61: =R59 -> 0 | S61: =S59 -> 0 | T61: =T59 -> 0 | U61: =SUM(O61:T61) -> 0 | V61: =M61+N61+U61 -> 0 | Y61: =Y59 -> 0 | Z61: =Z59 -> 0 | AA61: =AA59 -> 0 | AB61: =AB59 -> 0 | AC61: =AC59 -> 0 | AD61: =AD59 -> 0 | AE61: =AE59 -> 0 | AF61: =AF59 -> 0 | AG61: =SUM(AA61:AF61) -> 0 | AH61: =Y61+Z61+AG61 -> 0 | AK61: =AK59 -> 0 | AL61: =AL59 -> 0 | AM61: =AM59 -> 0 | AN61: =AN59 -> 0 | AO61: =AO59 -> 0 | AP61: =AP59 -> 0 | AQ61: =AQ59 -> 0 | AR61: =AR59 -> 0 | AS61: =SUM(AM61:AR61) -> 0 | AT61: =AK61+AL61+AS61 -> 0 | AW61: =AW59 -> 0 | AX61: =AX59 -> 0 | AY61: =AY59 -> 0 | AZ61: =AZ59 -> 0 | BA61: =BA59 -> 0 | BB61: =BB59 -> 0 | BC61: =BC59 -> 0 | BD61: =BD59 -> 0 | BE61: =SUM(AY61:BD61) -> 0 | BF61: =AW61+AX61+BE61 -> 0 | BI61: =BI59 -> 0 | BJ61: =BJ59 -> 0 | BK61: =BK59 -> 0 | BL61: =BL59 -> 0 | BM61: =BM59 -> 0 | BN61: =BN59 -> 0 | BO61: =BO59 -> 0 | BP61: =BP59 -> 0 | BQ61: =SUM(BK61:BP61) -> 0 | BR61: =BI61+BJ61+BQ61 -> 0 | BU61: =BU59 -> 0 | BV61: =BV59 -> 0 | BW61: =BW59 -> 0 | BX61: =BX59 -> 0 | BY61: =BY59 -> 0 | BZ61: =BZ59 -> 0 | CA61: =CA59 -> 0 | CB61: =CB59 -> 0 | CC61: =SUM(BW61:CB61) -> 0 | CD61: =BU61+BV61+CC61 -> 0 | CG61: =CG59 -> 0 | CH61: =CH59 -> 0 | CI61: =CI59 -> 0 | CJ61: =CJ59 -> 0 | CK61: =CK59 -> 0 | CL61: =CL59 -> 0 | CM61: =CM59 -> 0 | CN61: =CN59 -> 0 | CO61: =SUM(CI61:CN61) -> 0 | CP61: =CG61+CH61+CO61 -> 0 | CS61: =CS59 -> 0 | CT61: =CT59 -> 0 | CU61: =CU59 -> 0 | CV61: =CV59 -> 0 | CW61: =CW59 -> 0 | CX61: =CX59 -> 0 | CY61: =CY59 -> 0 | CZ61: =CZ59 -> 0 | DA61: =SUM(CU61:CZ61) -> 0 | DB61: =CS61+CT61+DA61 -> 0 | DE61: =DE59 -> 0 | DF61: =DF59 -> 0 | DG61: =DG59 -> 0 | DH61: =DH59 -> 0 | DI61: =DI59 -> 0 | DJ61: =DJ59 -> 0 | DK61: =DK59 -> 0 | DL61: =DL59 -> 0 | DM61: =SUM(DG61:DL61) -> 0 | DN61: =DE61+DF61+DM61 -> 0 | DQ61: =DQ59 -> 0 | DR61: =DR59 -> 0 | DS61: =DS59 -> 0 | DT61: =DT59 -> 0 | DU61: =DU59 -> 0 | DV61: =DV59 -> 0 | DW61: =DW59 -> 0 | DX61: =DX59 -> 0 | DY61: =SUM(DS61:DX61) -> 0 | DZ61: =DQ61+DR61+DY61 -> 0 | EC61: =EC59 -> 0 | ED61: =ED59 -> 0 | EE61: =EE59 -> 0 | EF61: =EF59 -> 0 | EG61: =EG59 -> 0 | EH61: =EH59 -> 0 | EI61: =EI59 -> 0 | EJ61: =EJ59 -> 0 | EK61: =SUM(EE61:EJ61) -> 0 | EL61: =EC61+ED61+EK61 -> 0
A62: Variation Ant. | B62: =B60-B58 -> 0 | C62: =C60-C58 -> 0 | D62: =D60-D58 -> 0 | E62: =E60-E58 -> 0 | F62: =F60-F58 -> 0 | G62: =G60-G58 -> 0 | H62: =H60-H58 -> 0 | I62: =I60-I58 -> 0 | J62: =SUM(D62:I62) -> 0 | K62: =B62+C62+J62 -> 0 | M62: =M60-M58 -> 0 | N62: =N60-N58 -> 0 | O62: =O60-O58 -> 0 | P62: =P60-P58 -> 0 | Q62: =Q60-Q58 -> 0 | R62: =R60-R58 -> 0 | S62: =S60-S58 -> 0 | T62: =T60-T58 -> 0 | U62: =SUM(O62:T62) -> 0 | V62: =M62+N62+U62 -> 0 | Y62: =Y60-Y58 -> 0 | Z62: =Z60-Z58 -> 0 | AA62: =AA60-AA58 -> 0 | AB62: =AB60-AB58 -> 0 | AC62: =AC60-AC58 -> 0 | AD62: =AD60-AD58 -> 0 | AE62: =AE60-AE58 -> 0 | AF62: =AF60-AF58 -> 0 | AG62: =SUM(AA62:AF62) -> 0 | AH62: =Y62+Z62+AG62 -> 0 | AK62: =AK60-AK58 -> 0 | AL62: =AL60-AL58 -> 0 | AM62: =AM60-AM58 -> 0 | AN62: =AN60-AN58 -> 0 | AO62: =AO60-AO58 -> 0 | AP62: =AP60-AP58 -> 0 | AQ62: =AQ60-AQ58 -> 0 | AR62: =AR60-AR58 -> 0 | AS62: =SUM(AM62:AR62) -> 0 | AT62: =AK62+AL62+AS62 -> 0 | AW62: =AW60-AW58 -> 0 | AX62: =AX60-AX58 -> 0 | AY62: =AY60-AY58 -> 0 | AZ62: =AZ60-AZ58 -> 0 | BA62: =BA60-BA58 -> 0 | BB62: =BB60-BB58 -> 0 | BC62: =BC60-BC58 -> 0 | BD62: =BD60-BD58 -> 0 | BE62: =SUM(AY62:BD62) -> 0 | BF62: =AW62+AX62+BE62 -> 0 | BI62: =BI60-BI58 -> 0 | BJ62: =BJ60-BJ58 -> 0 | BK62: =BK60-BK58 -> 0 | BL62: =BL60-BL58 -> 0 | BM62: =BM60-BM58 -> 0 | BN62: =BN60-BN58 -> 0 | BO62: =BO60-BO58 -> 0 | BP62: =BP60-BP58 -> 0 | BQ62: =SUM(BK62:BP62) -> 0 | BR62: =BI62+BJ62+BQ62 -> 0 | BU62: =BU60-BU58 -> 0 | BV62: =BV60-BV58 -> 0 | BW62: =BW60-BW58 -> 0 | BX62: =BX60-BX58 -> 0 | BY62: =BY60-BY58 -> 0 | BZ62: =BZ60-BZ58 -> 0 | CA62: =CA60-CA58 -> 0 | CB62: =CB60-CB58 -> 0 | CC62: =SUM(BW62:CB62) -> 0 | CD62: =BU62+BV62+CC62 -> 0 | CG62: =CG60-CG58 -> 0 | CH62: =CH60-CH58 -> 0 | CI62: =CI60-CI58 -> 0 | CJ62: =CJ60-CJ58 -> 0 | CK62: =CK60-CK58 -> 0 | CL62: =CL60-CL58 -> 0 | CM62: =CM60-CM58 -> 0 | CN62: =CN60-CN58 -> 0 | CO62: =SUM(CI62:CN62) -> 0 | CP62: =CG62+CH62+CO62 -> 0 | CS62: =CS60-CS58 -> 0 | CT62: =CT60-CT58 -> 0 | CU62: =CU60-CU58 -> 0 | CV62: =CV60-CV58 -> 0 | CW62: =CW60-CW58 -> 0 | CX62: =CX60-CX58 -> 0 | CY62: =CY60-CY58 -> 0 | CZ62: =CZ60-CZ58 -> 0 | DA62: =SUM(CU62:CZ62) -> 0 | DB62: =CS62+CT62+DA62 -> 0 | DE62: =DE60-DE58 -> 0 | DF62: =DF60-DF58 -> 0 | DG62: =DG60-DG58 -> 0 | DH62: =DH60-DH58 -> 0 | DI62: =DI60-DI58 -> 0 | DJ62: =DJ60-DJ58 -> 0 | DK62: =DK60-DK58 -> 0 | DL62: =DL60-DL58 -> 0 | DM62: =SUM(DG62:DL62) -> 0 | DN62: =DE62+DF62+DM62 -> 0 | DQ62: =DQ60-DQ58 -> 0 | DR62: =DR60-DR58 -> 0 | DS62: =DS60-DS58 -> 0 | DT62: =DT60-DT58 -> 0 | DU62: =DU60-DU58 -> 0 | DV62: =DV60-DV58 -> 0 | DW62: =DW60-DW58 -> 0 | DX62: =DX60-DX58 -> 0 | DY62: =SUM(DS62:DX62) -> 0 | DZ62: =DQ62+DR62+DY62 -> 0 | EC62: =EC60-EC58 -> 0 | ED62: =ED60-ED58 -> 0 | EE62: =EE60-EE58 -> 0 | EF62: =EF60-EF58 -> 0 | EG62: =EG60-EG58 -> 0 | EH62: =EH60-EH58 -> 0 | EI62: =EI60-EI58 -> 0 | EJ62: =EJ60-EJ58 -> 0 | EK62: =SUM(EE62:EJ62) -> 0 | EL62: =EC62+ED62+EK62 -> 0
A64: SAP hors chargement
A65: Ouverture | B65: 9.8809263e+09 | C65: 0 | D65: 34843226 | E65: 2.2628127e+09 | F65: 3.6038748e+08 | G65: 1.003921e+09 | H65: 1.1865668e+09 | I65: 8.5471176e+08 | J65: =SUM(D65:I65) -> 5.7032429e+09 | K65: =B65+C65+J65 -> 1.5584169e+10 | L65: ok | M65: =B65 -> 9.8809263e+09 | N65: =C65 -> 0 | O65: =D65 -> 34843226 | P65: =E65 -> 2.2628127e+09 | Q65: =F65 -> 3.6038748e+08 | R65: =G65 -> 1.003921e+09 | S65: =H65 -> 1.1865668e+09 | T65: =I65 -> 8.5471176e+08 | U65: =SUM(O65:T65) -> 5.7032429e+09 | V65: =M65+N65+U65 -> 1.5584169e+10 | W65: =V65=K65 -> TRUE | Y65: =M65 -> 9.8809263e+09 | Z65: =N65 -> 0 | AA65: =O65 -> 34843226 | AB65: =P65 -> 2.2628127e+09 | AC65: =Q65 -> 3.6038748e+08 | AD65: =R65 -> 1.003921e+09 | AE65: =S65 -> 1.1865668e+09 | AF65: =T65 -> 8.5471176e+08 | AG65: =SUM(AA65:AF65) -> 5.7032429e+09 | AH65: =AG65+Y65+Z65 -> 1.5584169e+10 | AI65: =AH65=V65 -> TRUE | AK65: =Y65*AK148 -> 9.8809263e+09 | AL65: =Z65*AL148 -> 0 | AM65: =AA65*AM148 -> 34843226 | AN65: =AB65*AN148 -> 2.2628127e+09 | AO65: =AC65*AO148 -> 3.6038748e+08 | AP65: =AD65*AP148 -> 1.003921e+09 | AQ65: =AE65*AQ148 -> 1.1865668e+09 | AR65: =AF65*AR148 -> 8.5471176e+08 | AS65: =SUM(AM65:AR65) -> 5.7032429e+09 | AT65: =AK65+AL65+AS65 -> 1.5584169e+10 | AU65: =AT65=AH65 -> TRUE | AW65: =AK65*AW148 -> 9.8809263e+09 | AX65: =AL65*AX148 -> 0 | AY65: =AM65*AY148 -> 34843226 | AZ65: =AN65*AZ148 -> 2.2628127e+09 | BA65: =AO65*BA148 -> 3.6038748e+08 | BB65: =AP65*BB148 -> 1.003921e+09 | BC65: =AQ65*BC148 -> 1.1865668e+09 | BD65: =AR65*BD148 -> 8.5471176e+08 | BE65: =SUM(AY65:BD65) -> 5.7032429e+09 | BF65: =AW65+AX65+BE65 -> 1.5584169e+10 | BG65: =BF65=AT65 -> TRUE | BI65: =AW65*BI148 -> 9.8809263e+09 | BJ65: =AX65*BJ148 -> 0 | BK65: =AY65*BK148 -> 34843226 | BL65: =AZ65*BL148 -> 2.2628127e+09 | BM65: =BA65*BM148 -> 3.6038748e+08 | BN65: =BB65*BN148 -> 1.003921e+09 | BO65: =BC65*BO148 -> 1.1865668e+09 | BP65: =BD65*BP148 -> 8.5471176e+08 | BQ65: =SUM(BK65:BP65) -> 5.7032429e+09 | BR65: =BI65+BJ65+BQ65 -> 1.5584169e+10 | BU65: =BI65*BU148 -> 9.8809263e+09 | BV65: =BJ65*BV148 -> 0 | BW65: =BK65*BW148 -> 34843226 | BX65: =BL65*BX148 -> 2.2628127e+09 | BY65: =BM65*BY148 -> 3.6038748e+08 | BZ65: =BN65*BZ148 -> 1.003921e+09 | CA65: =BO65*CA148 -> 1.1865668e+09 | CB65: =BP65*CB148 -> 8.5471176e+08 | CC65: =SUM(BW65:CB65) -> 5.7032429e+09 | CD65: =BU65+BV65+CC65 -> 1.5584169e+10 | CE65: =CD65=BR65 -> TRUE | CG65: =BU65*CG148 -> 9.8809263e+09 | CH65: =BV65*CH148 -> 0 | CI65: =BW65*CI148 -> 34843226 | CJ65: =BX65*CJ148 -> 2.2628127e+09 | CK65: =BY65*CK148 -> 3.6038748e+08 | CL65: =BZ65*CL148 -> 1.003921e+09 | CM65: =CA65*CM148 -> 1.1865668e+09 | CN65: =CB65*CN148 -> 8.5471176e+08 | CO65: =SUM(CI65:CN65) -> 5.7032429e+09 | CP65: =CG65+CH65+CO65 -> 1.5584169e+10 | CS65: =CG65*CS148 -> 9.8809263e+09 | CT65: =CH65*CT148 -> 0 | CU65: =CI65*CU148 -> 34843226 | CV65: =CJ65*CV148 -> 2.2628127e+09 | CW65: =CK65*CW148 -> 3.6038748e+08 | CX65: =CL65*CX148 -> 1.003921e+09 | CY65: =CM65*CY148 -> 1.1865668e+09 | CZ65: =CN65*CZ148 -> 8.5471176e+08 | DA65: =SUM(CU65:CZ65) -> 5.7032429e+09 | DB65: =CS65+CT65+DA65 -> 1.5584169e+10 | DE65: =CS65*DE148 -> 9.8809263e+09 | DF65: =CT65*DF148 -> 0 | DG65: =CU65*DG148 -> 34843226 | DH65: =CV65*DH148 -> 2.2628127e+09 | DI65: =CW65*DI148 -> 3.6038748e+08 | DJ65: =CX65*DJ148 -> 1.003921e+09 | DK65: =CY65*DK148 -> 1.1865668e+09 | DL65: =CZ65*DL148 -> 8.5471176e+08 | DM65: =SUM(DG65:DL65) -> 5.7032429e+09 | DN65: =DE65+DF65+DM65 -> 1.5584169e+10 | DQ65: =DE65*DQ148 -> 9.8809263e+09 | DR65: =DF65*DR148 -> 0 | DS65: =DG65*DS148 -> 34843226 | DT65: =DH65*DT148 -> 2.2628127e+09 | DU65: =DI65*DU148 -> 3.6038748e+08 | DV65: =DJ65*DV148 -> 1.003921e+09 | DW65: =DK65*DW148 -> 1.1865668e+09 | DX65: =DL65*DX148 -> 8.5471176e+08 | DY65: =SUM(DS65:DX65) -> 5.7032429e+09 | DZ65: =DQ65+DR65+DY65 -> 1.5584169e+10 | EC65: =DQ65*EC148 -> 9.8809263e+09 | ED65: =DR65*ED148 -> 0 | EE65: =DS65*EE148 -> 34843226 | EF65: =DT65*EF148 -> 2.2628127e+09 | EG65: =DU65*EG148 -> 3.6038748e+08 | EH65: =DV65*EH148 -> 1.003921e+09 | EI65: =DW65*EI148 -> 1.1865668e+09 | EJ65: =DX65*EJ148 -> 8.5471176e+08 | EK65: =SUM(EE65:EJ65) -> 5.7032429e+09 | EL65: =EC65+ED65+EK65 -> 1.5584169e+10
A66: Clôture Per. | B66: =B45-B47*0 -> 0 | C66: =C45-C47*0 -> 0 | D66: =D45-D47*0 -> 0 | E66: =E45-E47*0 -> 0 | F66: =F45-F47*0 -> 0 | G66: =G45-G47*0 -> 0 | H66: =H45-H47*0 -> 0 | I66: =I45-I47*0 -> 0 | J66: =SUM(D66:I66) -> 0 | K66: =B66+C66+J66 -> 0 | M66: =M45-M47*0 -> 0 | N66: =N45-N47*0 -> 0 | O66: =O45-O47*0 -> 0 | P66: =P45-P47*0 -> 0 | Q66: =Q45-Q47*0 -> 0 | R66: =R45-R47*0 -> 0 | S66: =S45-S47*0 -> 0 | T66: =T45-T47*0 -> 0 | U66: =SUM(O66:T66) -> 0 | V66: =M66+N66+U66 -> 0 | W66: =V66=K66 -> TRUE | Y66: =M66 -> 0 | Z66: =N66 -> 0 | AA66: =O66 -> 0 | AB66: =P66 -> 0 | AC66: =Q66 -> 0 | AD66: =R66 -> 0 | AE66: =S66 -> 0 | AF66: =T66 -> 0 | AG66: =SUM(AA66:AF66) -> 0 | AH66: =Y66+Z66+AG66 -> 0 | AI66: =AH66=V66 -> TRUE | AK66: =AK45-AK47*0 -> 0 | AL66: =AL45-AL47*0 -> 0 | AM66: =AM45-AM47*0 -> 0 | AN66: =AN45-AN47*0 -> 0 | AO66: =AO45-AO47*0 -> 0 | AP66: =AP45-AP47*0 -> 0 | AQ66: =AQ45-AQ47*0 -> 0 | AR66: =AR45-AR47*0 -> 0 | AS66: =SUM(AM66:AR66) -> 0 | AT66: =AK66+AL66+AS66 -> 0 | AU66: =AT66=AH66 -> TRUE | AW66: =AW45-AW47*0 -> 0 | AX66: =AX45-AX47*0 -> 0 | AY66: =AY45-AY47*0 -> 0 | AZ66: =AZ45-AZ47*0 -> 0 | BA66: =BA45-BA47*0 -> 0 | BB66: =BB45-BB47*0 -> 0 | BC66: =BC45-BC47*0 -> 0 | BD66: =BD45-BD47*0 -> 0 | BE66: =SUM(AY66:BD66) -> 0 | BF66: =AW66+AX66+BE66 -> 0 | BG66: =BF66=AT66 -> TRUE | BI66: =BI45-BI47*0 -> 0 | BJ66: =BJ45-BJ47*0 -> 0 | BK66: =BK45-BK47*0 -> 0 | BL66: =BL45-BL47*0 -> 0 | BM66: =BM45-BM47*0 -> 0 | BN66: =BN45-BN47*0 -> 0 | BO66: =BO45-BO47*0 -> 0 | BP66: =BP45-BP47*0 -> 0 | BQ66: =SUM(BK66:BP66) -> 0 | BR66: =BI66+BJ66+BQ66 -> 0 | BU66: =BU45-BU47*0 -> 0 | BV66: =BV45-BV47*0 -> 0 | BW66: =BW45-BW47*0 -> 0 | BX66: =BX45-BX47*0 -> 0 | BY66: =BY45-BY47*0 -> 0 | BZ66: =BZ45-BZ47*0 -> 0 | CA66: =CA45-CA47*0 -> 0 | CB66: =CB45-CB47*0 -> 0 | CC66: =SUM(BW66:CB66) -> 0 | CD66: =BU66+BV66+CC66 -> 0 | CE66: =CD66=BR66 -> TRUE | CG66: =CG45-CG47*0 -> 0 | CH66: =CH45-CH47*0 -> 0 | CI66: =CI45-CI47*0 -> 0 | CJ66: =CJ45-CJ47*0 -> 0 | CK66: =CK45-CK47*0 -> 0 | CL66: =CL45-CL47*0 -> 0 | CM66: =CM45-CM47*0 -> 0 | CN66: =CN45-CN47*0 -> 0 | CO66: =SUM(CI66:CN66) -> 0 | CP66: =CG66+CH66+CO66 -> 0 | CS66: =CS45-CS47*0 -> 0 | CT66: =CT45-CT47*0 -> 0 | CU66: =CU45-CU47*0 -> 0 | CV66: =CV45-CV47*0 -> 0 | CW66: =CW45-CW47*0 -> 0 | CX66: =CX45-CX47*0 -> 0 | CY66: =CY45-CY47*0 -> 0 | CZ66: =CZ45-CZ47*0 -> 0 | DA66: =SUM(CU66:CZ66) -> 0 | DB66: =CS66+CT66+DA66 -> 0 | DE66: =DE45-DE47*0 -> 0 | DF66: =DF45-DF47*0 -> 0 | DG66: =DG45-DG47*0 -> 0 | DH66: =DH45-DH47*0 -> 0 | DI66: =DI45-DI47*0 -> 0 | DJ66: =DJ45-DJ47*0 -> 0 | DK66: =DK45-DK47*0 -> 0 | DL66: =DL45-DL47*0 -> 0 | DM66: =SUM(DG66:DL66) -> 0 | DN66: =DE66+DF66+DM66 -> 0 | DQ66: =DQ45-DQ47*0 -> 0 | DR66: =DR45-DR47*0 -> 0 | DS66: =DS45-DS47*0 -> 0 | DT66: =DT45-DT47*0 -> 0 | DU66: =DU45-DU47*0 -> 0 | DV66: =DV45-DV47*0 -> 0 | DW66: =DW45-DW47*0 -> 0 | DX66: =DX45-DX47*0 -> 0 | DY66: =SUM(DS66:DX66) -> 0 | DZ66: =DQ66+DR66+DY66 -> 0 | EC66: =EC45-EC47*0 -> 0 | ED66: =ED45-ED47*0 -> 0 | EE66: =EE45-EE47*0 -> 0 | EF66: =EF45-EF47*0 -> 0 | EG66: =EG45-EG47*0 -> 0 | EH66: =EH45-EH47*0 -> 0 | EI66: =EI45-EI47*0 -> 0 | EJ66: =EJ45-EJ47*0 -> 0 | EK66: =SUM(EE66:EJ66) -> 0 | EL66: =EC66+ED66+EK66 -> 0
A67: Clôture Ant. | B67: =B46-B48*0 -> 9.8809263e+09 | C67: =C46-C48*0 -> 0 | D67: =D46-D48*0 -> 34843226 | E67: =E46-E48*0 -> 2.2628127e+09 | F67: =F46-F48*0 -> 3.6038748e+08 | G67: =G46-G48*0 -> 1.003921e+09 | H67: =H46-H48*0 -> 1.1865668e+09 | I67: =I46-I48*0 -> 8.5471176e+08 | J67: =SUM(D67:I67) -> 5.7032429e+09 | K67: =B67+C67+J67 -> 1.5584169e+10 | M67: =M46-M48*0 -> 9.8809263e+09 | N67: =N46-N48*0 -> 0 | O67: =O46-O48*0 -> 34843226 | P67: =P46-P48*0 -> 2.2628127e+09 | Q67: =Q46-Q48*0 -> 3.6038748e+08 | R67: =R46-R48*0 -> 1.003921e+09 | S67: =S46-S48*0 -> 1.1865668e+09 | T67: =T46-T48*0 -> 8.5471176e+08 | U67: =SUM(O67:T67) -> 5.7032429e+09 | V67: =M67+N67+U67 -> 1.5584169e+10 | W67: =V67=K67 -> TRUE | Y67: =M67 -> 9.8809263e+09 | Z67: =N67 -> 0 | AA67: =O67 -> 34843226 | AB67: =P67 -> 2.2628127e+09 | AC67: =Q67 -> 3.6038748e+08 | AD67: =R67 -> 1.003921e+09 | AE67: =S67 -> 1.1865668e+09 | AF67: =T67 -> 8.5471176e+08 | AG67: =SUM(AA67:AF67) -> 5.7032429e+09 | AH67: =Y67+Z67+AG67 -> 1.5584169e+10 | AI67: =AH67=V67 -> TRUE | AK67: =AK46-AK48*0 -> 9.8809263e+09 | AL67: =AL46-AL48*0 -> 0 | AM67: =AM46-AM48*0 -> 34843226 | AN67: =AN46-AN48*0 -> 2.2628127e+09 | AO67: =AO46-AO48*0 -> 3.6038748e+08 | AP67: =AP46-AP48*0 -> 1.003921e+09 | AQ67: =AQ46-AQ48*0 -> 1.1865668e+09 | AR67: =AR46-AR48*0 -> 8.5471176e+08 | AS67: =SUM(AM67:AR67) -> 5.7032429e+09 | AT67: =AK67+AL67+AS67 -> 1.5584169e+10 | AU67: =AT67=AH67 -> TRUE | AW67: =AW46-AW48*0 -> 9.8809263e+09 | AX67: =AX46-AX48*0 -> 0 | AY67: =AY46-AY48*0 -> 34843226 | AZ67: =AZ46-AZ48*0 -> 2.2628127e+09 | BA67: =BA46-BA48*0 -> 3.6038748e+08 | BB67: =BB46-BB48*0 -> 1.003921e+09 | BC67: =BC46-BC48*0 -> 1.1865668e+09 | BD67: =BD46-BD48*0 -> 8.5471176e+08 | BE67: =SUM(AY67:BD67) -> 5.7032429e+09 | BF67: =AW67+AX67+BE67 -> 1.5584169e+10 | BG67: =BF67=AT67 -> TRUE | BI67: =BI46-BI48*0 -> 9.8809263e+09 | BJ67: =BJ46-BJ48*0 -> 0 | BK67: =BK46-BK48*0 -> 34843226 | BL67: =BL46-BL48*0 -> 2.2628127e+09 | BM67: =BM46-BM48*0 -> 3.6038748e+08 | BN67: =BN46-BN48*0 -> 1.003921e+09 | BO67: =BO46-BO48*0 -> 1.1865668e+09 | BP67: =BP46-BP48*0 -> 8.5471176e+08 | BQ67: =SUM(BK67:BP67) -> 5.7032429e+09 | BR67: =BI67+BJ67+BQ67 -> 1.5584169e+10 | BU67: =BU46-BU48*0 -> 9.8809263e+09 | BV67: =BV46-BV48*0 -> 0 | BW67: =BW46-BW48*0 -> 34843226 | BX67: =BX46-BX48*0 -> 2.2628127e+09 | BY67: =BY46-BY48*0 -> 3.6038748e+08 | BZ67: =BZ46-BZ48*0 -> 1.003921e+09 | CA67: =CA46-CA48*0 -> 1.1865668e+09 | CB67: =CB46-CB48*0 -> 8.5471176e+08 | CC67: =SUM(BW67:CB67) -> 5.7032429e+09 | CD67: =BU67+BV67+CC67 -> 1.5584169e+10 | CE67: =CD67=BR67 -> TRUE | CG67: =CG46-CG48*0 -> 9.8809263e+09 | CH67: =CH46-CH48*0 -> 0 | CI67: =CI46-CI48*0 -> 34843226 | CJ67: =CJ46-CJ48*0 -> 2.2628127e+09 | CK67: =CK46-CK48*0 -> 3.6038748e+08 | CL67: =CL46-CL48*0 -> 1.003921e+09 | CM67: =CM46-CM48*0 -> 1.1865668e+09 | CN67: =CN46-CN48*0 -> 8.5471176e+08 | CO67: =SUM(CI67:CN67) -> 5.7032429e+09 | CP67: =CG67+CH67+CO67 -> 1.5584169e+10 | CS67: =CS46-CS48*0 -> 9.8809263e+09 | CT67: =CT46-CT48*0 -> 0 | CU67: =CU46-CU48*0 -> 34843226 | CV67: =CV46-CV48*0 -> 2.2628127e+09 | CW67: =CW46-CW48*0 -> 3.6038748e+08 | CX67: =CX46-CX48*0 -> 1.003921e+09 | CY67: =CY46-CY48*0 -> 1.1865668e+09 | CZ67: =CZ46-CZ48*0 -> 8.5471176e+08 | DA67: =SUM(CU67:CZ67) -> 5.7032429e+09 | DB67: =CS67+CT67+DA67 -> 1.5584169e+10 | DE67: =DE46-DE48*0 -> 9.8809263e+09 | DF67: =DF46-DF48*0 -> 0 | DG67: =DG46-DG48*0 -> 34843226 | DH67: =DH46-DH48*0 -> 2.2628127e+09 | DI67: =DI46-DI48*0 -> 3.6038748e+08 | DJ67: =DJ46-DJ48*0 -> 1.003921e+09 | DK67: =DK46-DK48*0 -> 1.1865668e+09 | DL67: =DL46-DL48*0 -> 8.5471176e+08 | DM67: =SUM(DG67:DL67) -> 5.7032429e+09 | DN67: =DE67+DF67+DM67 -> 1.5584169e+10 | DQ67: =DQ46-DQ48*0 -> 9.8809263e+09 | DR67: =DR46-DR48*0 -> 0 | DS67: =DS46-DS48*0 -> 34843226 | DT67: =DT46-DT48*0 -> 2.2628127e+09 | DU67: =DU46-DU48*0 -> 3.6038748e+08 | DV67: =DV46-DV48*0 -> 1.003921e+09 | DW67: =DW46-DW48*0 -> 1.1865668e+09 | DX67: =DX46-DX48*0 -> 8.5471176e+08 | DY67: =SUM(DS67:DX67) -> 5.7032429e+09 | DZ67: =DQ67+DR67+DY67 -> 1.5584169e+10 | EC67: =EC46-EC48*0 -> 9.8809263e+09 | ED67: =ED46-ED48*0 -> 0 | EE67: =EE46-EE48*0 -> 34843226 | EF67: =EF46-EF48*0 -> 2.2628127e+09 | EG67: =EG46-EG48*0 -> 3.6038748e+08 | EH67: =EH46-EH48*0 -> 1.003921e+09 | EI67: =EI46-EI48*0 -> 1.1865668e+09 | EJ67: =EJ46-EJ48*0 -> 8.5471176e+08 | EK67: =SUM(EE67:EJ67) -> 5.7032429e+09 | EL67: =EC67+ED67+EK67 -> 1.5584169e+10
A68: Variation Per. | B68: =B66 -> 0 | C68: =C66 -> 0 | D68: =D66 -> 0 | E68: =E66 -> 0 | F68: =F66 -> 0 | G68: =G66 -> 0 | H68: =H66 -> 0 | I68: =I66 -> 0 | J68: =SUM(D68:I68) -> 0 | K68: =B68+C68+J68 -> 0 | M68: =M66 -> 0 | N68: =N66 -> 0 | O68: =O66 -> 0 | P68: =P66 -> 0 | Q68: =Q66 -> 0 | R68: =R66 -> 0 | S68: =S66 -> 0 | T68: =T66 -> 0 | U68: =SUM(O68:T68) -> 0 | V68: =M68+N68+U68 -> 0 | Y68: =Y66 -> 0 | Z68: =Z66 -> 0 | AA68: =AA66 -> 0 | AB68: =AB66 -> 0 | AC68: =AC66 -> 0 | AD68: =AD66 -> 0 | AE68: =AE66 -> 0 | AF68: =AF66 -> 0 | AG68: =SUM(AA68:AF68) -> 0 | AH68: =Y68+Z68+AG68 -> 0 | AK68: =AK66 -> 0 | AL68: =AL66 -> 0 | AM68: =AM66 -> 0 | AN68: =AN66 -> 0 | AO68: =AO66 -> 0 | AP68: =AP66 -> 0 | AQ68: =AQ66 -> 0 | AR68: =AR66 -> 0 | AS68: =SUM(AM68:AR68) -> 0 | AT68: =AK68+AL68+AS68 -> 0 | AW68: =AW66 -> 0 | AX68: =AX66 -> 0 | AY68: =AY66 -> 0 | AZ68: =AZ66 -> 0 | BA68: =BA66 -> 0 | BB68: =BB66 -> 0 | BC68: =BC66 -> 0 | BD68: =BD66 -> 0 | BE68: =SUM(AY68:BD68) -> 0 | BF68: =AW68+AX68+BE68 -> 0 | BI68: =BI66 -> 0 | BJ68: =BJ66 -> 0 | BK68: =BK66 -> 0 | BL68: =BL66 -> 0 | BM68: =BM66 -> 0 | BN68: =BN66 -> 0 | BO68: =BO66 -> 0 | BP68: =BP66 -> 0 | BQ68: =SUM(BK68:BP68) -> 0 | BR68: =BI68+BJ68+BQ68 -> 0 | BU68: =BU66 -> 0 | BV68: =BV66 -> 0 | BW68: =BW66 -> 0 | BX68: =BX66 -> 0 | BY68: =BY66 -> 0 | BZ68: =BZ66 -> 0 | CA68: =CA66 -> 0 | CB68: =CB66 -> 0 | CC68: =SUM(BW68:CB68) -> 0 | CD68: =BU68+BV68+CC68 -> 0 | CG68: =CG66 -> 0 | CH68: =CH66 -> 0 | CI68: =CI66 -> 0 | CJ68: =CJ66 -> 0 | CK68: =CK66 -> 0 | CL68: =CL66 -> 0 | CM68: =CM66 -> 0 | CN68: =CN66 -> 0 | CO68: =SUM(CI68:CN68) -> 0 | CP68: =CG68+CH68+CO68 -> 0 | CS68: =CS66 -> 0 | CT68: =CT66 -> 0 | CU68: =CU66 -> 0 | CV68: =CV66 -> 0 | CW68: =CW66 -> 0 | CX68: =CX66 -> 0 | CY68: =CY66 -> 0 | CZ68: =CZ66 -> 0 | DA68: =SUM(CU68:CZ68) -> 0 | DB68: =CS68+CT68+DA68 -> 0 | DE68: =DE66 -> 0 | DF68: =DF66 -> 0 | DG68: =DG66 -> 0 | DH68: =DH66 -> 0 | DI68: =DI66 -> 0 | DJ68: =DJ66 -> 0 | DK68: =DK66 -> 0 | DL68: =DL66 -> 0 | DM68: =SUM(DG68:DL68) -> 0 | DN68: =DE68+DF68+DM68 -> 0 | DQ68: =DQ66 -> 0 | DR68: =DR66 -> 0 | DS68: =DS66 -> 0 | DT68: =DT66 -> 0 | DU68: =DU66 -> 0 | DV68: =DV66 -> 0 | DW68: =DW66 -> 0 | DX68: =DX66 -> 0 | DY68: =SUM(DS68:DX68) -> 0 | DZ68: =DQ68+DR68+DY68 -> 0 | EC68: =EC66 -> 0 | ED68: =ED66 -> 0 | EE68: =EE66 -> 0 | EF68: =EF66 -> 0 | EG68: =EG66 -> 0 | EH68: =EH66 -> 0 | EI68: =EI66 -> 0 | EJ68: =EJ66 -> 0 | EK68: =SUM(EE68:EJ68) -> 0 | EL68: =EC68+ED68+EK68 -> 0
A69: Variation Ant. | B69: =B67-B65 -> 0 | C69: =C67-C65 -> 0 | D69: =D67-D65 -> 0 | E69: =E67-E65 -> 4.7683716e-06 | F69: =F67-F65 -> 0 | G69: =G67-G65 -> 0 | H69: =H67-H65 -> 0 | I69: =I67-I65 -> 0 | J69: =SUM(D69:I69) -> 4.7683716e-06 | K69: =B69+C69+J69 -> 4.7683716e-06 | M69: =M67-M65 -> 0 | N69: =N67-N65 -> 0 | O69: =O67-O65 -> 0 | P69: =P67-P65 -> 4.7683716e-06 | Q69: =Q67-Q65 -> 0 | R69: =R67-R65 -> 0 | S69: =S67-S65 -> 0 | T69: =T67-T65 -> 0 | U69: =SUM(O69:T69) -> 4.7683716e-06 | V69: =M69+N69+U69 -> 4.7683716e-06 | Y69: =Y67-Y65 -> 0 | Z69: =Z67-Z65 -> 0 | AA69: =AA67-AA65 -> 0 | AB69: =AB67-AB65 -> 4.7683716e-06 | AC69: =AC67-AC65 -> 0 | AD69: =AD67-AD65 -> 0 | AE69: =AE67-AE65 -> 0 | AF69: =AF67-AF65 -> 0 | AG69: =SUM(AA69:AF69) -> 4.7683716e-06 | AH69: =Y69+Z69+AG69 -> 4.7683716e-06 | AK69: =AK67-AK65 -> 0 | AL69: =AL67-AL65 -> 0 | AM69: =AM67-AM65 -> 0 | AN69: =AN67-AN65 -> 4.7683716e-06 | AO69: =AO67-AO65 -> 0 | AP69: =AP67-AP65 -> 0 | AQ69: =AQ67-AQ65 -> 0 | AR69: =AR67-AR65 -> 0 | AS69: =SUM(AM69:AR69) -> 4.7683716e-06 | AT69: =AK69+AL69+AS69 -> 4.7683716e-06 | AW69: =AW67-AW65 -> 0 | AX69: =AX67-AX65 -> 0 | AY69: =AY67-AY65 -> 0 | AZ69: =AZ67-AZ65 -> 4.7683716e-06 | BA69: =BA67-BA65 -> 0 | BB69: =BB67-BB65 -> 0 | BC69: =BC67-BC65 -> 0 | BD69: =BD67-BD65 -> 0 | BE69: =SUM(AY69:BD69) -> 4.7683716e-06 | BF69: =AW69+AX69+BE69 -> 4.7683716e-06 | BI69: =BI67-BI65 -> 0 | BJ69: =BJ67-BJ65 -> 0 | BK69: =BK67-BK65 -> 0 | BL69: =BL67-BL65 -> 4.7683716e-06 | BM69: =BM67-BM65 -> 0 | BN69: =BN67-BN65 -> 0 | BO69: =BO67-BO65 -> 0 | BP69: =BP67-BP65 -> 0 | BQ69: =SUM(BK69:BP69) -> 4.7683716e-06 | BR69: =BI69+BJ69+BQ69 -> 4.7683716e-06 | BU69: =BU67-BU65 -> 0 | BV69: =BV67-BV65 -> 0 | BW69: =BW67-BW65 -> 0 | BX69: =BX67-BX65 -> 4.7683716e-06 | BY69: =BY67-BY65 -> 0 | BZ69: =BZ67-BZ65 -> 0 | CA69: =CA67-CA65 -> 0 | CB69: =CB67-CB65 -> 0 | CC69: =SUM(BW69:CB69) -> 4.7683716e-06 | CD69: =BU69+BV69+CC69 -> 4.7683716e-06 | CG69: =CG67-CG65 -> 0 | CH69: =CH67-CH65 -> 0 | CI69: =CI67-CI65 -> 0 | CJ69: =CJ67-CJ65 -> 4.7683716e-06 | CK69: =CK67-CK65 -> 0 | CL69: =CL67-CL65 -> 0 | CM69: =CM67-CM65 -> 0 | CN69: =CN67-CN65 -> 0 | CO69: =SUM(CI69:CN69) -> 4.7683716e-06 | CP69: =CG69+CH69+CO69 -> 4.7683716e-06 | CS69: =CS67-CS65 -> 0 | CT69: =CT67-CT65 -> 0 | CU69: =CU67-CU65 -> 0 | CV69: =CV67-CV65 -> 4.7683716e-06 | CW69: =CW67-CW65 -> 0 | CX69: =CX67-CX65 -> 0 | CY69: =CY67-CY65 -> 0 | CZ69: =CZ67-CZ65 -> 0 | DA69: =SUM(CU69:CZ69) -> 4.7683716e-06 | DB69: =CS69+CT69+DA69 -> 4.7683716e-06 | DE69: =DE67-DE65 -> 0 | DF69: =DF67-DF65 -> 0 | DG69: =DG67-DG65 -> 0 | DH69: =DH67-DH65 -> 4.7683716e-06 | DI69: =DI67-DI65 -> 0 | DJ69: =DJ67-DJ65 -> 0 | DK69: =DK67-DK65 -> 0 | DL69: =DL67-DL65 -> 0 | DM69: =SUM(DG69:DL69) -> 4.7683716e-06 | DN69: =DE69+DF69+DM69 -> 4.7683716e-06 | DQ69: =DQ67-DQ65 -> 0 | DR69: =DR67-DR65 -> 0 | DS69: =DS67-DS65 -> 0 | DT69: =DT67-DT65 -> 4.7683716e-06 | DU69: =DU67-DU65 -> 0 | DV69: =DV67-DV65 -> 0 | DW69: =DW67-DW65 -> 0 | DX69: =DX67-DX65 -> 0 | DY69: =SUM(DS69:DX69) -> 4.7683716e-06 | DZ69: =DQ69+DR69+DY69 -> 4.7683716e-06 | EC69: =EC67-EC65 -> 0 | ED69: =ED67-ED65 -> 0 | EE69: =EE67-EE65 -> 0 | EF69: =EF67-EF65 -> 4.7683716e-06 | EG69: =EG67-EG65 -> 0 | EH69: =EH67-EH65 -> 0 | EI69: =EI67-EI65 -> 0 | EJ69: =EJ67-EJ65 -> 0 | EK69: =SUM(EE69:EJ69) -> 4.7683716e-06 | EL69: =EC69+ED69+EK69 -> 4.7683716e-06
A71: SAP hors chargement | M71: =M66+M67 -> 9.8809263e+09 | N71: =N66+N67 -> 0 | O71: =O66+O67 -> 34843226 | P71: =P66+P67 -> 2.2628127e+09 | Q71: =Q66+Q67 -> 3.6038748e+08 | R71: =R66+R67 -> 1.003921e+09 | S71: =S66+S67 -> 1.1865668e+09 | T71: =T66+T67 -> 8.5471176e+08
A72: ULAE Ouverture | J72: =SUM(D72:I72) -> 0 | K72: =B72+C72+J72 -> 0 | U72: =SUM(O72:T72) -> 0 | V72: =M72+N72+U72 -> 0 | AG72: =SUM(AA72:AF72) -> 0 | AH72: =Y72+Z72+AG72 -> 0 | AS72: =SUM(AM72:AR72) -> 0 | AT72: =AK72+AL72+AS72 -> 0 | BE72: =SUM(AY72:BD72) -> 0 | BF72: =AW72+AX72+BE72 -> 0 | BQ72: =SUM(BK72:BP72) -> 0 | BR72: =BI72+BJ72+BQ72 -> 0 | CC72: =SUM(BW72:CB72) -> 0 | CD72: =BU72+BV72+CC72 -> 0 | CO72: =SUM(CI72:CN72) -> 0 | CP72: =CG72+CH72+CO72 -> 0 | DA72: =SUM(CU72:CZ72) -> 0 | DB72: =CS72+CT72+DA72 -> 0 | DM72: =SUM(DG72:DL72) -> 0 | DN72: =DE72+DF72+DM72 -> 0 | DY72: =SUM(DS72:DX72) -> 0 | DZ72: =DQ72+DR72+DY72 -> 0 | EK72: =SUM(EE72:EJ72) -> 0 | EL72: =EC72+ED72+EK72 -> 0
A73: ULAE Clôture | B73: =B57 -> 0 | C73: =C57 -> 0 | D73: =D57 -> 0 | E73: =E57 -> 0 | F73: =F57 -> 0 | G73: =G57 -> 0 | H73: =H57 -> 0 | I73: =I57 -> 0 | J73: =SUM(D73:I73) -> 0 | K73: =B73+C73+J73 -> 0 | M73: =M57 -> 0 | N73: =N57 -> 0 | O73: =O57 -> 0 | P73: =P57 -> 0 | Q73: =Q57 -> 0 | R73: =R57 -> 0 | S73: =S57 -> 0 | T73: =T57 -> 0 | U73: =SUM(O73:T73) -> 0 | V73: =M73+N73+U73 -> 0 | Y73: =Y57 -> 0 | Z73: =Z57 -> 0 | AA73: =AA57 -> 0 | AB73: =AB57 -> 0 | AC73: =AC57 -> 0 | AD73: =AD57 -> 0 | AE73: =AE57 -> 0 | AF73: =AF57 -> 0 | AG73: =SUM(AA73:AF73) -> 0 | AH73: =Y73+Z73+AG73 -> 0 | AK73: =AK57 -> 0 | AL73: =AL57 -> 0 | AM73: =AM57 -> 0 | AN73: =AN57 -> 0 | AO73: =AO57 -> 0 | AP73: =AP57 -> 0 | AQ73: =AQ57 -> 0 | AR73: =AR57 -> 0 | AS73: =SUM(AM73:AR73) -> 0 | AT73: =AK73+AL73+AS73 -> 0 | AW73: =AW57 -> 0 | AX73: =AX57 -> 0 | AY73: =AY57 -> 0 | AZ73: =AZ57 -> 0 | BA73: =BA57 -> 0 | BB73: =BB57 -> 0 | BC73: =BC57 -> 0 | BD73: =BD57 -> 0 | BE73: =SUM(AY73:BD73) -> 0 | BF73: =AW73+AX73+BE73 -> 0 | BI73: =BI57 -> 0 | BJ73: =BJ57 -> 0 | BK73: =BK57 -> 0 | BL73: =BL57 -> 0 | BM73: =BM57 -> 0 | BN73: =BN57 -> 0 | BO73: =BO57 -> 0 | BP73: =BP57 -> 0 | BQ73: =SUM(BK73:BP73) -> 0 | BR73: =BI73+BJ73+BQ73 -> 0 | BU73: =BU57 -> 0 | BV73: =BV57 -> 0 | BW73: =BW57 -> 0 | BX73: =BX57 -> 0 | BY73: =BY57 -> 0 | BZ73: =BZ57 -> 0 | CA73: =CA57 -> 0 | CB73: =CB57 -> 0 | CC73: =SUM(BW73:CB73) -> 0 | CD73: =BU73+BV73+CC73 -> 0 | CG73: =CG57 -> 0 | CH73: =CH57 -> 0 | CI73: =CI57 -> 0 | CJ73: =CJ57 -> 0 | CK73: =CK57 -> 0 | CL73: =CL57 -> 0 | CM73: =CM57 -> 0 | CN73: =CN57 -> 0 | CO73: =SUM(CI73:CN73) -> 0 | CP73: =CG73+CH73+CO73 -> 0 | CS73: =CS57 -> 0 | CT73: =CT57 -> 0 | CU73: =CU57 -> 0 | CV73: =CV57 -> 0 | CW73: =CW57 -> 0 | CX73: =CX57 -> 0 | CY73: =CY57 -> 0 | CZ73: =CZ57 -> 0 | DA73: =SUM(CU73:CZ73) -> 0 | DB73: =CS73+CT73+DA73 -> 0 | DE73: =DE57 -> 0 | DF73: =DF57 -> 0 | DG73: =DG57 -> 0 | DH73: =DH57 -> 0 | DI73: =DI57 -> 0 | DJ73: =DJ57 -> 0 | DK73: =DK57 -> 0 | DL73: =DL57 -> 0 | DM73: =SUM(DG73:DL73) -> 0 | DN73: =DE73+DF73+DM73 -> 0 | DQ73: =DQ57 -> 0 | DR73: =DR57 -> 0 | DS73: =DS57 -> 0 | DT73: =DT57 -> 0 | DU73: =DU57 -> 0 | DV73: =DV57 -> 0 | DW73: =DW57 -> 0 | DX73: =DX57 -> 0 | DY73: =SUM(DS73:DX73) -> 0 | DZ73: =DQ73+DR73+DY73 -> 0 | EC73: =EC57 -> 0 | ED73: =ED57 -> 0 | EE73: =EE57 -> 0 | EF73: =EF57 -> 0 | EG73: =EG57 -> 0 | EH73: =EH57 -> 0 | EI73: =EI57 -> 0 | EJ73: =EJ57 -> 0 | EK73: =SUM(EE73:EJ73) -> 0 | EL73: =EC73+ED73+EK73 -> 0
A74: Variation Per. | B74: =B73-B72 -> 0 | C74: =C73-C72 -> 0 | D74: =D73-D72 -> 0 | E74: =E73-E72 -> 0 | F74: =F73-F72 -> 0 | G74: =G73-G72 -> 0 | H74: =H73-H72 -> 0 | I74: =I73-I72 -> 0 | J74: =SUM(D74:I74) -> 0 | K74: =B74+C74+J74 -> 0 | M74: =M73-M72 -> 0 | N74: =N73-N72 -> 0 | O74: =O73-O72 -> 0 | P74: =P73-P72 -> 0 | Q74: =Q73-Q72 -> 0 | R74: =R73-R72 -> 0 | S74: =S73-S72 -> 0 | T74: =T73-T72 -> 0 | U74: =SUM(O74:T74) -> 0 | V74: =M74+N74+U74 -> 0 | Y74: =Y73-Y72 -> 0 | Z74: =Z73-Z72 -> 0 | AA74: =AA73-AA72 -> 0 | AB74: =AB73-AB72 -> 0 | AC74: =AC73-AC72 -> 0 | AD74: =AD73-AD72 -> 0 | AE74: =AE73-AE72 -> 0 | AF74: =AF73-AF72 -> 0 | AG74: =SUM(AA74:AF74) -> 0 | AH74: =Y74+Z74+AG74 -> 0 | AK74: =AK73-AK72 -> 0 | AL74: =AL73-AL72 -> 0 | AM74: =AM73-AM72 -> 0 | AN74: =AN73-AN72 -> 0 | AO74: =AO73-AO72 -> 0 | AP74: =AP73-AP72 -> 0 | AQ74: =AQ73-AQ72 -> 0 | AR74: =AR73-AR72 -> 0 | AS74: =SUM(AM74:AR74) -> 0 | AT74: =AK74+AL74+AS74 -> 0 | AW74: =AW73-AW72 -> 0 | AX74: =AX73-AX72 -> 0 | AY74: =AY73-AY72 -> 0 | AZ74: =AZ73-AZ72 -> 0 | BA74: =BA73-BA72 -> 0 | BB74: =BB73-BB72 -> 0 | BC74: =BC73-BC72 -> 0 | BD74: =BD73-BD72 -> 0 | BE74: =SUM(AY74:BD74) -> 0 | BF74: =AW74+AX74+BE74 -> 0 | BI74: =BI73-BI72 -> 0 | BJ74: =BJ73-BJ72 -> 0 | BK74: =BK73-BK72 -> 0 | BL74: =BL73-BL72 -> 0 | BM74: =BM73-BM72 -> 0 | BN74: =BN73-BN72 -> 0 | BO74: =BO73-BO72 -> 0 | BP74: =BP73-BP72 -> 0 | BQ74: =SUM(BK74:BP74) -> 0 | BR74: =BI74+BJ74+BQ74 -> 0 | BU74: =BU73-BU72 -> 0 | BV74: =BV73-BV72 -> 0 | BW74: =BW73-BW72 -> 0 | BX74: =BX73-BX72 -> 0 | BY74: =BY73-BY72 -> 0 | BZ74: =BZ73-BZ72 -> 0 | CA74: =CA73-CA72 -> 0 | CB74: =CB73-CB72 -> 0 | CC74: =SUM(BW74:CB74) -> 0 | CD74: =BU74+BV74+CC74 -> 0 | CG74: =CG73-CG72 -> 0 | CH74: =CH73-CH72 -> 0 | CI74: =CI73-CI72 -> 0 | CJ74: =CJ73-CJ72 -> 0 | CK74: =CK73-CK72 -> 0 | CL74: =CL73-CL72 -> 0 | CM74: =CM73-CM72 -> 0 | CN74: =CN73-CN72 -> 0 | CO74: =SUM(CI74:CN74) -> 0 | CP74: =CG74+CH74+CO74 -> 0 | CS74: =CS73-CS72 -> 0 | CT74: =CT73-CT72 -> 0 | CU74: =CU73-CU72 -> 0 | CV74: =CV73-CV72 -> 0 | CW74: =CW73-CW72 -> 0 | CX74: =CX73-CX72 -> 0 | CY74: =CY73-CY72 -> 0 | CZ74: =CZ73-CZ72 -> 0 | DA74: =SUM(CU74:CZ74) -> 0 | DB74: =CS74+CT74+DA74 -> 0 | DE74: =DE73-DE72 -> 0 | DF74: =DF73-DF72 -> 0 | DG74: =DG73-DG72 -> 0 | DH74: =DH73-DH72 -> 0 | DI74: =DI73-DI72 -> 0 | DJ74: =DJ73-DJ72 -> 0 | DK74: =DK73-DK72 -> 0 | DL74: =DL73-DL72 -> 0 | DM74: =SUM(DG74:DL74) -> 0 | DN74: =DE74+DF74+DM74 -> 0 | DQ74: =DQ73-DQ72 -> 0 | DR74: =DR73-DR72 -> 0 | DS74: =DS73-DS72 -> 0 | DT74: =DT73-DT72 -> 0 | DU74: =DU73-DU72 -> 0 | DV74: =DV73-DV72 -> 0 | DW74: =DW73-DW72 -> 0 | DX74: =DX73-DX72 -> 0 | DY74: =SUM(DS74:DX74) -> 0 | DZ74: =DQ74+DR74+DY74 -> 0 | EC74: =EC73-EC72 -> 0 | ED74: =ED73-ED72 -> 0 | EE74: =EE73-EE72 -> 0 | EF74: =EF73-EF72 -> 0 | EG74: =EG73-EG72 -> 0 | EH74: =EH73-EH72 -> 0 | EI74: =EI73-EI72 -> 0 | EJ74: =EJ73-EJ72 -> 0 | EK74: =SUM(EE74:EJ74) -> 0 | EL74: =EC74+ED74+EK74 -> 0
A75: Chargement SAP
